Workbook

Sheet Data
A1: Project Name | B1: Supplier | C1: Product | D1: Quantity | E1: Unit Price | F1: Total | G1: Start Date | H1: Project Duration (Weeks) | I1: Deadline | J1: Payment Status | K1: Status | L1: DateOK | M1: MatchAll | N1: MatchExclProduct | O1: MatchExclSupplier | P1: MatchExclStatus | Q1: MatchExclProject | R1: MatchExclPayment | S1: RowIdx | T1: ProjectList | U1: SupplierList | V1: ProductList
A2: FRA | B2: Wireless dynamics | C2: TC 56 handheld | D2: 2 | E2: 2 | F2: =IF(E2="","",D2*E2) -> 4 | G2: 46144 | H2: 1 | I2: =IF(OR(G2="",H2=""),"",G2+H2*7) -> 46151 | J2: Not Paid | K2: Completed | L2: =IF(A2="","",IF(OR(G2="",AND(G2>=Dashboard!$C$18,G2<=Dashboard!$C$19)),1,0)) -> 1 | M2: =IF(AND(L2=1,OR(Dashboard!$C$13="All",A2=Dashboard!$C$13),OR(Dashboard!$C$14="All",B2=Dashboard!$C$14),OR(Dashboard!$C$15="All",C2=Dashboard!$C$15),OR(Dashboard!$C$16="All",K2=Dashboard!$C$16),OR(Dashboard!$C$17="All",J2=Dashboard!$C$17)),1,0) -> 1 | N2: =IF(AND(L2=1,OR(Dashboard!$C$13="All",A2=Dashboard!$C$13),OR(Dashboard!$C$14="All",B2=Dashboard!$C$14),OR(Dashboard!$C$16="All",K2=Dashboard!$C$16),OR(Dashboard!$C$17="All",J2=Dashboard!$C$17)),1,0) -> 1 | O2: =IF(AND(L2=1,OR(Dashboard!$C$13="All",A2=Dashboard!$C$13),OR(Dashboard!$C$15="All",C2=Dashboard!$C$15),OR(Dashboard!$C$16="All",K2=Dashboard!$C$16),OR(Dashboard!$C$17="All",J2=Dashboard!$C$17)),1,0) -> 1 | P2: =IF(AND(L2=1,OR(Dashboard!$C$13="All",A2=Dashboard!$C$13),OR(Dashboard!$C$14="All",B2=Dashboard!$C$14),OR(Dashboard!$C$15="All",C2=Dashboard!$C$15),OR(Dashboard!$C$17="All",J2=Dashboard!$C$17)),1,0) -> 1 | Q2: =IF(AND(L2=1,OR(Dashboard!$C$14="All",B2=Dashboard!$C$14),OR(Dashboard!$C$15="All",C2=Dashboard!$C$15),OR(Dashboard!$C$16="All",K2=Dashboard!$C$16),OR(Dashboard!$C$17="All",J2=Dashboard!$C$17)),1,0) -> 1 | R2: =IF(AND(L2=1,OR(Dashboard!$C$13="All",A2=Dashboard!$C$13),OR(Dashboard!$C$14="All",B2=Dashboard!$C$14),OR(Dashboard!$C$15="All",C2=Dashboard!$C$15),OR(Dashboard!$C$16="All",K2=Dashboard!$C$16)),1,0) -> 1 | S2: =IF(M2=1,ROW()-1,"") -> 1 | T2: All | U2: All | V2: All
A3: FRA | B3: Fusion | C3: [5118.001.01] ID MAX.U500i-EU Compact UHF Access Control Re | D3: 2 | E3: 5 | F3: =IF(E3="","",D3*E3) -> 10 | G3: 46145 | H3: 2 | I3: =IF(OR(G3="",H3=""),"",G3+H3*7) -> 46159 | J3: Advance Payment | K3: Pending | L3: =IF(A3="","",IF(OR(G3="",AND(G3>=Dashboard!$C$18,G3<=Dashboard!$C$19)),1,0)) -> 1 | M3: =IF(AND(L3=1,OR(Dashboard!$C$13="All",A3=Dashboard!$C$13),OR(Dashboard!$C$14="All",B3=Dashboard!$C$14),OR(Dashboard!$C$15="All",C3=Dashboard!$C$15),OR(Dashboard!$C$16="All",K3=Dashboard!$C$16),OR(Dashboard!$C$17="All",J3=Dashboard!$C$17)),1,0) -> 1 | N3: =IF(AND(L3=1,OR(Dashboard!$C$13="All",A3=Dashboard!$C$13),OR(Dashboard!$C$14="All",B3=Dashboard!$C$14),OR(Dashboard!$C$16="All",K3=Dashboard!$C$16),OR(Dashboard!$C$17="All",J3=Dashboard!$C$17)),1,0) -> 1 | O3: =IF(AND(L3=1,OR(Dashboard!$C$13="All",A3=Dashboard!$C$13),OR(Dashboard!$C$15="All",C3=Dashboard!$C$15),OR(Dashboard!$C$16="All",K3=Dashboard!$C$16),OR(Dashboard!$C$17="All",J3=Dashboard!$C$17)),1,0) -> 1 | P3: =IF(AND(L3=1,OR(Dashboard!$C$13="All",A3=Dashboard!$C$13),OR(Dashboard!$C$14="All",B3=Dashboard!$C$14),OR(Dashboard!$C$15="All",C3=Dashboard!$C$15),OR(Dashboard!$C$17="All",J3=Dashboard!$C$17)),1,0) -> 1 | Q3: =IF(AND(L3=1,OR(Dashboard!$C$14="All",B3=Dashboard!$C$14),OR(Dashboard!$C$15="All",C3=Dashboard!$C$15),OR(Dashboard!$C$16="All",K3=Dashboard!$C$16),OR(Dashboard!$C$17="All",J3=Dashboard!$C$17)),1,0) -> 1 | R3: =IF(AND(L3=1,OR(Dashboard!$C$13="All",A3=Dashboard!$C$13),OR(Dashboard!$C$14="All",B3=Dashboard!$C$14),OR(Dashboard!$C$15="All",C3=Dashboard!$C$15),OR(Dashboard!$C$16="All",K3=Dashboard!$C$16)),1,0) -> 1 | S3: =IF(M3=1,ROW()-1,"") -> 2 | T3: FRA | U3: ATC | V3: MET QR Code Scanner
A4: FRA | B4: Metalcraft | C4: EU Universal tags | D4: 1000 | E4: 6 | F4: =IF(E4="","",D4*E4) -> 6000 | G4: 46146 | H4: 4 | I4: =IF(OR(G4="",H4=""),"",G4+H4*7) -> 46174 | J4: Fully Paid | K4: In Progress | L4: =IF(A4="","",IF(OR(G4="",AND(G4>=Dashboard!$C$18,G4<=Dashboard!$C$19)),1,0)) -> 1 | M4: =IF(AND(L4=1,OR(Dashboard!$C$13="All",A4=Dashboard!$C$13),OR(Dashboard!$C$14="All",B4=Dashboard!$C$14),OR(Dashboard!$C$15="All",C4=Dashboard!$C$15),OR(Dashboard!$C$16="All",K4=Dashboard!$C$16),OR(Dashboard!$C$17="All",J4=Dashboard!$C$17)),1,0) -> 1 | N4: =IF(AND(L4=1,OR(Dashboard!$C$13="All",A4=Dashboard!$C$13),OR(Dashboard!$C$14="All",B4=Dashboard!$C$14),OR(Dashboard!$C$16="All",K4=Dashboard!$C$16),OR(Dashboard!$C$17="All",J4=Dashboard!$C$17)),1,0) -> 1 | O4: =IF(AND(L4=1,OR(Dashboard!$C$13="All",A4=Dashboard!$C$13),OR(Dashboard!$C$15="All",C4=Dashboard!$C$15),OR(Dashboard!$C$16="All",K4=Dashboard!$C$16),OR(Dashboard!$C$17="All",J4=Dashboard!$C$17)),1,0) -> 1 | P4: =IF(AND(L4=1,OR(Dashboard!$C$13="All",A4=Dashboard!$C$13),OR(Dashboard!$C$14="All",B4=Dashboard!$C$14),OR(Dashboard!$C$15="All",C4=Dashboard!$C$15),OR(Dashboard!$C$17="All",J4=Dashboard!$C$17)),1,0) -> 1 | Q4: =IF(AND(L4=1,OR(Dashboard!$C$14="All",B4=Dashboard!$C$14),OR(Dashboard!$C$15="All",C4=Dashboard!$C$15),OR(Dashboard!$C$16="All",K4=Dashboard!$C$16),OR(Dashboard!$C$17="All",J4=Dashboard!$C$17)),1,0) -> 1 | R4: =IF(AND(L4=1,OR(Dashboard!$C$13="All",A4=Dashboard!$C$13),OR(Dashboard!$C$14="All",B4=Dashboard!$C$14),OR(Dashboard!$C$15="All",C4=Dashboard!$C$15),OR(Dashboard!$C$16="All",K4=Dashboard!$C$16)),1,0) -> 1 | S4: =IF(M4=1,ROW()-1,"") -> 3 | T4: El Kasr | U4: ATID | V4: (SBH01) Barrier Beam Connection piece Flange
A5: FRA | B5: Dipole | C5: Dogbone | D5: 3500 | E5: 7 | F5: =IF(E5="","",D5*E5) -> 24500 | G5: 46147 | H5: 6 | I5: =IF(OR(G5="",H5=""),"",G5+H5*7) -> 46189 | J5: Advance Payment | K5: Completed | L5: =IF(A5="","",IF(OR(G5="",AND(G5>=Dashboard!$C$18,G5<=Dashboard!$C$19)),1,0)) -> 1 | M5: =IF(AND(L5=1,OR(Dashboard!$C$13="All",A5=Dashboard!$C$13),OR(Dashboard!$C$14="All",B5=Dashboard!$C$14),OR(Dashboard!$C$15="All",C5=Dashboard!$C$15),OR(Dashboard!$C$16="All",K5=Dashboard!$C$16),OR(Dashboard!$C$17="All",J5=Dashboard!$C$17)),1,0) -> 1 | N5: =IF(AND(L5=1,OR(Dashboard!$C$13="All",A5=Dashboard!$C$13),OR(Dashboard!$C$14="All",B5=Dashboard!$C$14),OR(Dashboard!$C$16="All",K5=Dashboard!$C$16),OR(Dashboard!$C$17="All",J5=Dashboard!$C$17)),1,0) -> 1 | O5: =IF(AND(L5=1,OR(Dashboard!$C$13="All",A5=Dashboard!$C$13),OR(Dashboard!$C$15="All",C5=Dashboard!$C$15),OR(Dashboard!$C$16="All",K5=Dashboard!$C$16),OR(Dashboard!$C$17="All",J5=Dashboard!$C$17)),1,0) -> 1 | P5: =IF(AND(L5=1,OR(Dashboard!$C$13="All",A5=Dashboard!$C$13),OR(Dashboard!$C$14="All",B5=Dashboard!$C$14),OR(Dashboard!$C$15="All",C5=Dashboard!$C$15),OR(Dashboard!$C$17="All",J5=Dashboard!$C$17)),1,0) -> 1 | Q5: =IF(AND(L5=1,OR(Dashboard!$C$14="All",B5=Dashboard!$C$14),OR(Dashboard!$C$15="All",C5=Dashboard!$C$15),OR(Dashboard!$C$16="All",K5=Dashboard!$C$16),OR(Dashboard!$C$17="All",J5=Dashboard!$C$17)),1,0) -> 1 | R5: =IF(AND(L5=1,OR(Dashboard!$C$13="All",A5=Dashboard!$C$13),OR(Dashboard!$C$14="All",B5=Dashboard!$C$14),OR(Dashboard!$C$15="All",C5=Dashboard!$C$15),OR(Dashboard!$C$16="All",K5=Dashboard!$C$16)),1,0) -> 1 | S5: =IF(M5=1,ROW()-1,"") -> 4 | T5: Harvest | U5: Avery Dennison/Dipole | V5: 15 coaxial cable
A6: FRA | B6: Jarltech | C6: FX9600 Reader | D6: 18 | E6: 8 | F6: =IF(E6="","",D6*E6) -> 144 | G6: 46148 | H6: 8 | I6: =IF(OR(G6="",H6=""),"",G6+H6*7) -> 46204 | J6: Fully Paid | K6: Delayed | L6: =IF(A6="","",IF(OR(G6="",AND(G6>=Dashboard!$C$18,G6<=Dashboard!$C$19)),1,0)) -> 1 | M6: =IF(AND(L6=1,OR(Dashboard!$C$13="All",A6=Dashboard!$C$13),OR(Dashboard!$C$14="All",B6=Dashboard!$C$14),OR(Dashboard!$C$15="All",C6=Dashboard!$C$15),OR(Dashboard!$C$16="All",K6=Dashboard!$C$16),OR(Dashboard!$C$17="All",J6=Dashboard!$C$17)),1,0) -> 1 | N6: =IF(AND(L6=1,OR(Dashboard!$C$13="All",A6=Dashboard!$C$13),OR(Dashboard!$C$14="All",B6=Dashboard!$C$14),OR(Dashboard!$C$16="All",K6=Dashboard!$C$16),OR(Dashboard!$C$17="All",J6=Dashboard!$C$17)),1,0) -> 1 | O6: =IF(AND(L6=1,OR(Dashboard!$C$13="All",A6=Dashboard!$C$13),OR(Dashboard!$C$15="All",C6=Dashboard!$C$15),OR(Dashboard!$C$16="All",K6=Dashboard!$C$16),OR(Dashboard!$C$17="All",J6=Dashboard!$C$17)),1,0) -> 1 | P6: =IF(AND(L6=1,OR(Dashboard!$C$13="All",A6=Dashboard!$C$13),OR(Dashboard!$C$14="All",B6=Dashboard!$C$14),OR(Dashboard!$C$15="All",C6=Dashboard!$C$15),OR(Dashboard!$C$17="All",J6=Dashboard!$C$17)),1,0) -> 1 | Q6: =IF(AND(L6=1,OR(Dashboard!$C$14="All",B6=Dashboard!$C$14),OR(Dashboard!$C$15="All",C6=Dashboard!$C$15),OR(Dashboard!$C$16="All",K6=Dashboard!$C$16),OR(Dashboard!$C$17="All",J6=Dashboard!$C$17)),1,0) -> 1 | R6: =IF(AND(L6=1,OR(Dashboard!$C$13="All",A6=Dashboard!$C$13),OR(Dashboard!$C$14="All",B6=Dashboard!$C$14),OR(Dashboard!$C$15="All",C6=Dashboard!$C$15),OR(Dashboard!$C$16="All",K6=Dashboard!$C$16)),1,0) -> 1 | S6: =IF(M6=1,ROW()-1,"") -> 5 | T6: Lavista Patios | U6: Confidex | V6: 70 coaxial cable
A7: FRA | B7: Jarltech | C7: AN480 Antenna | D7: 37 | E7: 2 | F7: =IF(E7="","",D7*E7) -> 74 | G7: 46149 | H7: 9 | I7: =IF(OR(G7="",H7=""),"",G7+H7*7) -> 46212 | J7: Not Paid | K7: Pending | L7: =IF(A7="","",IF(OR(G7="",AND(G7>=Dashboard!$C$18,G7<=Dashboard!$C$19)),1,0)) -> 1 | M7: =IF(AND(L7=1,OR(Dashboard!$C$13="All",A7=Dashboard!$C$13),OR(Dashboard!$C$14="All",B7=Dashboard!$C$14),OR(Dashboard!$C$15="All",C7=Dashboard!$C$15),OR(Dashboard!$C$16="All",K7=Dashboard!$C$16),OR(Dashboard!$C$17="All",J7=Dashboard!$C$17)),1,0) -> 1 | N7: =IF(AND(L7=1,OR(Dashboard!$C$13="All",A7=Dashboard!$C$13),OR(Dashboard!$C$14="All",B7=Dashboard!$C$14),OR(Dashboard!$C$16="All",K7=Dashboard!$C$16),OR(Dashboard!$C$17="All",J7=Dashboard!$C$17)),1,0) -> 1 | O7: =IF(AND(L7=1,OR(Dashboard!$C$13="All",A7=Dashboard!$C$13),OR(Dashboard!$C$15="All",C7=Dashboard!$C$15),OR(Dashboard!$C$16="All",K7=Dashboard!$C$16),OR(Dashboard!$C$17="All",J7=Dashboard!$C$17)),1,0) -> 1 | P7: =IF(AND(L7=1,OR(Dashboard!$C$13="All",A7=Dashboard!$C$13),OR(Dashboard!$C$14="All",B7=Dashboard!$C$14),OR(Dashboard!$C$15="All",C7=Dashboard!$C$15),OR(Dashboard!$C$17="All",J7=Dashboard!$C$17)),1,0) -> 1 | Q7: =IF(AND(L7=1,OR(Dashboard!$C$14="All",B7=Dashboard!$C$14),OR(Dashboard!$C$15="All",C7=Dashboard!$C$15),OR(Dashboard!$C$16="All",K7=Dashboard!$C$16),OR(Dashboard!$C$17="All",J7=Dashboard!$C$17)),1,0) -> 1 | R7: =IF(AND(L7=1,OR(Dashboard!$C$13="All",A7=Dashboard!$C$13),OR(Dashboard!$C$14="All",B7=Dashboard!$C$14),OR(Dashboard!$C$15="All",C7=Dashboard!$C$15),OR(Dashboard!$C$16="All",K7=Dashboard!$C$16)),1,0) -> 1 | S7: =IF(M7=1,ROW()-1,"") -> 6 | T7: Layan | U7: Cube | V7: [14229] Paper tags (Dogbone) Blank
A8: FRA | B8: Local | C8: Protection cap | D8: 18 | E8: 15 | F8: =IF(E8="","",D8*E8) -> 270 | G8: 46150 | H8: 4 | I8: =IF(OR(G8="",H8=""),"",G8+H8*7) -> 46178 | J8: Advance Payment | K8: Completed | L8: =IF(A8="","",IF(OR(G8="",AND(G8>=Dashboard!$C$18,G8<=Dashboard!$C$19)),1,0)) -> 1 | M8: =IF(AND(L8=1,OR(Dashboard!$C$13="All",A8=Dashboard!$C$13),OR(Dashboard!$C$14="All",B8=Dashboard!$C$14),OR(Dashboard!$C$15="All",C8=Dashboard!$C$15),OR(Dashboard!$C$16="All",K8=Dashboard!$C$16),OR(Dashboard!$C$17="All",J8=Dashboard!$C$17)),1,0) -> 1 | N8: =IF(AND(L8=1,OR(Dashboard!$C$13="All",A8=Dashboard!$C$13),OR(Dashboard!$C$14="All",B8=Dashboard!$C$14),OR(Dashboard!$C$16="All",K8=Dashboard!$C$16),OR(Dashboard!$C$17="All",J8=Dashboard!$C$17)),1,0) -> 1 | O8: =IF(AND(L8=1,OR(Dashboard!$C$13="All",A8=Dashboard!$C$13),OR(Dashboard!$C$15="All",C8=Dashboard!$C$15),OR(Dashboard!$C$16="All",K8=Dashboard!$C$16),OR(Dashboard!$C$17="All",J8=Dashboard!$C$17)),1,0) -> 1 | P8: =IF(AND(L8=1,OR(Dashboard!$C$13="All",A8=Dashboard!$C$13),OR(Dashboard!$C$14="All",B8=Dashboard!$C$14),OR(Dashboard!$C$15="All",C8=Dashboard!$C$15),OR(Dashboard!$C$17="All",J8=Dashboard!$C$17)),1,0) -> 1 | Q8: =IF(AND(L8=1,OR(Dashboard!$C$14="All",B8=Dashboard!$C$14),OR(Dashboard!$C$15="All",C8=Dashboard!$C$15),OR(Dashboard!$C$16="All",K8=Dashboard!$C$16),OR(Dashboard!$C$17="All",J8=Dashboard!$C$17)),1,0) -> 1 | R8: =IF(AND(L8=1,OR(Dashboard!$C$13="All",A8=Dashboard!$C$13),OR(Dashboard!$C$14="All",B8=Dashboard!$C$14),OR(Dashboard!$C$15="All",C8=Dashboard!$C$15),OR(Dashboard!$C$16="All",K8=Dashboard!$C$16)),1,0) -> 1 | S8: =IF(M8=1,ROW()-1,"") -> 7 | T8: Majid El futtaim | U8: Dipole | V8: [14229] Paper tags (Dogbone) Blank
A9: FRA | B9: Local | C9: Antenna Stand | D9: 37 | E9: 45 | F9: =IF(E9="","",D9*E9) -> 1665 | G9: 46151 | H9: 3 | I9: =IF(OR(G9="",H9=""),"",G9+H9*7) -> 46172 | J9: Fully Paid | K9: Pending | L9: =IF(A9="","",IF(OR(G9="",AND(G9>=Dashboard!$C$18,G9<=Dashboard!$C$19)),1,0)) -> 1 | M9: =IF(AND(L9=1,OR(Dashboard!$C$13="All",A9=Dashboard!$C$13),OR(Dashboard!$C$14="All",B9=Dashboard!$C$14),OR(Dashboard!$C$15="All",C9=Dashboard!$C$15),OR(Dashboard!$C$16="All",K9=Dashboard!$C$16),OR(Dashboard!$C$17="All",J9=Dashboard!$C$17)),1,0) -> 1 | N9: =IF(AND(L9=1,OR(Dashboard!$C$13="All",A9=Dashboard!$C$13),OR(Dashboard!$C$14="All",B9=Dashboard!$C$14),OR(Dashboard!$C$16="All",K9=Dashboard!$C$16),OR(Dashboard!$C$17="All",J9=Dashboard!$C$17)),1,0) -> 1 | O9: =IF(AND(L9=1,OR(Dashboard!$C$13="All",A9=Dashboard!$C$13),OR(Dashboard!$C$15="All",C9=Dashboard!$C$15),OR(Dashboard!$C$16="All",K9=Dashboard!$C$16),OR(Dashboard!$C$17="All",J9=Dashboard!$C$17)),1,0) -> 1 | P9: =IF(AND(L9=1,OR(Dashboard!$C$13="All",A9=Dashboard!$C$13),OR(Dashboard!$C$14="All",B9=Dashboard!$C$14),OR(Dashboard!$C$15="All",C9=Dashboard!$C$15),OR(Dashboard!$C$17="All",J9=Dashboard!$C$17)),1,0) -> 1 | Q9: =IF(AND(L9=1,OR(Dashboard!$C$14="All",B9=Dashboard!$C$14),OR(Dashboard!$C$15="All",C9=Dashboard!$C$15),OR(Dashboard!$C$16="All",K9=Dashboard!$C$16),OR(Dashboard!$C$17="All",J9=Dashboard!$C$17)),1,0) -> 1 | R9: =IF(AND(L9=1,OR(Dashboard!$C$13="All",A9=Dashboard!$C$13),OR(Dashboard!$C$14="All",B9=Dashboard!$C$14),OR(Dashboard!$C$15="All",C9=Dashboard!$C$15),OR(Dashboard!$C$16="All",K9=Dashboard!$C$16)),1,0) -> 1 | S9: =IF(M9=1,ROW()-1,"") -> 8 | T9: مخازن وزارة الصحة | U9: El Nekheely | V9: [3199.000.00] ID ISC.ANT.U270/270-EU Antenna UHF
A10: El Kasr | B10: Feig | C10: Jewelry tags | D10: 40000 | E10: 24 | F10: =IF(E10="","",D10*E10) -> 960000 | G10: 46152 | H10: 1 | I10: =IF(OR(G10="",H10=""),"",G10+H10*7) -> 46159 | J10: Advance Payment | K10: In Progress | L10: =IF(A10="","",IF(OR(G10="",AND(G10>=Dashboard!$C$18,G10<=Dashboard!$C$19)),1,0)) -> 1 | M10: =IF(AND(L10=1,OR(Dashboard!$C$13="All",A10=Dashboard!$C$13),OR(Dashboard!$C$14="All",B10=Dashboard!$C$14),OR(Dashboard!$C$15="All",C10=Dashboard!$C$15),OR(Dashboard!$C$16="All",K10=Dashboard!$C$16),OR(Dashboard!$C$17="All",J10=Dashboard!$C$17)),1,0) -> 1 | N10: =IF(AND(L10=1,OR(Dashboard!$C$13="All",A10=Dashboard!$C$13),OR(Dashboard!$C$14="All",B10=Dashboard!$C$14),OR(Dashboard!$C$16="All",K10=Dashboard!$C$16),OR(Dashboard!$C$17="All",J10=Dashboard!$C$17)),1,0) -> 1 | O10: =IF(AND(L10=1,OR(Dashboard!$C$13="All",A10=Dashboard!$C$13),OR(Dashboard!$C$15="All",C10=Dashboard!$C$15),OR(Dashboard!$C$16="All",K10=Dashboard!$C$16),OR(Dashboard!$C$17="All",J10=Dashboard!$C$17)),1,0) -> 1 | P10: =IF(AND(L10=1,OR(Dashboard!$C$13="All",A10=Dashboard!$C$13),OR(Dashboard!$C$14="All",B10=Dashboard!$C$14),OR(Dashboard!$C$15="All",C10=Dashboard!$C$15),OR(Dashboard!$C$17="All",J10=Dashboard!$C$17)),1,0) -> 1 | Q10: =IF(AND(L10=1,OR(Dashboard!$C$14="All",B10=Dashboard!$C$14),OR(Dashboard!$C$15="All",C10=Dashboard!$C$15),OR(Dashboard!$C$16="All",K10=Dashboard!$C$16),OR(Dashboard!$C$17="All",J10=Dashboard!$C$17)),1,0) -> 1 | R10: =IF(AND(L10=1,OR(Dashboard!$C$13="All",A10=Dashboard!$C$13),OR(Dashboard!$C$14="All",B10=Dashboard!$C$14),OR(Dashboard!$C$15="All",C10=Dashboard!$C$15),OR(Dashboard!$C$16="All",K10=Dashboard!$C$16)),1,0) -> 1 | S10: =IF(M10=1,ROW()-1,"") -> 9 | T10: Telal Elsahel | U10: FAAC | V10: [3908425] SkinPack 615 Barrier
A11: El Kasr | B11: Dipole | C11: Printer CT4LX | D11: 5 | E11: 25 | F11: =IF(E11="","",D11*E11) -> 125 | G11: 46153 | H11: 2 | I11: =IF(OR(G11="",H11=""),"",G11+H11*7) -> 46167 | J11: Fully Paid | K11: Completed | L11: =IF(A11="","",IF(OR(G11="",AND(G11>=Dashboard!$C$18,G11<=Dashboard!$C$19)),1,0)) -> 1 | M11: =IF(AND(L11=1,OR(Dashboard!$C$13="All",A11=Dashboard!$C$13),OR(Dashboard!$C$14="All",B11=Dashboard!$C$14),OR(Dashboard!$C$15="All",C11=Dashboard!$C$15),OR(Dashboard!$C$16="All",K11=Dashboard!$C$16),OR(Dashboard!$C$17="All",J11=Dashboard!$C$17)),1,0) -> 1 | N11: =IF(AND(L11=1,OR(Dashboard!$C$13="All",A11=Dashboard!$C$13),OR(Dashboard!$C$14="All",B11=Dashboard!$C$14),OR(Dashboard!$C$16="All",K11=Dashboard!$C$16),OR(Dashboard!$C$17="All",J11=Dashboard!$C$17)),1,0) -> 1 | O11: =IF(AND(L11=1,OR(Dashboard!$C$13="All",A11=Dashboard!$C$13),OR(Dashboard!$C$15="All",C11=Dashboard!$C$15),OR(Dashboard!$C$16="All",K11=Dashboard!$C$16),OR(Dashboard!$C$17="All",J11=Dashboard!$C$17)),1,0) -> 1 | P11: =IF(AND(L11=1,OR(Dashboard!$C$13="All",A11=Dashboard!$C$13),OR(Dashboard!$C$14="All",B11=Dashboard!$C$14),OR(Dashboard!$C$15="All",C11=Dashboard!$C$15),OR(Dashboard!$C$17="All",J11=Dashboard!$C$17)),1,0) -> 1 | Q11: =IF(AND(L11=1,OR(Dashboard!$C$14="All",B11=Dashboard!$C$14),OR(Dashboard!$C$15="All",C11=Dashboard!$C$15),OR(Dashboard!$C$16="All",K11=Dashboard!$C$16),OR(Dashboard!$C$17="All",J11=Dashboard!$C$17)),1,0) -> 1 | R11: =IF(AND(L11=1,OR(Dashboard!$C$13="All",A11=Dashboard!$C$13),OR(Dashboard!$C$14="All",B11=Dashboard!$C$14),OR(Dashboard!$C$15="All",C11=Dashboard!$C$15),OR(Dashboard!$C$16="All",K11=Dashboard!$C$16)),1,0) -> 1 | S11: =IF(M11=1,ROW()-1,"") -> 10 | T11: El Kasr Jewelry | U11: FEIG | V11: [4127.001.01] ID ISC.LRU1002-EU Fixed UHF Long Range Reader (ID LRU1002-EU)
A12: El Kasr | B12: El Nekheely | C12: Ribbons | D12: 20 | E12: 36 | F12: =IF(E12="","",D12*E12) -> 720 | G12: 46154 | H12: 7 | I12: =IF(OR(G12="",H12=""),"",G12+H12*7) -> 46203 | J12: Not Paid | K12: Delayed | L12: =IF(A12="","",IF(OR(G12="",AND(G12>=Dashboard!$C$18,G12<=Dashboard!$C$19)),1,0)) -> 1 | M12: =IF(AND(L12=1,OR(Dashboard!$C$13="All",A12=Dashboard!$C$13),OR(Dashboard!$C$14="All",B12=Dashboard!$C$14),OR(Dashboard!$C$15="All",C12=Dashboard!$C$15),OR(Dashboard!$C$16="All",K12=Dashboard!$C$16),OR(Dashboard!$C$17="All",J12=Dashboard!$C$17)),1,0) -> 1 | N12: =IF(AND(L12=1,OR(Dashboard!$C$13="All",A12=Dashboard!$C$13),OR(Dashboard!$C$14="All",B12=Dashboard!$C$14),OR(Dashboard!$C$16="All",K12=Dashboard!$C$16),OR(Dashboard!$C$17="All",J12=Dashboard!$C$17)),1,0) -> 1 | O12: =IF(AND(L12=1,OR(Dashboard!$C$13="All",A12=Dashboard!$C$13),OR(Dashboard!$C$15="All",C12=Dashboard!$C$15),OR(Dashboard!$C$16="All",K12=Dashboard!$C$16),OR(Dashboard!$C$17="All",J12=Dashboard!$C$17)),1,0) -> 1 | P12: =IF(AND(L12=1,OR(Dashboard!$C$13="All",A12=Dashboard!$C$13),OR(Dashboard!$C$14="All",B12=Dashboard!$C$14),OR(Dashboard!$C$15="All",C12=Dashboard!$C$15),OR(Dashboard!$C$17="All",J12=Dashboard!$C$17)),1,0) -> 1 | Q12: =IF(AND(L12=1,OR(Dashboard!$C$14="All",B12=Dashboard!$C$14),OR(Dashboard!$C$15="All",C12=Dashboard!$C$15),OR(Dashboard!$C$16="All",K12=Dashboard!$C$16),OR(Dashboard!$C$17="All",J12=Dashboard!$C$17)),1,0) -> 1 | R12: =IF(AND(L12=1,OR(Dashboard!$C$13="All",A12=Dashboard!$C$13),OR(Dashboard!$C$14="All",B12=Dashboard!$C$14),OR(Dashboard!$C$15="All",C12=Dashboard!$C$15),OR(Dashboard!$C$16="All",K12=Dashboard!$C$16)),1,0) -> 1 | S12: =IF(M12=1,ROW()-1,"") -> 11 | T12: El Patio | U12: Feig | V12: [4245985] GR, EXT release standard 615
A13: El Kasr | B13: FAAC | C13: LRU1002 | D13: 5 | E13: 95 | F13: =IF(E13="","",D13*E13) -> 475 | G13: 46155 | H13: 2 | I13: =IF(OR(G13="",H13=""),"",G13+H13*7) -> 46169 | J13: Advance Payment | K13: Pending | L13: =IF(A13="","",IF(OR(G13="",AND(G13>=Dashboard!$C$18,G13<=Dashboard!$C$19)),1,0)) -> 1 | M13: =IF(AND(L13=1,OR(Dashboard!$C$13="All",A13=Dashboard!$C$13),OR(Dashboard!$C$14="All",B13=Dashboard!$C$14),OR(Dashboard!$C$15="All",C13=Dashboard!$C$15),OR(Dashboard!$C$16="All",K13=Dashboard!$C$16),OR(Dashboard!$C$17="All",J13=Dashboard!$C$17)),1,0) -> 1 | N13: =IF(AND(L13=1,OR(Dashboard!$C$13="All",A13=Dashboard!$C$13),OR(Dashboard!$C$14="All",B13=Dashboard!$C$14),OR(Dashboard!$C$16="All",K13=Dashboard!$C$16),OR(Dashboard!$C$17="All",J13=Dashboard!$C$17)),1,0) -> 1 | O13: =IF(AND(L13=1,OR(Dashboard!$C$13="All",A13=Dashboard!$C$13),OR(Dashboard!$C$15="All",C13=Dashboard!$C$15),OR(Dashboard!$C$16="All",K13=Dashboard!$C$16),OR(Dashboard!$C$17="All",J13=Dashboard!$C$17)),1,0) -> 1 | P13: =IF(AND(L13=1,OR(Dashboard!$C$13="All",A13=Dashboard!$C$13),OR(Dashboard!$C$14="All",B13=Dashboard!$C$14),OR(Dashboard!$C$15="All",C13=Dashboard!$C$15),OR(Dashboard!$C$17="All",J13=Dashboard!$C$17)),1,0) -> 1 | Q13: =IF(AND(L13=1,OR(Dashboard!$C$14="All",B13=Dashboard!$C$14),OR(Dashboard!$C$15="All",C13=Dashboard!$C$15),OR(Dashboard!$C$16="All",K13=Dashboard!$C$16),OR(Dashboard!$C$17="All",J13=Dashboard!$C$17)),1,0) -> 1 | R13: =IF(AND(L13=1,OR(Dashboard!$C$13="All",A13=Dashboard!$C$13),OR(Dashboard!$C$14="All",B13=Dashboard!$C$14),OR(Dashboard!$C$15="All",C13=Dashboard!$C$15),OR(Dashboard!$C$16="All",K13=Dashboard!$C$16)),1,0) -> 1 | S13: =IF(M13=1,ROW()-1,"") -> 12 | T13: Bellagio | U13: Fusion | V13: [5118.001.01] ID MAX.U500i-EU
A14: El Kasr | B14: Cube | C14: Antenna | D14: 10 | E14: 574 | F14: =IF(E14="","",D14*E14) -> 5740 | G14: 46156 | H14: 6 | I14: =IF(OR(G14="",H14=""),"",G14+H14*7) -> 46198 | J14: Fully Paid | K14: Pending | L14: =IF(A14="","",IF(OR(G14="",AND(G14>=Dashboard!$C$18,G14<=Dashboard!$C$19)),1,0)) -> 1 | M14: =IF(AND(L14=1,OR(Dashboard!$C$13="All",A14=Dashboard!$C$13),OR(Dashboard!$C$14="All",B14=Dashboard!$C$14),OR(Dashboard!$C$15="All",C14=Dashboard!$C$15),OR(Dashboard!$C$16="All",K14=Dashboard!$C$16),OR(Dashboard!$C$17="All",J14=Dashboard!$C$17)),1,0) -> 1 | N14: =IF(AND(L14=1,OR(Dashboard!$C$13="All",A14=Dashboard!$C$13),OR(Dashboard!$C$14="All",B14=Dashboard!$C$14),OR(Dashboard!$C$16="All",K14=Dashboard!$C$16),OR(Dashboard!$C$17="All",J14=Dashboard!$C$17)),1,0) -> 1 | O14: =IF(AND(L14=1,OR(Dashboard!$C$13="All",A14=Dashboard!$C$13),OR(Dashboard!$C$15="All",C14=Dashboard!$C$15),OR(Dashboard!$C$16="All",K14=Dashboard!$C$16),OR(Dashboard!$C$17="All",J14=Dashboard!$C$17)),1,0) -> 1 | P14: =IF(AND(L14=1,OR(Dashboard!$C$13="All",A14=Dashboard!$C$13),OR(Dashboard!$C$14="All",B14=Dashboard!$C$14),OR(Dashboard!$C$15="All",C14=Dashboard!$C$15),OR(Dashboard!$C$17="All",J14=Dashboard!$C$17)),1,0) -> 1 | Q14: =IF(AND(L14=1,OR(Dashboard!$C$14="All",B14=Dashboard!$C$14),OR(Dashboard!$C$15="All",C14=Dashboard!$C$15),OR(Dashboard!$C$16="All",K14=Dashboard!$C$16),OR(Dashboard!$C$17="All",J14=Dashboard!$C$17)),1,0) -> 1 | R14: =IF(AND(L14=1,OR(Dashboard!$C$13="All",A14=Dashboard!$C$13),OR(Dashboard!$C$14="All",B14=Dashboard!$C$14),OR(Dashboard!$C$15="All",C14=Dashboard!$C$15),OR(Dashboard!$C$16="All",K14=Dashboard!$C$16)),1,0) -> 1 | S14: =IF(M14=1,ROW()-1,"") -> 13 | T14: AlBurouj | U14: IPS | V14: [5118.001.01] ID MAX.U500i-EU Compact UHF Access Control Re
A15: El Kasr | B15: Confidex | C15: AT907 | E15: 558 | F15: =IF(E15="","",D15*E15) -> 0 | G15: 46157 | H15: 4 | I15: =IF(OR(G15="",H15=""),"",G15+H15*7) -> 46185 | J15: Advance Payment | K15: Pending | L15: =IF(A15="","",IF(OR(G15="",AND(G15>=Dashboard!$C$18,G15<=Dashboard!$C$19)),1,0)) -> 1 | M15: =IF(AND(L15=1,OR(Dashboard!$C$13="All",A15=Dashboard!$C$13),OR(Dashboard!$C$14="All",B15=Dashboard!$C$14),OR(Dashboard!$C$15="All",C15=Dashboard!$C$15),OR(Dashboard!$C$16="All",K15=Dashboard!$C$16),OR(Dashboard!$C$17="All",J15=Dashboard!$C$17)),1,0) -> 1 | N15: =IF(AND(L15=1,OR(Dashboard!$C$13="All",A15=Dashboard!$C$13),OR(Dashboard!$C$14="All",B15=Dashboard!$C$14),OR(Dashboard!$C$16="All",K15=Dashboard!$C$16),OR(Dashboard!$C$17="All",J15=Dashboard!$C$17)),1,0) -> 1 | O15: =IF(AND(L15=1,OR(Dashboard!$C$13="All",A15=Dashboard!$C$13),OR(Dashboard!$C$15="All",C15=Dashboard!$C$15),OR(Dashboard!$C$16="All",K15=Dashboard!$C$16),OR(Dashboard!$C$17="All",J15=Dashboard!$C$17)),1,0) -> 1 | P15: =IF(AND(L15=1,OR(Dashboard!$C$13="All",A15=Dashboard!$C$13),OR(Dashboard!$C$14="All",B15=Dashboard!$C$14),OR(Dashboard!$C$15="All",C15=Dashboard!$C$15),OR(Dashboard!$C$17="All",J15=Dashboard!$C$17)),1,0) -> 1 | Q15: =IF(AND(L15=1,OR(Dashboard!$C$14="All",B15=Dashboard!$C$14),OR(Dashboard!$C$15="All",C15=Dashboard!$C$15),OR(Dashboard!$C$16="All",K15=Dashboard!$C$16),OR(Dashboard!$C$17="All",J15=Dashboard!$C$17)),1,0) -> 1 | R15: =IF(AND(L15=1,OR(Dashboard!$C$13="All",A15=Dashboard!$C$13),OR(Dashboard!$C$14="All",B15=Dashboard!$C$14),OR(Dashboard!$C$15="All",C15=Dashboard!$C$15),OR(Dashboard!$C$16="All",K15=Dashboard!$C$16)),1,0) -> 1 | S15: =IF(M15=1,ROW()-1,"") -> 14 | T15: Suez Canal Bank | U15: Jarltech | V15: [5118.001.01] ID MAX.U500i-EU Compact UHF Access Control Reader with integrated Antenna
A16: Harvest | B16: koodle | C16: RFID Desktop Printer with Feeder- (CT4LX) | D16: 2 | E16: 2265 | F16: =IF(E16="","",D16*E16) -> 4530 | G16: 46158 | H16: 1 | I16: =IF(OR(G16="",H16=""),"",G16+H16*7) -> 46165 | J16: Fully Paid | K16: Pending | L16: =IF(A16="","",IF(OR(G16="",AND(G16>=Dashboard!$C$18,G16<=Dashboard!$C$19)),1,0)) -> 1 | M16: =IF(AND(L16=1,OR(Dashboard!$C$13="All",A16=Dashboard!$C$13),OR(Dashboard!$C$14="All",B16=Dashboard!$C$14),OR(Dashboard!$C$15="All",C16=Dashboard!$C$15),OR(Dashboard!$C$16="All",K16=Dashboard!$C$16),OR(Dashboard!$C$17="All",J16=Dashboard!$C$17)),1,0) -> 1 | N16: =IF(AND(L16=1,OR(Dashboard!$C$13="All",A16=Dashboard!$C$13),OR(Dashboard!$C$14="All",B16=Dashboard!$C$14),OR(Dashboard!$C$16="All",K16=Dashboard!$C$16),OR(Dashboard!$C$17="All",J16=Dashboard!$C$17)),1,0) -> 1 | O16: =IF(AND(L16=1,OR(Dashboard!$C$13="All",A16=Dashboard!$C$13),OR(Dashboard!$C$15="All",C16=Dashboard!$C$15),OR(Dashboard!$C$16="All",K16=Dashboard!$C$16),OR(Dashboard!$C$17="All",J16=Dashboard!$C$17)),1,0) -> 1 | P16: =IF(AND(L16=1,OR(Dashboard!$C$13="All",A16=Dashboard!$C$13),OR(Dashboard!$C$14="All",B16=Dashboard!$C$14),OR(Dashboard!$C$15="All",C16=Dashboard!$C$15),OR(Dashboard!$C$17="All",J16=Dashboard!$C$17)),1,0) -> 1 | Q16: =IF(AND(L16=1,OR(Dashboard!$C$14="All",B16=Dashboard!$C$14),OR(Dashboard!$C$15="All",C16=Dashboard!$C$15),OR(Dashboard!$C$16="All",K16=Dashboard!$C$16),OR(Dashboard!$C$17="All",J16=Dashboard!$C$17)),1,0) -> 1 | R16: =IF(AND(L16=1,OR(Dashboard!$C$13="All",A16=Dashboard!$C$13),OR(Dashboard!$C$14="All",B16=Dashboard!$C$14),OR(Dashboard!$C$15="All",C16=Dashboard!$C$15),OR(Dashboard!$C$16="All",K16=Dashboard!$C$16)),1,0) -> 1 | S16: =IF(M16=1,ROW()-1,"") -> 15 | T16: Akoya | U16: jarltech | V16: [5400.001.01] ID ANT1710/690-A Crystal Gate Wave "Base"
A17: Harvest | B17: The tag factory | C17: Ribbons for the printer | D17: 9 | E17: 45 | F17: =IF(E17="","",D17*E17) -> 405 | G17: 46159 | H17: 2 | I17: =IF(OR(G17="",H17=""),"",G17+H17*7) -> 46173 | J17: Not Paid | K17: Pending | L17: =IF(A17="","",IF(OR(G17="",AND(G17>=Dashboard!$C$18,G17<=Dashboard!$C$19)),1,0)) -> 1 | M17: =IF(AND(L17=1,OR(Dashboard!$C$13="All",A17=Dashboard!$C$13),OR(Dashboard!$C$14="All",B17=Dashboard!$C$14),OR(Dashboard!$C$15="All",C17=Dashboard!$C$15),OR(Dashboard!$C$16="All",K17=Dashboard!$C$16),OR(Dashboard!$C$17="All",J17=Dashboard!$C$17)),1,0) -> 1 | N17: =IF(AND(L17=1,OR(Dashboard!$C$13="All",A17=Dashboard!$C$13),OR(Dashboard!$C$14="All",B17=Dashboard!$C$14),OR(Dashboard!$C$16="All",K17=Dashboard!$C$16),OR(Dashboard!$C$17="All",J17=Dashboard!$C$17)),1,0) -> 1 | O17: =IF(AND(L17=1,OR(Dashboard!$C$13="All",A17=Dashboard!$C$13),OR(Dashboard!$C$15="All",C17=Dashboard!$C$15),OR(Dashboard!$C$16="All",K17=Dashboard!$C$16),OR(Dashboard!$C$17="All",J17=Dashboard!$C$17)),1,0) -> 1 | P17: =IF(AND(L17=1,OR(Dashboard!$C$13="All",A17=Dashboard!$C$13),OR(Dashboard!$C$14="All",B17=Dashboard!$C$14),OR(Dashboard!$C$15="All",C17=Dashboard!$C$15),OR(Dashboard!$C$17="All",J17=Dashboard!$C$17)),1,0) -> 1 | Q17: =IF(AND(L17=1,OR(Dashboard!$C$14="All",B17=Dashboard!$C$14),OR(Dashboard!$C$15="All",C17=Dashboard!$C$15),OR(Dashboard!$C$16="All",K17=Dashboard!$C$16),OR(Dashboard!$C$17="All",J17=Dashboard!$C$17)),1,0) -> 1 | R17: =IF(AND(L17=1,OR(Dashboard!$C$13="All",A17=Dashboard!$C$13),OR(Dashboard!$C$14="All",B17=Dashboard!$C$14),OR(Dashboard!$C$15="All",C17=Dashboard!$C$15),OR(Dashboard!$C$16="All",K17=Dashboard!$C$16)),1,0) -> 1 | S17: =IF(M17=1,ROW()-1,"") -> 16 | T17: Marshmallow | U17: koodle | V17: [5401.001.01] ID ANT1710/690-B Crystal Gate Wave
A18: Harvest | B18: Confidex | C18: AT907 | D18: 2 | E18: 5554 | F18: =IF(E18="","",D18*E18) -> 11108 | G18: 46160 | H18: 4 | I18: =IF(OR(G18="",H18=""),"",G18+H18*7) -> 46188 | J18: Not Paid | K18: Completed | L18: =IF(A18="","",IF(OR(G18="",AND(G18>=Dashboard!$C$18,G18<=Dashboard!$C$19)),1,0)) -> 1 | M18: =IF(AND(L18=1,OR(Dashboard!$C$13="All",A18=Dashboard!$C$13),OR(Dashboard!$C$14="All",B18=Dashboard!$C$14),OR(Dashboard!$C$15="All",C18=Dashboard!$C$15),OR(Dashboard!$C$16="All",K18=Dashboard!$C$16),OR(Dashboard!$C$17="All",J18=Dashboard!$C$17)),1,0) -> 1 | N18: =IF(AND(L18=1,OR(Dashboard!$C$13="All",A18=Dashboard!$C$13),OR(Dashboard!$C$14="All",B18=Dashboard!$C$14),OR(Dashboard!$C$16="All",K18=Dashboard!$C$16),OR(Dashboard!$C$17="All",J18=Dashboard!$C$17)),1,0) -> 1 | O18: =IF(AND(L18=1,OR(Dashboard!$C$13="All",A18=Dashboard!$C$13),OR(Dashboard!$C$15="All",C18=Dashboard!$C$15),OR(Dashboard!$C$16="All",K18=Dashboard!$C$16),OR(Dashboard!$C$17="All",J18=Dashboard!$C$17)),1,0) -> 1 | P18: =IF(AND(L18=1,OR(Dashboard!$C$13="All",A18=Dashboard!$C$13),OR(Dashboard!$C$14="All",B18=Dashboard!$C$14),OR(Dashboard!$C$15="All",C18=Dashboard!$C$15),OR(Dashboard!$C$17="All",J18=Dashboard!$C$17)),1,0) -> 1 | Q18: =IF(AND(L18=1,OR(Dashboard!$C$14="All",B18=Dashboard!$C$14),OR(Dashboard!$C$15="All",C18=Dashboard!$C$15),OR(Dashboard!$C$16="All",K18=Dashboard!$C$16),OR(Dashboard!$C$17="All",J18=Dashboard!$C$17)),1,0) -> 1 | R18: =IF(AND(L18=1,OR(Dashboard!$C$13="All",A18=Dashboard!$C$13),OR(Dashboard!$C$14="All",B18=Dashboard!$C$14),OR(Dashboard!$C$15="All",C18=Dashboard!$C$15),OR(Dashboard!$C$16="All",K18=Dashboard!$C$16)),1,0) -> 1 | S18: =IF(M18=1,ROW()-1,"") -> 17 | T18: Karma | U18: Koodle | V18: [7080435] cylinder joint 615
A19: Harvest | B19: Wireless dynamics | C19: Dogbone tags | D19: 20198 | E19: 41 | F19: =IF(E19="","",D19*E19) -> 828118 | G19: 46161 | H19: 6 | I19: =IF(OR(G19="",H19=""),"",G19+H19*7) -> 46203 | J19: Advance Payment | K19: Pending | L19: =IF(A19="","",IF(OR(G19="",AND(G19>=Dashboard!$C$18,G19<=Dashboard!$C$19)),1,0)) -> 1 | M19: =IF(AND(L19=1,OR(Dashboard!$C$13="All",A19=Dashboard!$C$13),OR(Dashboard!$C$14="All",B19=Dashboard!$C$14),OR(Dashboard!$C$15="All",C19=Dashboard!$C$15),OR(Dashboard!$C$16="All",K19=Dashboard!$C$16),OR(Dashboard!$C$17="All",J19=Dashboard!$C$17)),1,0) -> 1 | N19: =IF(AND(L19=1,OR(Dashboard!$C$13="All",A19=Dashboard!$C$13),OR(Dashboard!$C$14="All",B19=Dashboard!$C$14),OR(Dashboard!$C$16="All",K19=Dashboard!$C$16),OR(Dashboard!$C$17="All",J19=Dashboard!$C$17)),1,0) -> 1 | O19: =IF(AND(L19=1,OR(Dashboard!$C$13="All",A19=Dashboard!$C$13),OR(Dashboard!$C$15="All",C19=Dashboard!$C$15),OR(Dashboard!$C$16="All",K19=Dashboard!$C$16),OR(Dashboard!$C$17="All",J19=Dashboard!$C$17)),1,0) -> 1 | P19: =IF(AND(L19=1,OR(Dashboard!$C$13="All",A19=Dashboard!$C$13),OR(Dashboard!$C$14="All",B19=Dashboard!$C$14),OR(Dashboard!$C$15="All",C19=Dashboard!$C$15),OR(Dashboard!$C$17="All",J19=Dashboard!$C$17)),1,0) -> 1 | Q19: =IF(AND(L19=1,OR(Dashboard!$C$14="All",B19=Dashboard!$C$14),OR(Dashboard!$C$15="All",C19=Dashboard!$C$15),OR(Dashboard!$C$16="All",K19=Dashboard!$C$16),OR(Dashboard!$C$17="All",J19=Dashboard!$C$17)),1,0) -> 1 | R19: =IF(AND(L19=1,OR(Dashboard!$C$13="All",A19=Dashboard!$C$13),OR(Dashboard!$C$14="All",B19=Dashboard!$C$14),OR(Dashboard!$C$15="All",C19=Dashboard!$C$15),OR(Dashboard!$C$16="All",K19=Dashboard!$C$16)),1,0) -> 1 | S19: =IF(M19=1,ROW()-1,"") -> 18 | T19: Geera | U19: Local | V19: [7128035] cylinder lock
A20: Harvest | B20: Metalcraft | C20: EU Universal tags- Blank | D20: 1069 | E20: 231 | F20: =IF(E20="","",D20*E20) -> 246939 | G20: 46162 | H20: 8 | I20: =IF(OR(G20="",H20=""),"",G20+H20*7) -> 46218 | J20: Fully Paid | K20: In Progress | L20: =IF(A20="","",IF(OR(G20="",AND(G20>=Dashboard!$C$18,G20<=Dashboard!$C$19)),1,0)) -> 1 | M20: =IF(AND(L20=1,OR(Dashboard!$C$13="All",A20=Dashboard!$C$13),OR(Dashboard!$C$14="All",B20=Dashboard!$C$14),OR(Dashboard!$C$15="All",C20=Dashboard!$C$15),OR(Dashboard!$C$16="All",K20=Dashboard!$C$16),OR(Dashboard!$C$17="All",J20=Dashboard!$C$17)),1,0) -> 1 | N20: =IF(AND(L20=1,OR(Dashboard!$C$13="All",A20=Dashboard!$C$13),OR(Dashboard!$C$14="All",B20=Dashboard!$C$14),OR(Dashboard!$C$16="All",K20=Dashboard!$C$16),OR(Dashboard!$C$17="All",J20=Dashboard!$C$17)),1,0) -> 1 | O20: =IF(AND(L20=1,OR(Dashboard!$C$13="All",A20=Dashboard!$C$13),OR(Dashboard!$C$15="All",C20=Dashboard!$C$15),OR(Dashboard!$C$16="All",K20=Dashboard!$C$16),OR(Dashboard!$C$17="All",J20=Dashboard!$C$17)),1,0) -> 1 | P20: =IF(AND(L20=1,OR(Dashboard!$C$13="All",A20=Dashboard!$C$13),OR(Dashboard!$C$14="All",B20=Dashboard!$C$14),OR(Dashboard!$C$15="All",C20=Dashboard!$C$15),OR(Dashboard!$C$17="All",J20=Dashboard!$C$17)),1,0) -> 1 | Q20: =IF(AND(L20=1,OR(Dashboard!$C$14="All",B20=Dashboard!$C$14),OR(Dashboard!$C$15="All",C20=Dashboard!$C$15),OR(Dashboard!$C$16="All",K20=Dashboard!$C$16),OR(Dashboard!$C$17="All",J20=Dashboard!$C$17)),1,0) -> 1 | R20: =IF(AND(L20=1,OR(Dashboard!$C$13="All",A20=Dashboard!$C$13),OR(Dashboard!$C$14="All",B20=Dashboard!$C$14),OR(Dashboard!$C$15="All",C20=Dashboard!$C$15),OR(Dashboard!$C$16="All",K20=Dashboard!$C$16)),1,0) -> 1 | S20: =IF(M20=1,ROW()-1,"") -> 19 | T20: Jewar | U20: Metalcraft | V20: [713002] 402 release key
A21: Harvest | B21: zebra | C21: Hang tags | D21: 447 | E21: 25 | F21: =IF(E21="","",D21*E21) -> 11175 | G21: 46163 | H21: 9 | I21: =IF(OR(G21="",H21=""),"",G21+H21*7) -> 46226 | J21: Advance Payment | K21: Completed | L21: =IF(A21="","",IF(OR(G21="",AND(G21>=Dashboard!$C$18,G21<=Dashboard!$C$19)),1,0)) -> 1 | M21: =IF(AND(L21=1,OR(Dashboard!$C$13="All",A21=Dashboard!$C$13),OR(Dashboard!$C$14="All",B21=Dashboard!$C$14),OR(Dashboard!$C$15="All",C21=Dashboard!$C$15),OR(Dashboard!$C$16="All",K21=Dashboard!$C$16),OR(Dashboard!$C$17="All",J21=Dashboard!$C$17)),1,0) -> 1 | N21: =IF(AND(L21=1,OR(Dashboard!$C$13="All",A21=Dashboard!$C$13),OR(Dashboard!$C$14="All",B21=Dashboard!$C$14),OR(Dashboard!$C$16="All",K21=Dashboard!$C$16),OR(Dashboard!$C$17="All",J21=Dashboard!$C$17)),1,0) -> 1 | O21: =IF(AND(L21=1,OR(Dashboard!$C$13="All",A21=Dashboard!$C$13),OR(Dashboard!$C$15="All",C21=Dashboard!$C$15),OR(Dashboard!$C$16="All",K21=Dashboard!$C$16),OR(Dashboard!$C$17="All",J21=Dashboard!$C$17)),1,0) -> 1 | P21: =IF(AND(L21=1,OR(Dashboard!$C$13="All",A21=Dashboard!$C$13),OR(Dashboard!$C$14="All",B21=Dashboard!$C$14),OR(Dashboard!$C$15="All",C21=Dashboard!$C$15),OR(Dashboard!$C$17="All",J21=Dashboard!$C$17)),1,0) -> 1 | Q21: =IF(AND(L21=1,OR(Dashboard!$C$14="All",B21=Dashboard!$C$14),OR(Dashboard!$C$15="All",C21=Dashboard!$C$15),OR(Dashboard!$C$16="All",K21=Dashboard!$C$16),OR(Dashboard!$C$17="All",J21=Dashboard!$C$17)),1,0) -> 1 | R21: =IF(AND(L21=1,OR(Dashboard!$C$13="All",A21=Dashboard!$C$13),OR(Dashboard!$C$14="All",B21=Dashboard!$C$14),OR(Dashboard!$C$15="All",C21=Dashboard!$C$15),OR(Dashboard!$C$16="All",K21=Dashboard!$C$16)),1,0) -> 1 | S21: =IF(M21=1,ROW()-1,"") -> 20 | T21: El Nakheel | U21: Metalcraft/ Thabet | V21: [ACG8065] Pair of columns for FIT SLIM photocells
A22: Harvest | B22: The tag factory | C22: Dest windshield tags | D22: 482 | E22: 245 | F22: =IF(E22="","",D22*E22) -> 118090 | G22: 46164 | H22: 4 | I22: =IF(OR(G22="",H22=""),"",G22+H22*7) -> 46192 | J22: Fully Paid | K22: Delayed | L22: =IF(A22="","",IF(OR(G22="",AND(G22>=Dashboard!$C$18,G22<=Dashboard!$C$19)),1,0)) -> 1 | M22: =IF(AND(L22=1,OR(Dashboard!$C$13="All",A22=Dashboard!$C$13),OR(Dashboard!$C$14="All",B22=Dashboard!$C$14),OR(Dashboard!$C$15="All",C22=Dashboard!$C$15),OR(Dashboard!$C$16="All",K22=Dashboard!$C$16),OR(Dashboard!$C$17="All",J22=Dashboard!$C$17)),1,0) -> 1 | N22: =IF(AND(L22=1,OR(Dashboard!$C$13="All",A22=Dashboard!$C$13),OR(Dashboard!$C$14="All",B22=Dashboard!$C$14),OR(Dashboard!$C$16="All",K22=Dashboard!$C$16),OR(Dashboard!$C$17="All",J22=Dashboard!$C$17)),1,0) -> 1 | O22: =IF(AND(L22=1,OR(Dashboard!$C$13="All",A22=Dashboard!$C$13),OR(Dashboard!$C$15="All",C22=Dashboard!$C$15),OR(Dashboard!$C$16="All",K22=Dashboard!$C$16),OR(Dashboard!$C$17="All",J22=Dashboard!$C$17)),1,0) -> 1 | P22: =IF(AND(L22=1,OR(Dashboard!$C$13="All",A22=Dashboard!$C$13),OR(Dashboard!$C$14="All",B22=Dashboard!$C$14),OR(Dashboard!$C$15="All",C22=Dashboard!$C$15),OR(Dashboard!$C$17="All",J22=Dashboard!$C$17)),1,0) -> 1 | Q22: =IF(AND(L22=1,OR(Dashboard!$C$14="All",B22=Dashboard!$C$14),OR(Dashboard!$C$15="All",C22=Dashboard!$C$15),OR(Dashboard!$C$16="All",K22=Dashboard!$C$16),OR(Dashboard!$C$17="All",J22=Dashboard!$C$17)),1,0) -> 1 | R22: =IF(AND(L22=1,OR(Dashboard!$C$13="All",A22=Dashboard!$C$13),OR(Dashboard!$C$14="All",B22=Dashboard!$C$14),OR(Dashboard!$C$15="All",C22=Dashboard!$C$15),OR(Dashboard!$C$16="All",K22=Dashboard!$C$16)),1,0) -> 1 | S22: =IF(M22=1,ROW()-1,"") -> 21 | T22: Radisson Blue | U22: Minamark | V22: [ACG8502] RIB Boom arm 4 m. - Ø80mm
A23: Lavista Patios | B23: Rich | C23: Dest windshield tags | D23: 500 | E23: 2555 | F23: =IF(E23="","",D23*E23) -> 1277500 | G23: 46165 | H23: 3 | I23: =IF(OR(G23="",H23=""),"",G23+H23*7) -> 46186 | J23: Not Paid | K23: Pending | L23: =IF(A23="","",IF(OR(G23="",AND(G23>=Dashboard!$C$18,G23<=Dashboard!$C$19)),1,0)) -> 1 | M23: =IF(AND(L23=1,OR(Dashboard!$C$13="All",A23=Dashboard!$C$13),OR(Dashboard!$C$14="All",B23=Dashboard!$C$14),OR(Dashboard!$C$15="All",C23=Dashboard!$C$15),OR(Dashboard!$C$16="All",K23=Dashboard!$C$16),OR(Dashboard!$C$17="All",J23=Dashboard!$C$17)),1,0) -> 1 | N23: =IF(AND(L23=1,OR(Dashboard!$C$13="All",A23=Dashboard!$C$13),OR(Dashboard!$C$14="All",B23=Dashboard!$C$14),OR(Dashboard!$C$16="All",K23=Dashboard!$C$16),OR(Dashboard!$C$17="All",J23=Dashboard!$C$17)),1,0) -> 1 | O23: =IF(AND(L23=1,OR(Dashboard!$C$13="All",A23=Dashboard!$C$13),OR(Dashboard!$C$15="All",C23=Dashboard!$C$15),OR(Dashboard!$C$16="All",K23=Dashboard!$C$16),OR(Dashboard!$C$17="All",J23=Dashboard!$C$17)),1,0) -> 1 | P23: =IF(AND(L23=1,OR(Dashboard!$C$13="All",A23=Dashboard!$C$13),OR(Dashboard!$C$14="All",B23=Dashboard!$C$14),OR(Dashboard!$C$15="All",C23=Dashboard!$C$15),OR(Dashboard!$C$17="All",J23=Dashboard!$C$17)),1,0) -> 1 | Q23: =IF(AND(L23=1,OR(Dashboard!$C$14="All",B23=Dashboard!$C$14),OR(Dashboard!$C$15="All",C23=Dashboard!$C$15),OR(Dashboard!$C$16="All",K23=Dashboard!$C$16),OR(Dashboard!$C$17="All",J23=Dashboard!$C$17)),1,0) -> 1 | R23: =IF(AND(L23=1,OR(Dashboard!$C$13="All",A23=Dashboard!$C$13),OR(Dashboard!$C$14="All",B23=Dashboard!$C$14),OR(Dashboard!$C$15="All",C23=Dashboard!$C$15),OR(Dashboard!$C$16="All",K23=Dashboard!$C$16)),1,0) -> 1 | S23: =IF(M23=1,ROW()-1,"") -> 22 | T23: Prometeon | U23: OGTech Dubai | V23: [BA04011] Mechanical Stopper
A24: Layan | B24: Metalcraft | C24: Dest windshield tags | D24: 5000 | E24: 255 | F24: =IF(E24="","",D24*E24) -> 1275000 | G24: 46166 | H24: 1 | I24: =IF(OR(G24="",H24=""),"",G24+H24*7) -> 46173 | J24: Not Paid | K24: Pending | L24: =IF(A24="","",IF(OR(G24="",AND(G24>=Dashboard!$C$18,G24<=Dashboard!$C$19)),1,0)) -> 1 | M24: =IF(AND(L24=1,OR(Dashboard!$C$13="All",A24=Dashboard!$C$13),OR(Dashboard!$C$14="All",B24=Dashboard!$C$14),OR(Dashboard!$C$15="All",C24=Dashboard!$C$15),OR(Dashboard!$C$16="All",K24=Dashboard!$C$16),OR(Dashboard!$C$17="All",J24=Dashboard!$C$17)),1,0) -> 1 | N24: =IF(AND(L24=1,OR(Dashboard!$C$13="All",A24=Dashboard!$C$13),OR(Dashboard!$C$14="All",B24=Dashboard!$C$14),OR(Dashboard!$C$16="All",K24=Dashboard!$C$16),OR(Dashboard!$C$17="All",J24=Dashboard!$C$17)),1,0) -> 1 | O24: =IF(AND(L24=1,OR(Dashboard!$C$13="All",A24=Dashboard!$C$13),OR(Dashboard!$C$15="All",C24=Dashboard!$C$15),OR(Dashboard!$C$16="All",K24=Dashboard!$C$16),OR(Dashboard!$C$17="All",J24=Dashboard!$C$17)),1,0) -> 1 | P24: =IF(AND(L24=1,OR(Dashboard!$C$13="All",A24=Dashboard!$C$13),OR(Dashboard!$C$14="All",B24=Dashboard!$C$14),OR(Dashboard!$C$15="All",C24=Dashboard!$C$15),OR(Dashboard!$C$17="All",J24=Dashboard!$C$17)),1,0) -> 1 | Q24: =IF(AND(L24=1,OR(Dashboard!$C$14="All",B24=Dashboard!$C$14),OR(Dashboard!$C$15="All",C24=Dashboard!$C$15),OR(Dashboard!$C$16="All",K24=Dashboard!$C$16),OR(Dashboard!$C$17="All",J24=Dashboard!$C$17)),1,0) -> 1 | R24: =IF(AND(L24=1,OR(Dashboard!$C$13="All",A24=Dashboard!$C$13),OR(Dashboard!$C$14="All",B24=Dashboard!$C$14),OR(Dashboard!$C$15="All",C24=Dashboard!$C$15),OR(Dashboard!$C$16="All",K24=Dashboard!$C$16)),1,0) -> 1 | S24: =IF(M24=1,ROW()-1,"") -> 23 | T24: SIDC | U24: Perkotek | V24: [CEL1425] Capacitor 230v
A25: Majid El futtaim | B25: OGTech Dubai | C25: MaxU1002 | D25: 1 | E25: 45 | F25: =IF(E25="","",D25*E25) -> 45 | G25: 46167 | H25: 2 | I25: =IF(OR(G25="",H25=""),"",G25+H25*7) -> 46181 | J25: Advance Payment | K25: Pending | L25: =IF(A25="","",IF(OR(G25="",AND(G25>=Dashboard!$C$18,G25<=Dashboard!$C$19)),1,0)) -> 1 | M25: =IF(AND(L25=1,OR(Dashboard!$C$13="All",A25=Dashboard!$C$13),OR(Dashboard!$C$14="All",B25=Dashboard!$C$14),OR(Dashboard!$C$15="All",C25=Dashboard!$C$15),OR(Dashboard!$C$16="All",K25=Dashboard!$C$16),OR(Dashboard!$C$17="All",J25=Dashboard!$C$17)),1,0) -> 1 | N25: =IF(AND(L25=1,OR(Dashboard!$C$13="All",A25=Dashboard!$C$13),OR(Dashboard!$C$14="All",B25=Dashboard!$C$14),OR(Dashboard!$C$16="All",K25=Dashboard!$C$16),OR(Dashboard!$C$17="All",J25=Dashboard!$C$17)),1,0) -> 1 | O25: =IF(AND(L25=1,OR(Dashboard!$C$13="All",A25=Dashboard!$C$13),OR(Dashboard!$C$15="All",C25=Dashboard!$C$15),OR(Dashboard!$C$16="All",K25=Dashboard!$C$16),OR(Dashboard!$C$17="All",J25=Dashboard!$C$17)),1,0) -> 1 | P25: =IF(AND(L25=1,OR(Dashboard!$C$13="All",A25=Dashboard!$C$13),OR(Dashboard!$C$14="All",B25=Dashboard!$C$14),OR(Dashboard!$C$15="All",C25=Dashboard!$C$15),OR(Dashboard!$C$17="All",J25=Dashboard!$C$17)),1,0) -> 1 | Q25: =IF(AND(L25=1,OR(Dashboard!$C$14="All",B25=Dashboard!$C$14),OR(Dashboard!$C$15="All",C25=Dashboard!$C$15),OR(Dashboard!$C$16="All",K25=Dashboard!$C$16),OR(Dashboard!$C$17="All",J25=Dashboard!$C$17)),1,0) -> 1 | R25: =IF(AND(L25=1,OR(Dashboard!$C$13="All",A25=Dashboard!$C$13),OR(Dashboard!$C$14="All",B25=Dashboard!$C$14),OR(Dashboard!$C$15="All",C25=Dashboard!$C$15),OR(Dashboard!$C$16="All",K25=Dashboard!$C$16)),1,0) -> 1 | S25: =IF(M25=1,ROW()-1,"") -> 24 | T25: SLR-RFID | U25: Promojet | V25: [CEL1425] Capacitor 230v
A26: Majid El futtaim | B26: FEIG | C26: Antenna 270/270 U | D26: 2 | E26: 36 | F26: =IF(E26="","",D26*E26) -> 72 | G26: 46168 | H26: 7 | I26: =IF(OR(G26="",H26=""),"",G26+H26*7) -> 46217 | J26: Fully Paid | K26: Completed | L26: =IF(A26="","",IF(OR(G26="",AND(G26>=Dashboard!$C$18,G26<=Dashboard!$C$19)),1,0)) -> 1 | M26: =IF(AND(L26=1,OR(Dashboard!$C$13="All",A26=Dashboard!$C$13),OR(Dashboard!$C$14="All",B26=Dashboard!$C$14),OR(Dashboard!$C$15="All",C26=Dashboard!$C$15),OR(Dashboard!$C$16="All",K26=Dashboard!$C$16),OR(Dashboard!$C$17="All",J26=Dashboard!$C$17)),1,0) -> 1 | N26: =IF(AND(L26=1,OR(Dashboard!$C$13="All",A26=Dashboard!$C$13),OR(Dashboard!$C$14="All",B26=Dashboard!$C$14),OR(Dashboard!$C$16="All",K26=Dashboard!$C$16),OR(Dashboard!$C$17="All",J26=Dashboard!$C$17)),1,0) -> 1 | O26: =IF(AND(L26=1,OR(Dashboard!$C$13="All",A26=Dashboard!$C$13),OR(Dashboard!$C$15="All",C26=Dashboard!$C$15),OR(Dashboard!$C$16="All",K26=Dashboard!$C$16),OR(Dashboard!$C$17="All",J26=Dashboard!$C$17)),1,0) -> 1 | P26: =IF(AND(L26=1,OR(Dashboard!$C$13="All",A26=Dashboard!$C$13),OR(Dashboard!$C$14="All",B26=Dashboard!$C$14),OR(Dashboard!$C$15="All",C26=Dashboard!$C$15),OR(Dashboard!$C$17="All",J26=Dashboard!$C$17)),1,0) -> 1 | Q26: =IF(AND(L26=1,OR(Dashboard!$C$14="All",B26=Dashboard!$C$14),OR(Dashboard!$C$15="All",C26=Dashboard!$C$15),OR(Dashboard!$C$16="All",K26=Dashboard!$C$16),OR(Dashboard!$C$17="All",J26=Dashboard!$C$17)),1,0) -> 1 | R26: =IF(AND(L26=1,OR(Dashboard!$C$13="All",A26=Dashboard!$C$13),OR(Dashboard!$C$14="All",B26=Dashboard!$C$14),OR(Dashboard!$C$15="All",C26=Dashboard!$C$15),OR(Dashboard!$C$16="All",K26=Dashboard!$C$16)),1,0) -> 1 | S26: =IF(M26=1,ROW()-1,"") -> 25 | T26: Enova | U26: RIB | V26: [EG-437750582-001] LF Cards- Printed
A27: Majid El futtaim | B27: Metalcraft | C27: RFID Destructive WINDSHIELD Tags Printed | D27: 50 | E27: 96 | F27: =IF(E27="","",D27*E27) -> 4800 | G27: 46169 | H27: 2 | I27: =IF(OR(G27="",H27=""),"",G27+H27*7) -> 46183 | J27: Advance Payment | K27: Pending | L27: =IF(A27="","",IF(OR(G27="",AND(G27>=Dashboard!$C$18,G27<=Dashboard!$C$19)),1,0)) -> 1 | M27: =IF(AND(L27=1,OR(Dashboard!$C$13="All",A27=Dashboard!$C$13),OR(Dashboard!$C$14="All",B27=Dashboard!$C$14),OR(Dashboard!$C$15="All",C27=Dashboard!$C$15),OR(Dashboard!$C$16="All",K27=Dashboard!$C$16),OR(Dashboard!$C$17="All",J27=Dashboard!$C$17)),1,0) -> 1 | N27: =IF(AND(L27=1,OR(Dashboard!$C$13="All",A27=Dashboard!$C$13),OR(Dashboard!$C$14="All",B27=Dashboard!$C$14),OR(Dashboard!$C$16="All",K27=Dashboard!$C$16),OR(Dashboard!$C$17="All",J27=Dashboard!$C$17)),1,0) -> 1 | O27: =IF(AND(L27=1,OR(Dashboard!$C$13="All",A27=Dashboard!$C$13),OR(Dashboard!$C$15="All",C27=Dashboard!$C$15),OR(Dashboard!$C$16="All",K27=Dashboard!$C$16),OR(Dashboard!$C$17="All",J27=Dashboard!$C$17)),1,0) -> 1 | P27: =IF(AND(L27=1,OR(Dashboard!$C$13="All",A27=Dashboard!$C$13),OR(Dashboard!$C$14="All",B27=Dashboard!$C$14),OR(Dashboard!$C$15="All",C27=Dashboard!$C$15),OR(Dashboard!$C$17="All",J27=Dashboard!$C$17)),1,0) -> 1 | Q27: =IF(AND(L27=1,OR(Dashboard!$C$14="All",B27=Dashboard!$C$14),OR(Dashboard!$C$15="All",C27=Dashboard!$C$15),OR(Dashboard!$C$16="All",K27=Dashboard!$C$16),OR(Dashboard!$C$17="All",J27=Dashboard!$C$17)),1,0) -> 1 | R27: =IF(AND(L27=1,OR(Dashboard!$C$13="All",A27=Dashboard!$C$13),OR(Dashboard!$C$14="All",B27=Dashboard!$C$14),OR(Dashboard!$C$15="All",C27=Dashboard!$C$15),OR(Dashboard!$C$16="All",K27=Dashboard!$C$16)),1,0) -> 1 | S27: =IF(M27=1,ROW()-1,"") -> 26 | T27: Semiramis | U27: Rich | V27: [OG-00170] UHF cards- printed
... A39: El Patio | B39: El Nekheely | C39: Coaxial 13m | D39: 2 | E39: 15 | F39: =IF(E39="","",D39*E39) -> 30 | G39: 46181 | H39: 5 | I39: =IF(OR(G39="",H39=""),"",G39+H39*7) -> 46216 | J39: Not Paid | K39: Completed | L39: =IF(A39="","",IF(OR(G39="",AND(G39>=Dashboard!$C$18,G39<=Dashboard!$C$19)),1,0)) -> 1 | M39: =IF(AND(L39=1,OR(Dashboard!$C$13="All",A39=Dashboard!$C$13),OR(Dashboard!$C$14="All",B39=Dashboard!$C$14),OR(Dashboard!$C$15="All",C39=Dashboard!$C$15),OR(Dashboard!$C$16="All",K39=Dashboard!$C$16),OR(Dashboard!$C$17="All",J39=Dashboard!$C$17)),1,0) -> 1 | N39: =IF(AND(L39=1,OR(Dashboard!$C$13="All",A39=Dashboard!$C$13),OR(Dashboard!$C$14="All",B39=Dashboard!$C$14),OR(Dashboard!$C$16="All",K39=Dashboard!$C$16),OR(Dashboard!$C$17="All",J39=Dashboard!$C$17)),1,0) -> 1 | O39: =IF(AND(L39=1,OR(Dashboard!$C$13="All",A39=Dashboard!$C$13),OR(Dashboard!$C$15="All",C39=Dashboard!$C$15),OR(Dashboard!$C$16="All",K39=Dashboard!$C$16),OR(Dashboard!$C$17="All",J39=Dashboard!$C$17)),1,0) -> 1 | P39: =IF(AND(L39=1,OR(Dashboard!$C$13="All",A39=Dashboard!$C$13),OR(Dashboard!$C$14="All",B39=Dashboard!$C$14),OR(Dashboard!$C$15="All",C39=Dashboard!$C$15),OR(Dashboard!$C$17="All",J39=Dashboard!$C$17)),1,0) -> 1 | Q39: =IF(AND(L39=1,OR(Dashboard!$C$14="All",B39=Dashboard!$C$14),OR(Dashboard!$C$15="All",C39=Dashboard!$C$15),OR(Dashboard!$C$16="All",K39=Dashboard!$C$16),OR(Dashboard!$C$17="All",J39=Dashboard!$C$17)),1,0) -> 1 | R39: =IF(AND(L39=1,OR(Dashboard!$C$13="All",A39=Dashboard!$C$13),OR(Dashboard!$C$14="All",B39=Dashboard!$C$14),OR(Dashboard!$C$15="All",C39=Dashboard!$C$15),OR(Dashboard!$C$16="All",K39=Dashboard!$C$16)),1,0) -> 1 | S39: =IF(M39=1,ROW()-1,"") -> 38 | T39: Obour institute | U39: zebra | V39: [WWCT03243] CT4−LX TT203 RFID UHF Printer
A40: Bellagio | B40: Tech-Electrique | C40: FAAC Gate B614- 4m | D40: 2 | E40: 45 | F40: =IF(E40="","",D40*E40) -> 90 | G40: 46182 | H40: 8 | I40: =IF(OR(G40="",H40=""),"",G40+H40*7) -> 46238 | J40: Not Paid | K40: Delayed | L40: =IF(A40="","",IF(OR(G40="",AND(G40>=Dashboard!$C$18,G40<=Dashboard!$C$19)),1,0)) -> 1 | M40: =IF(AND(L40=1,OR(Dashboard!$C$13="All",A40=Dashboard!$C$13),OR(Dashboard!$C$14="All",B40=Dashboard!$C$14),OR(Dashboard!$C$15="All",C40=Dashboard!$C$15),OR(Dashboard!$C$16="All",K40=Dashboard!$C$16),OR(Dashboard!$C$17="All",J40=Dashboard!$C$17)),1,0) -> 1 | N40: =IF(AND(L40=1,OR(Dashboard!$C$13="All",A40=Dashboard!$C$13),OR(Dashboard!$C$14="All",B40=Dashboard!$C$14),OR(Dashboard!$C$16="All",K40=Dashboard!$C$16),OR(Dashboard!$C$17="All",J40=Dashboard!$C$17)),1,0) -> 1 | O40: =IF(AND(L40=1,OR(Dashboard!$C$13="All",A40=Dashboard!$C$13),OR(Dashboard!$C$15="All",C40=Dashboard!$C$15),OR(Dashboard!$C$16="All",K40=Dashboard!$C$16),OR(Dashboard!$C$17="All",J40=Dashboard!$C$17)),1,0) -> 1 | P40: =IF(AND(L40=1,OR(Dashboard!$C$13="All",A40=Dashboard!$C$13),OR(Dashboard!$C$14="All",B40=Dashboard!$C$14),OR(Dashboard!$C$15="All",C40=Dashboard!$C$15),OR(Dashboard!$C$17="All",J40=Dashboard!$C$17)),1,0) -> 1 | Q40: =IF(AND(L40=1,OR(Dashboard!$C$14="All",B40=Dashboard!$C$14),OR(Dashboard!$C$15="All",C40=Dashboard!$C$15),OR(Dashboard!$C$16="All",K40=Dashboard!$C$16),OR(Dashboard!$C$17="All",J40=Dashboard!$C$17)),1,0) -> 1 | R40: =IF(AND(L40=1,OR(Dashboard!$C$13="All",A40=Dashboard!$C$13),OR(Dashboard!$C$14="All",B40=Dashboard!$C$14),OR(Dashboard!$C$15="All",C40=Dashboard!$C$15),OR(Dashboard!$C$16="All",K40=Dashboard!$C$16)),1,0) -> 1 | S40: =IF(M40=1,ROW()-1,"") -> 39 | T40: Obour university | V40: [WWFX31243] FX3-LX SATO Food Printer
A41: Bellagio | B41: Tech-Electrique | C41: Control Board of Barrier FAAC B614 | D41: 1 | E41: 24 | F41: =IF(E41="","",D41*E41) -> 24 | G41: 46183 | H41: 5 | I41: =IF(OR(G41="",H41=""),"",G41+H41*7) -> 46218 | J41: Not Paid | K41: Pending | L41: =IF(A41="","",IF(OR(G41="",AND(G41>=Dashboard!$C$18,G41<=Dashboard!$C$19)),1,0)) -> 1 | M41: =IF(AND(L41=1,OR(Dashboard!$C$13="All",A41=Dashboard!$C$13),OR(Dashboard!$C$14="All",B41=Dashboard!$C$14),OR(Dashboard!$C$15="All",C41=Dashboard!$C$15),OR(Dashboard!$C$16="All",K41=Dashboard!$C$16),OR(Dashboard!$C$17="All",J41=Dashboard!$C$17)),1,0) -> 1 | N41: =IF(AND(L41=1,OR(Dashboard!$C$13="All",A41=Dashboard!$C$13),OR(Dashboard!$C$14="All",B41=Dashboard!$C$14),OR(Dashboard!$C$16="All",K41=Dashboard!$C$16),OR(Dashboard!$C$17="All",J41=Dashboard!$C$17)),1,0) -> 1 | O41: =IF(AND(L41=1,OR(Dashboard!$C$13="All",A41=Dashboard!$C$13),OR(Dashboard!$C$15="All",C41=Dashboard!$C$15),OR(Dashboard!$C$16="All",K41=Dashboard!$C$16),OR(Dashboard!$C$17="All",J41=Dashboard!$C$17)),1,0) -> 1 | P41: =IF(AND(L41=1,OR(Dashboard!$C$13="All",A41=Dashboard!$C$13),OR(Dashboard!$C$14="All",B41=Dashboard!$C$14),OR(Dashboard!$C$15="All",C41=Dashboard!$C$15),OR(Dashboard!$C$17="All",J41=Dashboard!$C$17)),1,0) -> 1 | Q41: =IF(AND(L41=1,OR(Dashboard!$C$14="All",B41=Dashboard!$C$14),OR(Dashboard!$C$15="All",C41=Dashboard!$C$15),OR(Dashboard!$C$16="All",K41=Dashboard!$C$16),OR(Dashboard!$C$17="All",J41=Dashboard!$C$17)),1,0) -> 1 | R41: =IF(AND(L41=1,OR(Dashboard!$C$13="All",A41=Dashboard!$C$13),OR(Dashboard!$C$14="All",B41=Dashboard!$C$14),OR(Dashboard!$C$15="All",C41=Dashboard!$C$15),OR(Dashboard!$C$16="All",K41=Dashboard!$C$16)),1,0) -> 1 | S41: =IF(M41=1,ROW()-1,"") -> 40 | T41: Tanmyah | V41: [Y10110600011] Special Ribbons for SATO Desktop Printer
A42: AlBurouj | C42: FAAC Boom- 3m | D42: 1 | E42: 25 | F42: =IF(E42="","",D42*E42) -> 25 | G42: 46184 | H42: 6 | I42: =IF(OR(G42="",H42=""),"",G42+H42*7) -> 46226 | J42: Not Paid | K42: Completed | L42: =IF(A42="","",IF(OR(G42="",AND(G42>=Dashboard!$C$18,G42<=Dashboard!$C$19)),1,0)) -> 1 | M42: =IF(AND(L42=1,OR(Dashboard!$C$13="All",A42=Dashboard!$C$13),OR(Dashboard!$C$14="All",B42=Dashboard!$C$14),OR(Dashboard!$C$15="All",C42=Dashboard!$C$15),OR(Dashboard!$C$16="All",K42=Dashboard!$C$16),OR(Dashboard!$C$17="All",J42=Dashboard!$C$17)),1,0) -> 1 | N42: =IF(AND(L42=1,OR(Dashboard!$C$13="All",A42=Dashboard!$C$13),OR(Dashboard!$C$14="All",B42=Dashboard!$C$14),OR(Dashboard!$C$16="All",K42=Dashboard!$C$16),OR(Dashboard!$C$17="All",J42=Dashboard!$C$17)),1,0) -> 1 | O42: =IF(AND(L42=1,OR(Dashboard!$C$13="All",A42=Dashboard!$C$13),OR(Dashboard!$C$15="All",C42=Dashboard!$C$15),OR(Dashboard!$C$16="All",K42=Dashboard!$C$16),OR(Dashboard!$C$17="All",J42=Dashboard!$C$17)),1,0) -> 1 | P42: =IF(AND(L42=1,OR(Dashboard!$C$13="All",A42=Dashboard!$C$13),OR(Dashboard!$C$14="All",B42=Dashboard!$C$14),OR(Dashboard!$C$15="All",C42=Dashboard!$C$15),OR(Dashboard!$C$17="All",J42=Dashboard!$C$17)),1,0) -> 1 | Q42: =IF(AND(L42=1,OR(Dashboard!$C$14="All",B42=Dashboard!$C$14),OR(Dashboard!$C$15="All",C42=Dashboard!$C$15),OR(Dashboard!$C$16="All",K42=Dashboard!$C$16),OR(Dashboard!$C$17="All",J42=Dashboard!$C$17)),1,0) -> 1 | R42: =IF(AND(L42=1,OR(Dashboard!$C$13="All",A42=Dashboard!$C$13),OR(Dashboard!$C$14="All",B42=Dashboard!$C$14),OR(Dashboard!$C$15="All",C42=Dashboard!$C$15),OR(Dashboard!$C$16="All",K42=Dashboard!$C$16)),1,0) -> 1 | S42: =IF(M42=1,ROW()-1,"") -> 41 | T42: La Hacienda | V42: [Zebra Z-ULTIMATE 3000T] 3000T WHITE 82.55 x 37.3062 outside core Diameter 31.75, Labels per Roll 2000
A43: AlBurouj | B43: Local | C43: Automatic switch | D43: 1 | E43: 36 | F43: =IF(E43="","",D43*E43) -> 36 | G43: 46185 | H43: 9 | I43: =IF(OR(G43="",H43=""),"",G43+H43*7) -> 46248 | J43: Not Paid | K43: Pending | L43: =IF(A43="","",IF(OR(G43="",AND(G43>=Dashboard!$C$18,G43<=Dashboard!$C$19)),1,0)) -> 1 | M43: =IF(AND(L43=1,OR(Dashboard!$C$13="All",A43=Dashboard!$C$13),OR(Dashboard!$C$14="All",B43=Dashboard!$C$14),OR(Dashboard!$C$15="All",C43=Dashboard!$C$15),OR(Dashboard!$C$16="All",K43=Dashboard!$C$16),OR(Dashboard!$C$17="All",J43=Dashboard!$C$17)),1,0) -> 1 | N43: =IF(AND(L43=1,OR(Dashboard!$C$13="All",A43=Dashboard!$C$13),OR(Dashboard!$C$14="All",B43=Dashboard!$C$14),OR(Dashboard!$C$16="All",K43=Dashboard!$C$16),OR(Dashboard!$C$17="All",J43=Dashboard!$C$17)),1,0) -> 1 | O43: =IF(AND(L43=1,OR(Dashboard!$C$13="All",A43=Dashboard!$C$13),OR(Dashboard!$C$15="All",C43=Dashboard!$C$15),OR(Dashboard!$C$16="All",K43=Dashboard!$C$16),OR(Dashboard!$C$17="All",J43=Dashboard!$C$17)),1,0) -> 1 | P43: =IF(AND(L43=1,OR(Dashboard!$C$13="All",A43=Dashboard!$C$13),OR(Dashboard!$C$14="All",B43=Dashboard!$C$14),OR(Dashboard!$C$15="All",C43=Dashboard!$C$15),OR(Dashboard!$C$17="All",J43=Dashboard!$C$17)),1,0) -> 1 | Q43: =IF(AND(L43=1,OR(Dashboard!$C$14="All",B43=Dashboard!$C$14),OR(Dashboard!$C$15="All",C43=Dashboard!$C$15),OR(Dashboard!$C$16="All",K43=Dashboard!$C$16),OR(Dashboard!$C$17="All",J43=Dashboard!$C$17)),1,0) -> 1 | R43: =IF(AND(L43=1,OR(Dashboard!$C$13="All",A43=Dashboard!$C$13),OR(Dashboard!$C$14="All",B43=Dashboard!$C$14),OR(Dashboard!$C$15="All",C43=Dashboard!$C$15),OR(Dashboard!$C$16="All",K43=Dashboard!$C$16)),1,0) -> 1 | S43: =IF(M43=1,ROW()-1,"") -> 42 | T43: Marina | V43: A5 Paper Sticker Label - Blank
A44: Suez Canal Bank | B44: RICH RFID | C44: UHF On metal tags | D44: 3000 | E44: 95 | F44: =IF(E44="","",D44*E44) -> 285000 | G44: 46186 | H44: 9 | I44: =IF(OR(G44="",H44=""),"",G44+H44*7) -> 46249 | J44: Not Paid | K44: In Progress | L44: =IF(A44="","",IF(OR(G44="",AND(G44>=Dashboard!$C$18,G44<=Dashboard!$C$19)),1,0)) -> 1 | M44: =IF(AND(L44=1,OR(Dashboard!$C$13="All",A44=Dashboard!$C$13),OR(Dashboard!$C$14="All",B44=Dashboard!$C$14),OR(Dashboard!$C$15="All",C44=Dashboard!$C$15),OR(Dashboard!$C$16="All",K44=Dashboard!$C$16),OR(Dashboard!$C$17="All",J44=Dashboard!$C$17)),1,0) -> 1 | N44: =IF(AND(L44=1,OR(Dashboard!$C$13="All",A44=Dashboard!$C$13),OR(Dashboard!$C$14="All",B44=Dashboard!$C$14),OR(Dashboard!$C$16="All",K44=Dashboard!$C$16),OR(Dashboard!$C$17="All",J44=Dashboard!$C$17)),1,0) -> 1 | O44: =IF(AND(L44=1,OR(Dashboard!$C$13="All",A44=Dashboard!$C$13),OR(Dashboard!$C$15="All",C44=Dashboard!$C$15),OR(Dashboard!$C$16="All",K44=Dashboard!$C$16),OR(Dashboard!$C$17="All",J44=Dashboard!$C$17)),1,0) -> 1 | P44: =IF(AND(L44=1,OR(Dashboard!$C$13="All",A44=Dashboard!$C$13),OR(Dashboard!$C$14="All",B44=Dashboard!$C$14),OR(Dashboard!$C$15="All",C44=Dashboard!$C$15),OR(Dashboard!$C$17="All",J44=Dashboard!$C$17)),1,0) -> 1 | Q44: =IF(AND(L44=1,OR(Dashboard!$C$14="All",B44=Dashboard!$C$14),OR(Dashboard!$C$15="All",C44=Dashboard!$C$15),OR(Dashboard!$C$16="All",K44=Dashboard!$C$16),OR(Dashboard!$C$17="All",J44=Dashboard!$C$17)),1,0) -> 1 | R44: =IF(AND(L44=1,OR(Dashboard!$C$13="All",A44=Dashboard!$C$13),OR(Dashboard!$C$14="All",B44=Dashboard!$C$14),OR(Dashboard!$C$15="All",C44=Dashboard!$C$15),OR(Dashboard!$C$16="All",K44=Dashboard!$C$16)),1,0) -> 1 | S44: =IF(M44=1,ROW()-1,"") -> 43 | T44: Marbella | V44: Adapter 12V
A45: Akoya | B45: Metalcraft | C45: Dest windshield tags | D45: 300 | E45: 574 | F45: =IF(E45="","",D45*E45) -> 172200 | G45: 46187 | H45: 9 | I45: =IF(OR(G45="",H45=""),"",G45+H45*7) -> 46250 | J45: Not Paid | K45: Completed | L45: =IF(A45="","",IF(OR(G45="",AND(G45>=Dashboard!$C$18,G45<=Dashboard!$C$19)),1,0)) -> 1 | M45: =IF(AND(L45=1,OR(Dashboard!$C$13="All",A45=Dashboard!$C$13),OR(Dashboard!$C$14="All",B45=Dashboard!$C$14),OR(Dashboard!$C$15="All",C45=Dashboard!$C$15),OR(Dashboard!$C$16="All",K45=Dashboard!$C$16),OR(Dashboard!$C$17="All",J45=Dashboard!$C$17)),1,0) -> 1 | N45: =IF(AND(L45=1,OR(Dashboard!$C$13="All",A45=Dashboard!$C$13),OR(Dashboard!$C$14="All",B45=Dashboard!$C$14),OR(Dashboard!$C$16="All",K45=Dashboard!$C$16),OR(Dashboard!$C$17="All",J45=Dashboard!$C$17)),1,0) -> 1 | O45: =IF(AND(L45=1,OR(Dashboard!$C$13="All",A45=Dashboard!$C$13),OR(Dashboard!$C$15="All",C45=Dashboard!$C$15),OR(Dashboard!$C$16="All",K45=Dashboard!$C$16),OR(Dashboard!$C$17="All",J45=Dashboard!$C$17)),1,0) -> 1 | P45: =IF(AND(L45=1,OR(Dashboard!$C$13="All",A45=Dashboard!$C$13),OR(Dashboard!$C$14="All",B45=Dashboard!$C$14),OR(Dashboard!$C$15="All",C45=Dashboard!$C$15),OR(Dashboard!$C$17="All",J45=Dashboard!$C$17)),1,0) -> 1 | Q45: =IF(AND(L45=1,OR(Dashboard!$C$14="All",B45=Dashboard!$C$14),OR(Dashboard!$C$15="All",C45=Dashboard!$C$15),OR(Dashboard!$C$16="All",K45=Dashboard!$C$16),OR(Dashboard!$C$17="All",J45=Dashboard!$C$17)),1,0) -> 1 | R45: =IF(AND(L45=1,OR(Dashboard!$C$13="All",A45=Dashboard!$C$13),OR(Dashboard!$C$14="All",B45=Dashboard!$C$14),OR(Dashboard!$C$15="All",C45=Dashboard!$C$15),OR(Dashboard!$C$16="All",K45=Dashboard!$C$16)),1,0) -> 1 | S45: =IF(M45=1,ROW()-1,"") -> 44 | T45: El-Shorouk | V45: Adapter 24V
A46: Marshmallow | C46: Max50.10 | D46: 1 | E46: 558 | F46: =IF(E46="","",D46*E46) -> 558 | G46: 46188 | H46: 9 | I46: =IF(OR(G46="",H46=""),"",G46+H46*7) -> 46251 | J46: Not Paid | K46: Completed | L46: =IF(A46="","",IF(OR(G46="",AND(G46>=Dashboard!$C$18,G46<=Dashboard!$C$19)),1,0)) -> 1 | M46: =IF(AND(L46=1,OR(Dashboard!$C$13="All",A46=Dashboard!$C$13),OR(Dashboard!$C$14="All",B46=Dashboard!$C$14),OR(Dashboard!$C$15="All",C46=Dashboard!$C$15),OR(Dashboard!$C$16="All",K46=Dashboard!$C$16),OR(Dashboard!$C$17="All",J46=Dashboard!$C$17)),1,0) -> 1 | N46: =IF(AND(L46=1,OR(Dashboard!$C$13="All",A46=Dashboard!$C$13),OR(Dashboard!$C$14="All",B46=Dashboard!$C$14),OR(Dashboard!$C$16="All",K46=Dashboard!$C$16),OR(Dashboard!$C$17="All",J46=Dashboard!$C$17)),1,0) -> 1 | O46: =IF(AND(L46=1,OR(Dashboard!$C$13="All",A46=Dashboard!$C$13),OR(Dashboard!$C$15="All",C46=Dashboard!$C$15),OR(Dashboard!$C$16="All",K46=Dashboard!$C$16),OR(Dashboard!$C$17="All",J46=Dashboard!$C$17)),1,0) -> 1 | P46: =IF(AND(L46=1,OR(Dashboard!$C$13="All",A46=Dashboard!$C$13),OR(Dashboard!$C$14="All",B46=Dashboard!$C$14),OR(Dashboard!$C$15="All",C46=Dashboard!$C$15),OR(Dashboard!$C$17="All",J46=Dashboard!$C$17)),1,0) -> 1 | Q46: =IF(AND(L46=1,OR(Dashboard!$C$14="All",B46=Dashboard!$C$14),OR(Dashboard!$C$15="All",C46=Dashboard!$C$15),OR(Dashboard!$C$16="All",K46=Dashboard!$C$16),OR(Dashboard!$C$17="All",J46=Dashboard!$C$17)),1,0) -> 1 | R46: =IF(AND(L46=1,OR(Dashboard!$C$13="All",A46=Dashboard!$C$13),OR(Dashboard!$C$14="All",B46=Dashboard!$C$14),OR(Dashboard!$C$15="All",C46=Dashboard!$C$15),OR(Dashboard!$C$16="All",K46=Dashboard!$C$16)),1,0) -> 1 | S46: =IF(M46=1,ROW()-1,"") -> 45 | T46: Diamond Palace | V46: Adapter and charging cable
A47: Marshmallow | C47: Power reader 24V | D47: 1 | E47: 2265 | F47: =IF(E47="","",D47*E47) -> 2265 | G47: 46189 | H47: 9 | I47: =IF(OR(G47="",H47=""),"",G47+H47*7) -> 46252 | J47: Not Paid | K47: Pending | L47: =IF(A47="","",IF(OR(G47="",AND(G47>=Dashboard!$C$18,G47<=Dashboard!$C$19)),1,0)) -> 1 | M47: =IF(AND(L47=1,OR(Dashboard!$C$13="All",A47=Dashboard!$C$13),OR(Dashboard!$C$14="All",B47=Dashboard!$C$14),OR(Dashboard!$C$15="All",C47=Dashboard!$C$15),OR(Dashboard!$C$16="All",K47=Dashboard!$C$16),OR(Dashboard!$C$17="All",J47=Dashboard!$C$17)),1,0) -> 1 | N47: =IF(AND(L47=1,OR(Dashboard!$C$13="All",A47=Dashboard!$C$13),OR(Dashboard!$C$14="All",B47=Dashboard!$C$14),OR(Dashboard!$C$16="All",K47=Dashboard!$C$16),OR(Dashboard!$C$17="All",J47=Dashboard!$C$17)),1,0) -> 1 | O47: =IF(AND(L47=1,OR(Dashboard!$C$13="All",A47=Dashboard!$C$13),OR(Dashboard!$C$15="All",C47=Dashboard!$C$15),OR(Dashboard!$C$16="All",K47=Dashboard!$C$16),OR(Dashboard!$C$17="All",J47=Dashboard!$C$17)),1,0) -> 1 | P47: =IF(AND(L47=1,OR(Dashboard!$C$13="All",A47=Dashboard!$C$13),OR(Dashboard!$C$14="All",B47=Dashboard!$C$14),OR(Dashboard!$C$15="All",C47=Dashboard!$C$15),OR(Dashboard!$C$17="All",J47=Dashboard!$C$17)),1,0) -> 1 | Q47: =IF(AND(L47=1,OR(Dashboard!$C$14="All",B47=Dashboard!$C$14),OR(Dashboard!$C$15="All",C47=Dashboard!$C$15),OR(Dashboard!$C$16="All",K47=Dashboard!$C$16),OR(Dashboard!$C$17="All",J47=Dashboard!$C$17)),1,0) -> 1 | R47: =IF(AND(L47=1,OR(Dashboard!$C$13="All",A47=Dashboard!$C$13),OR(Dashboard!$C$14="All",B47=Dashboard!$C$14),OR(Dashboard!$C$15="All",C47=Dashboard!$C$15),OR(Dashboard!$C$16="All",K47=Dashboard!$C$16)),1,0) -> 1 | S47: =IF(M47=1,ROW()-1,"") -> 46 | T47: Dreamland | V47: adaptor12 v
A48: Marshmallow | C48: Electric lock | D48: 1 | E48: 45 | F48: =IF(E48="","",D48*E48) -> 45 | G48: 46190 | H48: 7 | I48: =IF(OR(G48="",H48=""),"",G48+H48*7) -> 46239 | J48: Not Paid | K48: In Progress | L48: =IF(A48="","",IF(OR(G48="",AND(G48>=Dashboard!$C$18,G48<=Dashboard!$C$19)),1,0)) -> 1 | M48: =IF(AND(L48=1,OR(Dashboard!$C$13="All",A48=Dashboard!$C$13),OR(Dashboard!$C$14="All",B48=Dashboard!$C$14),OR(Dashboard!$C$15="All",C48=Dashboard!$C$15),OR(Dashboard!$C$16="All",K48=Dashboard!$C$16),OR(Dashboard!$C$17="All",J48=Dashboard!$C$17)),1,0) -> 1 | N48: =IF(AND(L48=1,OR(Dashboard!$C$13="All",A48=Dashboard!$C$13),OR(Dashboard!$C$14="All",B48=Dashboard!$C$14),OR(Dashboard!$C$16="All",K48=Dashboard!$C$16),OR(Dashboard!$C$17="All",J48=Dashboard!$C$17)),1,0) -> 1 | O48: =IF(AND(L48=1,OR(Dashboard!$C$13="All",A48=Dashboard!$C$13),OR(Dashboard!$C$15="All",C48=Dashboard!$C$15),OR(Dashboard!$C$16="All",K48=Dashboard!$C$16),OR(Dashboard!$C$17="All",J48=Dashboard!$C$17)),1,0) -> 1 | P48: =IF(AND(L48=1,OR(Dashboard!$C$13="All",A48=Dashboard!$C$13),OR(Dashboard!$C$14="All",B48=Dashboard!$C$14),OR(Dashboard!$C$15="All",C48=Dashboard!$C$15),OR(Dashboard!$C$17="All",J48=Dashboard!$C$17)),1,0) -> 1 | Q48: =IF(AND(L48=1,OR(Dashboard!$C$14="All",B48=Dashboard!$C$14),OR(Dashboard!$C$15="All",C48=Dashboard!$C$15),OR(Dashboard!$C$16="All",K48=Dashboard!$C$16),OR(Dashboard!$C$17="All",J48=Dashboard!$C$17)),1,0) -> 1 | R48: =IF(AND(L48=1,OR(Dashboard!$C$13="All",A48=Dashboard!$C$13),OR(Dashboard!$C$14="All",B48=Dashboard!$C$14),OR(Dashboard!$C$15="All",C48=Dashboard!$C$15),OR(Dashboard!$C$16="All",K48=Dashboard!$C$16)),1,0) -> 1 | S48: =IF(M48=1,ROW()-1,"") -> 47 | T48: Maraqia | V48: Advantech industrial PC IPC-610H
A49: Marshmallow | C49: Push button | D49: 1 | E49: 5554 | F49: =IF(E49="","",D49*E49) -> 5554 | G49: 46191 | H49: 10 | I49: =IF(OR(G49="",H49=""),"",G49+H49*7) -> 46261 | J49: Not Paid | K49: Completed | L49: =IF(A49="","",IF(OR(G49="",AND(G49>=Dashboard!$C$18,G49<=Dashboard!$C$19)),1,0)) -> 1 | M49: =IF(AND(L49=1,OR(Dashboard!$C$13="All",A49=Dashboard!$C$13),OR(Dashboard!$C$14="All",B49=Dashboard!$C$14),OR(Dashboard!$C$15="All",C49=Dashboard!$C$15),OR(Dashboard!$C$16="All",K49=Dashboard!$C$16),OR(Dashboard!$C$17="All",J49=Dashboard!$C$17)),1,0) -> 1 | N49: =IF(AND(L49=1,OR(Dashboard!$C$13="All",A49=Dashboard!$C$13),OR(Dashboard!$C$14="All",B49=Dashboard!$C$14),OR(Dashboard!$C$16="All",K49=Dashboard!$C$16),OR(Dashboard!$C$17="All",J49=Dashboard!$C$17)),1,0) -> 1 | O49: =IF(AND(L49=1,OR(Dashboard!$C$13="All",A49=Dashboard!$C$13),OR(Dashboard!$C$15="All",C49=Dashboard!$C$15),OR(Dashboard!$C$16="All",K49=Dashboard!$C$16),OR(Dashboard!$C$17="All",J49=Dashboard!$C$17)),1,0) -> 1 | P49: =IF(AND(L49=1,OR(Dashboard!$C$13="All",A49=Dashboard!$C$13),OR(Dashboard!$C$14="All",B49=Dashboard!$C$14),OR(Dashboard!$C$15="All",C49=Dashboard!$C$15),OR(Dashboard!$C$17="All",J49=Dashboard!$C$17)),1,0) -> 1 | Q49: =IF(AND(L49=1,OR(Dashboard!$C$14="All",B49=Dashboard!$C$14),OR(Dashboard!$C$15="All",C49=Dashboard!$C$15),OR(Dashboard!$C$16="All",K49=Dashboard!$C$16),OR(Dashboard!$C$17="All",J49=Dashboard!$C$17)),1,0) -> 1 | R49: =IF(AND(L49=1,OR(Dashboard!$C$13="All",A49=Dashboard!$C$13),OR(Dashboard!$C$14="All",B49=Dashboard!$C$14),OR(Dashboard!$C$15="All",C49=Dashboard!$C$15),OR(Dashboard!$C$16="All",K49=Dashboard!$C$16)),1,0) -> 1 | S49: =IF(M49=1,ROW()-1,"") -> 48 | T49: July | V49: AN480 Antenna
A50: Marshmallow | C50: HF Cards | D50: 50 | E50: 41 | F50: =IF(E50="","",D50*E50) -> 2050 | G50: 46192 | H50: 9 | I50: =IF(OR(G50="",H50=""),"",G50+H50*7) -> 46255 | J50: Not Paid | K50: Delayed | L50: =IF(A50="","",IF(OR(G50="",AND(G50>=Dashboard!$C$18,G50<=Dashboard!$C$19)),1,0)) -> 1 | M50: =IF(AND(L50=1,OR(Dashboard!$C$13="All",A50=Dashboard!$C$13),OR(Dashboard!$C$14="All",B50=Dashboard!$C$14),OR(Dashboard!$C$15="All",C50=Dashboard!$C$15),OR(Dashboard!$C$16="All",K50=Dashboard!$C$16),OR(Dashboard!$C$17="All",J50=Dashboard!$C$17)),1,0) -> 1 | N50: =IF(AND(L50=1,OR(Dashboard!$C$13="All",A50=Dashboard!$C$13),OR(Dashboard!$C$14="All",B50=Dashboard!$C$14),OR(Dashboard!$C$16="All",K50=Dashboard!$C$16),OR(Dashboard!$C$17="All",J50=Dashboard!$C$17)),1,0) -> 1 | O50: =IF(AND(L50=1,OR(Dashboard!$C$13="All",A50=Dashboard!$C$13),OR(Dashboard!$C$15="All",C50=Dashboard!$C$15),OR(Dashboard!$C$16="All",K50=Dashboard!$C$16),OR(Dashboard!$C$17="All",J50=Dashboard!$C$17)),1,0) -> 1 | P50: =IF(AND(L50=1,OR(Dashboard!$C$13="All",A50=Dashboard!$C$13),OR(Dashboard!$C$14="All",B50=Dashboard!$C$14),OR(Dashboard!$C$15="All",C50=Dashboard!$C$15),OR(Dashboard!$C$17="All",J50=Dashboard!$C$17)),1,0) -> 1 | Q50: =IF(AND(L50=1,OR(Dashboard!$C$14="All",B50=Dashboard!$C$14),OR(Dashboard!$C$15="All",C50=Dashboard!$C$15),OR(Dashboard!$C$16="All",K50=Dashboard!$C$16),OR(Dashboard!$C$17="All",J50=Dashboard!$C$17)),1,0) -> 1 | R50: =IF(AND(L50=1,OR(Dashboard!$C$13="All",A50=Dashboard!$C$13),OR(Dashboard!$C$14="All",B50=Dashboard!$C$14),OR(Dashboard!$C$15="All",C50=Dashboard!$C$15),OR(Dashboard!$C$16="All",K50=Dashboard!$C$16)),1,0) -> 1 | S50: =IF(M50=1,ROW()-1,"") -> 49 | T50: DANLESCO | V50: ANT 270
A51: Karma | B51: FEIG | C51: MRU102-POE | D51: 2 | E51: 231 | F51: =IF(E51="","",D51*E51) -> 462 | G51: 46193 | H51: 9 | I51: =IF(OR(G51="",H51=""),"",G51+H51*7) -> 46256 | J51: Not Paid | K51: Pending | L51: =IF(A51="","",IF(OR(G51="",AND(G51>=Dashboard!$C$18,G51<=Dashboard!$C$19)),1,0)) -> 1 | M51: =IF(AND(L51=1,OR(Dashboard!$C$13="All",A51=Dashboard!$C$13),OR(Dashboard!$C$14="All",B51=Dashboard!$C$14),OR(Dashboard!$C$15="All",C51=Dashboard!$C$15),OR(Dashboard!$C$16="All",K51=Dashboard!$C$16),OR(Dashboard!$C$17="All",J51=Dashboard!$C$17)),1,0) -> 1 | N51: =IF(AND(L51=1,OR(Dashboard!$C$13="All",A51=Dashboard!$C$13),OR(Dashboard!$C$14="All",B51=Dashboard!$C$14),OR(Dashboard!$C$16="All",K51=Dashboard!$C$16),OR(Dashboard!$C$17="All",J51=Dashboard!$C$17)),1,0) -> 1 | O51: =IF(AND(L51=1,OR(Dashboard!$C$13="All",A51=Dashboard!$C$13),OR(Dashboard!$C$15="All",C51=Dashboard!$C$15),OR(Dashboard!$C$16="All",K51=Dashboard!$C$16),OR(Dashboard!$C$17="All",J51=Dashboard!$C$17)),1,0) -> 1 | P51: =IF(AND(L51=1,OR(Dashboard!$C$13="All",A51=Dashboard!$C$13),OR(Dashboard!$C$14="All",B51=Dashboard!$C$14),OR(Dashboard!$C$15="All",C51=Dashboard!$C$15),OR(Dashboard!$C$17="All",J51=Dashboard!$C$17)),1,0) -> 1 | Q51: =IF(AND(L51=1,OR(Dashboard!$C$14="All",B51=Dashboard!$C$14),OR(Dashboard!$C$15="All",C51=Dashboard!$C$15),OR(Dashboard!$C$16="All",K51=Dashboard!$C$16),OR(Dashboard!$C$17="All",J51=Dashboard!$C$17)),1,0) -> 1 | R51: =IF(AND(L51=1,OR(Dashboard!$C$13="All",A51=Dashboard!$C$13),OR(Dashboard!$C$14="All",B51=Dashboard!$C$14),OR(Dashboard!$C$15="All",C51=Dashboard!$C$15),OR(Dashboard!$C$16="All",K51=Dashboard!$C$16)),1,0) -> 1 | S51: =IF(M51=1,ROW()-1,"") -> 50 | T51: Al Borouj | V51: ANT.U290/290
A52: Geera | B52: RIB | C52: spring rubber | D52: 1 | E52: 25 | F52: =IF(E52="","",D52*E52) -> 25 | G52: 46194 | H52: 9 | I52: =IF(OR(G52="",H52=""),"",G52+H52*7) -> 46257 | J52: Not Paid | K52: Pending | L52: =IF(A52="","",IF(OR(G52="",AND(G52>=Dashboard!$C$18,G52<=Dashboard!$C$19)),1,0)) -> 1 | M52: =IF(AND(L52=1,OR(Dashboard!$C$13="All",A52=Dashboard!$C$13),OR(Dashboard!$C$14="All",B52=Dashboard!$C$14),OR(Dashboard!$C$15="All",C52=Dashboard!$C$15),OR(Dashboard!$C$16="All",K52=Dashboard!$C$16),OR(Dashboard!$C$17="All",J52=Dashboard!$C$17)),1,0) -> 1 | N52: =IF(AND(L52=1,OR(Dashboard!$C$13="All",A52=Dashboard!$C$13),OR(Dashboard!$C$14="All",B52=Dashboard!$C$14),OR(Dashboard!$C$16="All",K52=Dashboard!$C$16),OR(Dashboard!$C$17="All",J52=Dashboard!$C$17)),1,0) -> 1 | O52: =IF(AND(L52=1,OR(Dashboard!$C$13="All",A52=Dashboard!$C$13),OR(Dashboard!$C$15="All",C52=Dashboard!$C$15),OR(Dashboard!$C$16="All",K52=Dashboard!$C$16),OR(Dashboard!$C$17="All",J52=Dashboard!$C$17)),1,0) -> 1 | P52: =IF(AND(L52=1,OR(Dashboard!$C$13="All",A52=Dashboard!$C$13),OR(Dashboard!$C$14="All",B52=Dashboard!$C$14),OR(Dashboard!$C$15="All",C52=Dashboard!$C$15),OR(Dashboard!$C$17="All",J52=Dashboard!$C$17)),1,0) -> 1 | Q52: =IF(AND(L52=1,OR(Dashboard!$C$14="All",B52=Dashboard!$C$14),OR(Dashboard!$C$15="All",C52=Dashboard!$C$15),OR(Dashboard!$C$16="All",K52=Dashboard!$C$16),OR(Dashboard!$C$17="All",J52=Dashboard!$C$17)),1,0) -> 1 | R52: =IF(AND(L52=1,OR(Dashboard!$C$13="All",A52=Dashboard!$C$13),OR(Dashboard!$C$14="All",B52=Dashboard!$C$14),OR(Dashboard!$C$15="All",C52=Dashboard!$C$15),OR(Dashboard!$C$16="All",K52=Dashboard!$C$16)),1,0) -> 1 | S52: =IF(M52=1,ROW()-1,"") -> 51 | T52: Amigo | V52: Antenna
A53: Geera | B53: RIB | C53: Spring blue | D53: 1 | E53: 245 | F53: =IF(E53="","",D53*E53) -> 245 | G53: 46195 | H53: 7 | I53: =IF(OR(G53="",H53=""),"",G53+H53*7) -> 46244 | J53: Not Paid | K53: Completed | L53: =IF(A53="","",IF(OR(G53="",AND(G53>=Dashboard!$C$18,G53<=Dashboard!$C$19)),1,0)) -> 1 | M53: =IF(AND(L53=1,OR(Dashboard!$C$13="All",A53=Dashboard!$C$13),OR(Dashboard!$C$14="All",B53=Dashboard!$C$14),OR(Dashboard!$C$15="All",C53=Dashboard!$C$15),OR(Dashboard!$C$16="All",K53=Dashboard!$C$16),OR(Dashboard!$C$17="All",J53=Dashboard!$C$17)),1,0) -> 1 | N53: =IF(AND(L53=1,OR(Dashboard!$C$13="All",A53=Dashboard!$C$13),OR(Dashboard!$C$14="All",B53=Dashboard!$C$14),OR(Dashboard!$C$16="All",K53=Dashboard!$C$16),OR(Dashboard!$C$17="All",J53=Dashboard!$C$17)),1,0) -> 1 | O53: =IF(AND(L53=1,OR(Dashboard!$C$13="All",A53=Dashboard!$C$13),OR(Dashboard!$C$15="All",C53=Dashboard!$C$15),OR(Dashboard!$C$16="All",K53=Dashboard!$C$16),OR(Dashboard!$C$17="All",J53=Dashboard!$C$17)),1,0) -> 1 | P53: =IF(AND(L53=1,OR(Dashboard!$C$13="All",A53=Dashboard!$C$13),OR(Dashboard!$C$14="All",B53=Dashboard!$C$14),OR(Dashboard!$C$15="All",C53=Dashboard!$C$15),OR(Dashboard!$C$17="All",J53=Dashboard!$C$17)),1,0) -> 1 | Q53: =IF(AND(L53=1,OR(Dashboard!$C$14="All",B53=Dashboard!$C$14),OR(Dashboard!$C$15="All",C53=Dashboard!$C$15),OR(Dashboard!$C$16="All",K53=Dashboard!$C$16),OR(Dashboard!$C$17="All",J53=Dashboard!$C$17)),1,0) -> 1 | R53: =IF(AND(L53=1,OR(Dashboard!$C$13="All",A53=Dashboard!$C$13),OR(Dashboard!$C$14="All",B53=Dashboard!$C$14),OR(Dashboard!$C$15="All",C53=Dashboard!$C$15),OR(Dashboard!$C$16="All",K53=Dashboard!$C$16)),1,0) -> 1 | S53: =IF(M53=1,ROW()-1,"") -> 52 | T53: NASPS | V53: Antenna 270/270 U
A54: Geera | C54: Motor body | D54: 1 | E54: 2555 | F54: =IF(E54="","",D54*E54) -> 2555 | G54: 46196 | H54: 10 | I54: =IF(OR(G54="",H54=""),"",G54+H54*7) -> 46266 | J54: Not Paid | K54: Pending | L54: =IF(A54="","",IF(OR(G54="",AND(G54>=Dashboard!$C$18,G54<=Dashboard!$C$19)),1,0)) -> 1 | M54: =IF(AND(L54=1,OR(Dashboard!$C$13="All",A54=Dashboard!$C$13),OR(Dashboard!$C$14="All",B54=Dashboard!$C$14),OR(Dashboard!$C$15="All",C54=Dashboard!$C$15),OR(Dashboard!$C$16="All",K54=Dashboard!$C$16),OR(Dashboard!$C$17="All",J54=Dashboard!$C$17)),1,0) -> 1 | N54: =IF(AND(L54=1,OR(Dashboard!$C$13="All",A54=Dashboard!$C$13),OR(Dashboard!$C$14="All",B54=Dashboard!$C$14),OR(Dashboard!$C$16="All",K54=Dashboard!$C$16),OR(Dashboard!$C$17="All",J54=Dashboard!$C$17)),1,0) -> 1 | O54: =IF(AND(L54=1,OR(Dashboard!$C$13="All",A54=Dashboard!$C$13),OR(Dashboard!$C$15="All",C54=Dashboard!$C$15),OR(Dashboard!$C$16="All",K54=Dashboard!$C$16),OR(Dashboard!$C$17="All",J54=Dashboard!$C$17)),1,0) -> 1 | P54: =IF(AND(L54=1,OR(Dashboard!$C$13="All",A54=Dashboard!$C$13),OR(Dashboard!$C$14="All",B54=Dashboard!$C$14),OR(Dashboard!$C$15="All",C54=Dashboard!$C$15),OR(Dashboard!$C$17="All",J54=Dashboard!$C$17)),1,0) -> 1 | Q54: =IF(AND(L54=1,OR(Dashboard!$C$14="All",B54=Dashboard!$C$14),OR(Dashboard!$C$15="All",C54=Dashboard!$C$15),OR(Dashboard!$C$16="All",K54=Dashboard!$C$16),OR(Dashboard!$C$17="All",J54=Dashboard!$C$17)),1,0) -> 1 | R54: =IF(AND(L54=1,OR(Dashboard!$C$13="All",A54=Dashboard!$C$13),OR(Dashboard!$C$14="All",B54=Dashboard!$C$14),OR(Dashboard!$C$15="All",C54=Dashboard!$C$15),OR(Dashboard!$C$16="All",K54=Dashboard!$C$16)),1,0) -> 1 | S54: =IF(M54=1,ROW()-1,"") -> 53 | T54: Alzad | V54: Antenna Stand
A55: Jewar | C55: Limit Switch | D55: 1 | E55: 255 | F55: =IF(E55="","",D55*E55) -> 255 | G55: 46197 | H55: 6 | I55: =IF(OR(G55="",H55=""),"",G55+H55*7) -> 46239 | J55: Not Paid | K55: In Progress | L55: =IF(A55="","",IF(OR(G55="",AND(G55>=Dashboard!$C$18,G55<=Dashboard!$C$19)),1,0)) -> 1 | M55: =IF(AND(L55=1,OR(Dashboard!$C$13="All",A55=Dashboard!$C$13),OR(Dashboard!$C$14="All",B55=Dashboard!$C$14),OR(Dashboard!$C$15="All",C55=Dashboard!$C$15),OR(Dashboard!$C$16="All",K55=Dashboard!$C$16),OR(Dashboard!$C$17="All",J55=Dashboard!$C$17)),1,0) -> 1 | N55: =IF(AND(L55=1,OR(Dashboard!$C$13="All",A55=Dashboard!$C$13),OR(Dashboard!$C$14="All",B55=Dashboard!$C$14),OR(Dashboard!$C$16="All",K55=Dashboard!$C$16),OR(Dashboard!$C$17="All",J55=Dashboard!$C$17)),1,0) -> 1 | O55: =IF(AND(L55=1,OR(Dashboard!$C$13="All",A55=Dashboard!$C$13),OR(Dashboard!$C$15="All",C55=Dashboard!$C$15),OR(Dashboard!$C$16="All",K55=Dashboard!$C$16),OR(Dashboard!$C$17="All",J55=Dashboard!$C$17)),1,0) -> 1 | P55: =IF(AND(L55=1,OR(Dashboard!$C$13="All",A55=Dashboard!$C$13),OR(Dashboard!$C$14="All",B55=Dashboard!$C$14),OR(Dashboard!$C$15="All",C55=Dashboard!$C$15),OR(Dashboard!$C$17="All",J55=Dashboard!$C$17)),1,0) -> 1 | Q55: =IF(AND(L55=1,OR(Dashboard!$C$14="All",B55=Dashboard!$C$14),OR(Dashboard!$C$15="All",C55=Dashboard!$C$15),OR(Dashboard!$C$16="All",K55=Dashboard!$C$16),OR(Dashboard!$C$17="All",J55=Dashboard!$C$17)),1,0) -> 1 | R55: =IF(AND(L55=1,OR(Dashboard!$C$13="All",A55=Dashboard!$C$13),OR(Dashboard!$C$14="All",B55=Dashboard!$C$14),OR(Dashboard!$C$15="All",C55=Dashboard!$C$15),OR(Dashboard!$C$16="All",K55=Dashboard!$C$16)),1,0) -> 1 | S55: =IF(M55=1,ROW()-1,"") -> 54 | T55: OGTech Dubai | V55: Antenna stand
A56: Jewar | C56: HUB | D56: 1 | E56: 45 | F56: =IF(E56="","",D56*E56) -> 45 | G56: 46198 | H56: 9 | I56: =IF(OR(G56="",H56=""),"",G56+H56*7) -> 46261 | J56: Not Paid | K56: Completed | L56: =IF(A56="","",IF(OR(G56="",AND(G56>=Dashboard!$C$18,G56<=Dashboard!$C$19)),1,0)) -> 1 | M56: =IF(AND(L56=1,OR(Dashboard!$C$13="All",A56=Dashboard!$C$13),OR(Dashboard!$C$14="All",B56=Dashboard!$C$14),OR(Dashboard!$C$15="All",C56=Dashboard!$C$15),OR(Dashboard!$C$16="All",K56=Dashboard!$C$16),OR(Dashboard!$C$17="All",J56=Dashboard!$C$17)),1,0) -> 1 | N56: =IF(AND(L56=1,OR(Dashboard!$C$13="All",A56=Dashboard!$C$13),OR(Dashboard!$C$14="All",B56=Dashboard!$C$14),OR(Dashboard!$C$16="All",K56=Dashboard!$C$16),OR(Dashboard!$C$17="All",J56=Dashboard!$C$17)),1,0) -> 1 | O56: =IF(AND(L56=1,OR(Dashboard!$C$13="All",A56=Dashboard!$C$13),OR(Dashboard!$C$15="All",C56=Dashboard!$C$15),OR(Dashboard!$C$16="All",K56=Dashboard!$C$16),OR(Dashboard!$C$17="All",J56=Dashboard!$C$17)),1,0) -> 1 | P56: =IF(AND(L56=1,OR(Dashboard!$C$13="All",A56=Dashboard!$C$13),OR(Dashboard!$C$14="All",B56=Dashboard!$C$14),OR(Dashboard!$C$15="All",C56=Dashboard!$C$15),OR(Dashboard!$C$17="All",J56=Dashboard!$C$17)),1,0) -> 1 | Q56: =IF(AND(L56=1,OR(Dashboard!$C$14="All",B56=Dashboard!$C$14),OR(Dashboard!$C$15="All",C56=Dashboard!$C$15),OR(Dashboard!$C$16="All",K56=Dashboard!$C$16),OR(Dashboard!$C$17="All",J56=Dashboard!$C$17)),1,0) -> 1 | R56: =IF(AND(L56=1,OR(Dashboard!$C$13="All",A56=Dashboard!$C$13),OR(Dashboard!$C$14="All",B56=Dashboard!$C$14),OR(Dashboard!$C$15="All",C56=Dashboard!$C$15),OR(Dashboard!$C$16="All",K56=Dashboard!$C$16)),1,0) -> 1 | S56: =IF(M56=1,ROW()-1,"") -> 55 | T56: The Sovereign Fund Of Egypt | V56: Anttena
A57: Jewar | C57: Spring Green | D57: 2 | E57: 36 | F57: =IF(E57="","",D57*E57) -> 72 | G57: 46199 | H57: 7 | I57: =IF(OR(G57="",H57=""),"",G57+H57*7) -> 46248 | J57: Not Paid | K57: Delayed | L57: =IF(A57="","",IF(OR(G57="",AND(G57>=Dashboard!$C$18,G57<=Dashboard!$C$19)),1,0)) -> 1 | M57: =IF(AND(L57=1,OR(Dashboard!$C$13="All",A57=Dashboard!$C$13),OR(Dashboard!$C$14="All",B57=Dashboard!$C$14),OR(Dashboard!$C$15="All",C57=Dashboard!$C$15),OR(Dashboard!$C$16="All",K57=Dashboard!$C$16),OR(Dashboard!$C$17="All",J57=Dashboard!$C$17)),1,0) -> 1 | N57: =IF(AND(L57=1,OR(Dashboard!$C$13="All",A57=Dashboard!$C$13),OR(Dashboard!$C$14="All",B57=Dashboard!$C$14),OR(Dashboard!$C$16="All",K57=Dashboard!$C$16),OR(Dashboard!$C$17="All",J57=Dashboard!$C$17)),1,0) -> 1 | O57: =IF(AND(L57=1,OR(Dashboard!$C$13="All",A57=Dashboard!$C$13),OR(Dashboard!$C$15="All",C57=Dashboard!$C$15),OR(Dashboard!$C$16="All",K57=Dashboard!$C$16),OR(Dashboard!$C$17="All",J57=Dashboard!$C$17)),1,0) -> 1 | P57: =IF(AND(L57=1,OR(Dashboard!$C$13="All",A57=Dashboard!$C$13),OR(Dashboard!$C$14="All",B57=Dashboard!$C$14),OR(Dashboard!$C$15="All",C57=Dashboard!$C$15),OR(Dashboard!$C$17="All",J57=Dashboard!$C$17)),1,0) -> 1 | Q57: =IF(AND(L57=1,OR(Dashboard!$C$14="All",B57=Dashboard!$C$14),OR(Dashboard!$C$15="All",C57=Dashboard!$C$15),OR(Dashboard!$C$16="All",K57=Dashboard!$C$16),OR(Dashboard!$C$17="All",J57=Dashboard!$C$17)),1,0) -> 1 | R57: =IF(AND(L57=1,OR(Dashboard!$C$13="All",A57=Dashboard!$C$13),OR(Dashboard!$C$14="All",B57=Dashboard!$C$14),OR(Dashboard!$C$15="All",C57=Dashboard!$C$15),OR(Dashboard!$C$16="All",K57=Dashboard!$C$16)),1,0) -> 1 | S57: =IF(M57=1,ROW()-1,"") -> 56 | T57: Katameya heights | V57: APC Easy UPS On-Line 1000VA/800W
A58: Jewar | C58: Spring Blue | D58: 1 | E58: 96 | F58: =IF(E58="","",D58*E58) -> 96 | G58: 46200 | H58: 10 | I58: =IF(OR(G58="",H58=""),"",G58+H58*7) -> 46270 | J58: Not Paid | K58: Completed | L58: =IF(A58="","",IF(OR(G58="",AND(G58>=Dashboard!$C$18,G58<=Dashboard!$C$19)),1,0)) -> 1 | M58: =IF(AND(L58=1,OR(Dashboard!$C$13="All",A58=Dashboard!$C$13),OR(Dashboard!$C$14="All",B58=Dashboard!$C$14),OR(Dashboard!$C$15="All",C58=Dashboard!$C$15),OR(Dashboard!$C$16="All",K58=Dashboard!$C$16),OR(Dashboard!$C$17="All",J58=Dashboard!$C$17)),1,0) -> 1 | N58: =IF(AND(L58=1,OR(Dashboard!$C$13="All",A58=Dashboard!$C$13),OR(Dashboard!$C$14="All",B58=Dashboard!$C$14),OR(Dashboard!$C$16="All",K58=Dashboard!$C$16),OR(Dashboard!$C$17="All",J58=Dashboard!$C$17)),1,0) -> 1 | O58: =IF(AND(L58=1,OR(Dashboard!$C$13="All",A58=Dashboard!$C$13),OR(Dashboard!$C$15="All",C58=Dashboard!$C$15),OR(Dashboard!$C$16="All",K58=Dashboard!$C$16),OR(Dashboard!$C$17="All",J58=Dashboard!$C$17)),1,0) -> 1 | P58: =IF(AND(L58=1,OR(Dashboard!$C$13="All",A58=Dashboard!$C$13),OR(Dashboard!$C$14="All",B58=Dashboard!$C$14),OR(Dashboard!$C$15="All",C58=Dashboard!$C$15),OR(Dashboard!$C$17="All",J58=Dashboard!$C$17)),1,0) -> 1 | Q58: =IF(AND(L58=1,OR(Dashboard!$C$14="All",B58=Dashboard!$C$14),OR(Dashboard!$C$15="All",C58=Dashboard!$C$15),OR(Dashboard!$C$16="All",K58=Dashboard!$C$16),OR(Dashboard!$C$17="All",J58=Dashboard!$C$17)),1,0) -> 1 | R58: =IF(AND(L58=1,OR(Dashboard!$C$13="All",A58=Dashboard!$C$13),OR(Dashboard!$C$14="All",B58=Dashboard!$C$14),OR(Dashboard!$C$15="All",C58=Dashboard!$C$15),OR(Dashboard!$C$16="All",K58=Dashboard!$C$16)),1,0) -> 1 | S58: =IF(M58=1,ROW()-1,"") -> 57 | T58: BUE | V58: Aruba 124W Switch POE ARUBA - 8 Ports
A59: El Kasr Jewelry | C59: Battary | D59: 1 | E59: 8 | F59: =IF(E59="","",D59*E59) -> 8 | G59: 46201 | H59: 6 | I59: =IF(OR(G59="",H59=""),"",G59+H59*7) -> 46243 | J59: Not Paid | K59: Pending | L59: =IF(A59="","",IF(OR(G59="",AND(G59>=Dashboard!$C$18,G59<=Dashboard!$C$19)),1,0)) -> 1 | M59: =IF(AND(L59=1,OR(Dashboard!$C$13="All",A59=Dashboard!$C$13),OR(Dashboard!$C$14="All",B59=Dashboard!$C$14),OR(Dashboard!$C$15="All",C59=Dashboard!$C$15),OR(Dashboard!$C$16="All",K59=Dashboard!$C$16),OR(Dashboard!$C$17="All",J59=Dashboard!$C$17)),1,0) -> 1 | N59: =IF(AND(L59=1,OR(Dashboard!$C$13="All",A59=Dashboard!$C$13),OR(Dashboard!$C$14="All",B59=Dashboard!$C$14),OR(Dashboard!$C$16="All",K59=Dashboard!$C$16),OR(Dashboard!$C$17="All",J59=Dashboard!$C$17)),1,0) -> 1 | O59: =IF(AND(L59=1,OR(Dashboard!$C$13="All",A59=Dashboard!$C$13),OR(Dashboard!$C$15="All",C59=Dashboard!$C$15),OR(Dashboard!$C$16="All",K59=Dashboard!$C$16),OR(Dashboard!$C$17="All",J59=Dashboard!$C$17)),1,0) -> 1 | P59: =IF(AND(L59=1,OR(Dashboard!$C$13="All",A59=Dashboard!$C$13),OR(Dashboard!$C$14="All",B59=Dashboard!$C$14),OR(Dashboard!$C$15="All",C59=Dashboard!$C$15),OR(Dashboard!$C$17="All",J59=Dashboard!$C$17)),1,0) -> 1 | Q59: =IF(AND(L59=1,OR(Dashboard!$C$14="All",B59=Dashboard!$C$14),OR(Dashboard!$C$15="All",C59=Dashboard!$C$15),OR(Dashboard!$C$16="All",K59=Dashboard!$C$16),OR(Dashboard!$C$17="All",J59=Dashboard!$C$17)),1,0) -> 1 | R59: =IF(AND(L59=1,OR(Dashboard!$C$13="All",A59=Dashboard!$C$13),OR(Dashboard!$C$14="All",B59=Dashboard!$C$14),OR(Dashboard!$C$15="All",C59=Dashboard!$C$15),OR(Dashboard!$C$16="All",K59=Dashboard!$C$16)),1,0) -> 1 | S59: =IF(M59=1,ROW()-1,"") -> 58 | T59: Heliopolis Residence | V59: AT 909
A60: El Kasr Jewelry | C60: Adapter and charging cable | D60: 2 | E60: 5 | F60: =IF(E60="","",D60*E60) -> 10 | G60: 46202 | H60: 6 | I60: =IF(OR(G60="",H60=""),"",G60+H60*7) -> 46244 | J60: Not Paid | K60: In Progress | L60: =IF(A60="","",IF(OR(G60="",AND(G60>=Dashboard!$C$18,G60<=Dashboard!$C$19)),1,0)) -> 1 | M60: =IF(AND(L60=1,OR(Dashboard!$C$13="All",A60=Dashboard!$C$13),OR(Dashboard!$C$14="All",B60=Dashboard!$C$14),OR(Dashboard!$C$15="All",C60=Dashboard!$C$15),OR(Dashboard!$C$16="All",K60=Dashboard!$C$16),OR(Dashboard!$C$17="All",J60=Dashboard!$C$17)),1,0) -> 1 | N60: =IF(AND(L60=1,OR(Dashboard!$C$13="All",A60=Dashboard!$C$13),OR(Dashboard!$C$14="All",B60=Dashboard!$C$14),OR(Dashboard!$C$16="All",K60=Dashboard!$C$16),OR(Dashboard!$C$17="All",J60=Dashboard!$C$17)),1,0) -> 1 | O60: =IF(AND(L60=1,OR(Dashboard!$C$13="All",A60=Dashboard!$C$13),OR(Dashboard!$C$15="All",C60=Dashboard!$C$15),OR(Dashboard!$C$16="All",K60=Dashboard!$C$16),OR(Dashboard!$C$17="All",J60=Dashboard!$C$17)),1,0) -> 1 | P60: =IF(AND(L60=1,OR(Dashboard!$C$13="All",A60=Dashboard!$C$13),OR(Dashboard!$C$14="All",B60=Dashboard!$C$14),OR(Dashboard!$C$15="All",C60=Dashboard!$C$15),OR(Dashboard!$C$17="All",J60=Dashboard!$C$17)),1,0) -> 1 | Q60: =IF(AND(L60=1,OR(Dashboard!$C$14="All",B60=Dashboard!$C$14),OR(Dashboard!$C$15="All",C60=Dashboard!$C$15),OR(Dashboard!$C$16="All",K60=Dashboard!$C$16),OR(Dashboard!$C$17="All",J60=Dashboard!$C$17)),1,0) -> 1 | R60: =IF(AND(L60=1,OR(Dashboard!$C$13="All",A60=Dashboard!$C$13),OR(Dashboard!$C$14="All",B60=Dashboard!$C$14),OR(Dashboard!$C$15="All",C60=Dashboard!$C$15),OR(Dashboard!$C$16="All",K60=Dashboard!$C$16)),1,0) -> 1 | S60: =IF(M60=1,ROW()-1,"") -> 59 | T60: Jeera, Jewar, Jedar | V60: at 909
A61: El Nakheel | B61: Metalcraft | C61: Dest windshield tags | D61: 3000 | E61: 4 | F61: =IF(E61="","",D61*E61) -> 12000 | G61: 46203 | H61: 7 | I61: =IF(OR(G61="",H61=""),"",G61+H61*7) -> 46252 | J61: Not Paid | K61: Completed | L61: =IF(A61="","",IF(OR(G61="",AND(G61>=Dashboard!$C$18,G61<=Dashboard!$C$19)),1,0)) -> 1 | M61: =IF(AND(L61=1,OR(Dashboard!$C$13="All",A61=Dashboard!$C$13),OR(Dashboard!$C$14="All",B61=Dashboard!$C$14),OR(Dashboard!$C$15="All",C61=Dashboard!$C$15),OR(Dashboard!$C$16="All",K61=Dashboard!$C$16),OR(Dashboard!$C$17="All",J61=Dashboard!$C$17)),1,0) -> 1 | N61: =IF(AND(L61=1,OR(Dashboard!$C$13="All",A61=Dashboard!$C$13),OR(Dashboard!$C$14="All",B61=Dashboard!$C$14),OR(Dashboard!$C$16="All",K61=Dashboard!$C$16),OR(Dashboard!$C$17="All",J61=Dashboard!$C$17)),1,0) -> 1 | O61: =IF(AND(L61=1,OR(Dashboard!$C$13="All",A61=Dashboard!$C$13),OR(Dashboard!$C$15="All",C61=Dashboard!$C$15),OR(Dashboard!$C$16="All",K61=Dashboard!$C$16),OR(Dashboard!$C$17="All",J61=Dashboard!$C$17)),1,0) -> 1 | P61: =IF(AND(L61=1,OR(Dashboard!$C$13="All",A61=Dashboard!$C$13),OR(Dashboard!$C$14="All",B61=Dashboard!$C$14),OR(Dashboard!$C$15="All",C61=Dashboard!$C$15),OR(Dashboard!$C$17="All",J61=Dashboard!$C$17)),1,0) -> 1 | Q61: =IF(AND(L61=1,OR(Dashboard!$C$14="All",B61=Dashboard!$C$14),OR(Dashboard!$C$15="All",C61=Dashboard!$C$15),OR(Dashboard!$C$16="All",K61=Dashboard!$C$16),OR(Dashboard!$C$17="All",J61=Dashboard!$C$17)),1,0) -> 1 | R61: =IF(AND(L61=1,OR(Dashboard!$C$13="All",A61=Dashboard!$C$13),OR(Dashboard!$C$14="All",B61=Dashboard!$C$14),OR(Dashboard!$C$15="All",C61=Dashboard!$C$15),OR(Dashboard!$C$16="All",K61=Dashboard!$C$16)),1,0) -> 1 | S61: =IF(M61=1,ROW()-1,"") -> 60 | T61: Villa Khaled Abu El Naga | V61: At 909
A62: Radisson Blue | C62: Silver Barcode Labels 50mm*25mm Blank 1 Roll includes 1800 labels | D62: 14 | E62: 2 | F62: =IF(E62="","",D62*E62) -> 28 | G62: 46204 | H62: 8 | I62: =IF(OR(G62="",H62=""),"",G62+H62*7) -> 46260 | J62: Not Paid | K62: Delayed | L62: =IF(A62="","",IF(OR(G62="",AND(G62>=Dashboard!$C$18,G62<=Dashboard!$C$19)),1,0)) -> 1 | M62: =IF(AND(L62=1,OR(Dashboard!$C$13="All",A62=Dashboard!$C$13),OR(Dashboard!$C$14="All",B62=Dashboard!$C$14),OR(Dashboard!$C$15="All",C62=Dashboard!$C$15),OR(Dashboard!$C$16="All",K62=Dashboard!$C$16),OR(Dashboard!$C$17="All",J62=Dashboard!$C$17)),1,0) -> 1 | N62: =IF(AND(L62=1,OR(Dashboard!$C$13="All",A62=Dashboard!$C$13),OR(Dashboard!$C$14="All",B62=Dashboard!$C$14),OR(Dashboard!$C$16="All",K62=Dashboard!$C$16),OR(Dashboard!$C$17="All",J62=Dashboard!$C$17)),1,0) -> 1 | O62: =IF(AND(L62=1,OR(Dashboard!$C$13="All",A62=Dashboard!$C$13),OR(Dashboard!$C$15="All",C62=Dashboard!$C$15),OR(Dashboard!$C$16="All",K62=Dashboard!$C$16),OR(Dashboard!$C$17="All",J62=Dashboard!$C$17)),1,0) -> 1 | P62: =IF(AND(L62=1,OR(Dashboard!$C$13="All",A62=Dashboard!$C$13),OR(Dashboard!$C$14="All",B62=Dashboard!$C$14),OR(Dashboard!$C$15="All",C62=Dashboard!$C$15),OR(Dashboard!$C$17="All",J62=Dashboard!$C$17)),1,0) -> 1 | Q62: =IF(AND(L62=1,OR(Dashboard!$C$14="All",B62=Dashboard!$C$14),OR(Dashboard!$C$15="All",C62=Dashboard!$C$15),OR(Dashboard!$C$16="All",K62=Dashboard!$C$16),OR(Dashboard!$C$17="All",J62=Dashboard!$C$17)),1,0) -> 1 | R62: =IF(AND(L62=1,OR(Dashboard!$C$13="All",A62=Dashboard!$C$13),OR(Dashboard!$C$14="All",B62=Dashboard!$C$14),OR(Dashboard!$C$15="All",C62=Dashboard!$C$15),OR(Dashboard!$C$16="All",K62=Dashboard!$C$16)),1,0) -> 1 | S62: =IF(M62=1,ROW()-1,"") -> 61 | T62: Lavista 6 | V62: AT 909-rent
A63: Radisson Blue | B63: ATID | C63: AT907 | D63: 1 | E63: 36 | F63: =IF(E63="","",D63*E63) -> 36 | G63: 46205 | H63: 14 | I63: =IF(OR(G63="",H63=""),"",G63+H63*7) -> 46303 | J63: Not Paid | K63: Pending | L63: =IF(A63="","",IF(OR(G63="",AND(G63>=Dashboard!$C$18,G63<=Dashboard!$C$19)),1,0)) -> 1 | M63: =IF(AND(L63=1,OR(Dashboard!$C$13="All",A63=Dashboard!$C$13),OR(Dashboard!$C$14="All",B63=Dashboard!$C$14),OR(Dashboard!$C$15="All",C63=Dashboard!$C$15),OR(Dashboard!$C$16="All",K63=Dashboard!$C$16),OR(Dashboard!$C$17="All",J63=Dashboard!$C$17)),1,0) -> 1 | N63: =IF(AND(L63=1,OR(Dashboard!$C$13="All",A63=Dashboard!$C$13),OR(Dashboard!$C$14="All",B63=Dashboard!$C$14),OR(Dashboard!$C$16="All",K63=Dashboard!$C$16),OR(Dashboard!$C$17="All",J63=Dashboard!$C$17)),1,0) -> 1 | O63: =IF(AND(L63=1,OR(Dashboard!$C$13="All",A63=Dashboard!$C$13),OR(Dashboard!$C$15="All",C63=Dashboard!$C$15),OR(Dashboard!$C$16="All",K63=Dashboard!$C$16),OR(Dashboard!$C$17="All",J63=Dashboard!$C$17)),1,0) -> 1 | P63: =IF(AND(L63=1,OR(Dashboard!$C$13="All",A63=Dashboard!$C$13),OR(Dashboard!$C$14="All",B63=Dashboard!$C$14),OR(Dashboard!$C$15="All",C63=Dashboard!$C$15),OR(Dashboard!$C$17="All",J63=Dashboard!$C$17)),1,0) -> 1 | Q63: =IF(AND(L63=1,OR(Dashboard!$C$14="All",B63=Dashboard!$C$14),OR(Dashboard!$C$15="All",C63=Dashboard!$C$15),OR(Dashboard!$C$16="All",K63=Dashboard!$C$16),OR(Dashboard!$C$17="All",J63=Dashboard!$C$17)),1,0) -> 1 | R63: =IF(AND(L63=1,OR(Dashboard!$C$13="All",A63=Dashboard!$C$13),OR(Dashboard!$C$14="All",B63=Dashboard!$C$14),OR(Dashboard!$C$15="All",C63=Dashboard!$C$15),OR(Dashboard!$C$16="All",K63=Dashboard!$C$16)),1,0) -> 1 | S63: =IF(M63=1,ROW()-1,"") -> 62 | T63: Lavista 8 | V63: AT907
A64: Radisson Blue | B64: SATO | C64: Industrial Barcode printer (CL4NX) | D64: 1 | E64: 2 | F64: =IF(E64="","",D64*E64) -> 2 | G64: 46206 | H64: 16 | I64: =IF(OR(G64="",H64=""),"",G64+H64*7) -> 46318 | J64: Not Paid | K64: Pending | L64: =IF(A64="","",IF(OR(G64="",AND(G64>=Dashboard!$C$18,G64<=Dashboard!$C$19)),1,0)) -> 1 | M64: =IF(AND(L64=1,OR(Dashboard!$C$13="All",A64=Dashboard!$C$13),OR(Dashboard!$C$14="All",B64=Dashboard!$C$14),OR(Dashboard!$C$15="All",C64=Dashboard!$C$15),OR(Dashboard!$C$16="All",K64=Dashboard!$C$16),OR(Dashboard!$C$17="All",J64=Dashboard!$C$17)),1,0) -> 1 | N64: =IF(AND(L64=1,OR(Dashboard!$C$13="All",A64=Dashboard!$C$13),OR(Dashboard!$C$14="All",B64=Dashboard!$C$14),OR(Dashboard!$C$16="All",K64=Dashboard!$C$16),OR(Dashboard!$C$17="All",J64=Dashboard!$C$17)),1,0) -> 1 | O64: =IF(AND(L64=1,OR(Dashboard!$C$13="All",A64=Dashboard!$C$13),OR(Dashboard!$C$15="All",C64=Dashboard!$C$15),OR(Dashboard!$C$16="All",K64=Dashboard!$C$16),OR(Dashboard!$C$17="All",J64=Dashboard!$C$17)),1,0) -> 1 | P64: =IF(AND(L64=1,OR(Dashboard!$C$13="All",A64=Dashboard!$C$13),OR(Dashboard!$C$14="All",B64=Dashboard!$C$14),OR(Dashboard!$C$15="All",C64=Dashboard!$C$15),OR(Dashboard!$C$17="All",J64=Dashboard!$C$17)),1,0) -> 1 | Q64: =IF(AND(L64=1,OR(Dashboard!$C$14="All",B64=Dashboard!$C$14),OR(Dashboard!$C$15="All",C64=Dashboard!$C$15),OR(Dashboard!$C$16="All",K64=Dashboard!$C$16),OR(Dashboard!$C$17="All",J64=Dashboard!$C$17)),1,0) -> 1 | R64: =IF(AND(L64=1,OR(Dashboard!$C$13="All",A64=Dashboard!$C$13),OR(Dashboard!$C$14="All",B64=Dashboard!$C$14),OR(Dashboard!$C$15="All",C64=Dashboard!$C$15),OR(Dashboard!$C$16="All",K64=Dashboard!$C$16)),1,0) -> 1 | S64: =IF(M64=1,ROW()-1,"") -> 63 | T64: iscore | V64: AT909
A65: Radisson Blue | B65: SATO | C65: Ribbons | D65: 4 out of 14 | E65: 5 | F65: =IF(E65="","",D65*E65) -> #VALUE! | G65: 46207 | H65: 15 | I65: =IF(OR(G65="",H65=""),"",G65+H65*7) -> 46312 | J65: Not Paid | K65: In Progress | L65: =IF(A65="","",IF(OR(G65="",AND(G65>=Dashboard!$C$18,G65<=Dashboard!$C$19)),1,0)) -> 1 | M65: =IF(AND(L65=1,OR(Dashboard!$C$13="All",A65=Dashboard!$C$13),OR(Dashboard!$C$14="All",B65=Dashboard!$C$14),OR(Dashboard!$C$15="All",C65=Dashboard!$C$15),OR(Dashboard!$C$16="All",K65=Dashboard!$C$16),OR(Dashboard!$C$17="All",J65=Dashboard!$C$17)),1,0) -> 1 | N65: =IF(AND(L65=1,OR(Dashboard!$C$13="All",A65=Dashboard!$C$13),OR(Dashboard!$C$14="All",B65=Dashboard!$C$14),OR(Dashboard!$C$16="All",K65=Dashboard!$C$16),OR(Dashboard!$C$17="All",J65=Dashboard!$C$17)),1,0) -> 1 | O65: =IF(AND(L65=1,OR(Dashboard!$C$13="All",A65=Dashboard!$C$13),OR(Dashboard!$C$15="All",C65=Dashboard!$C$15),OR(Dashboard!$C$16="All",K65=Dashboard!$C$16),OR(Dashboard!$C$17="All",J65=Dashboard!$C$17)),1,0) -> 1 | P65: =IF(AND(L65=1,OR(Dashboard!$C$13="All",A65=Dashboard!$C$13),OR(Dashboard!$C$14="All",B65=Dashboard!$C$14),OR(Dashboard!$C$15="All",C65=Dashboard!$C$15),OR(Dashboard!$C$17="All",J65=Dashboard!$C$17)),1,0) -> 1 | Q65: =IF(AND(L65=1,OR(Dashboard!$C$14="All",B65=Dashboard!$C$14),OR(Dashboard!$C$15="All",C65=Dashboard!$C$15),OR(Dashboard!$C$16="All",K65=Dashboard!$C$16),OR(Dashboard!$C$17="All",J65=Dashboard!$C$17)),1,0) -> 1 | R65: =IF(AND(L65=1,OR(Dashboard!$C$13="All",A65=Dashboard!$C$13),OR(Dashboard!$C$14="All",B65=Dashboard!$C$14),OR(Dashboard!$C$15="All",C65=Dashboard!$C$15),OR(Dashboard!$C$16="All",K65=Dashboard!$C$16)),1,0) -> 1 | S65: =IF(M65=1,ROW()-1,"") -> 64 | T65: Mediterranean | V65: at909
A66: Prometeon | C66: Industrial Barcode printer (CL4NX) | D66: 17 | E66: 6 | F66: =IF(E66="","",D66*E66) -> 102 | G66: 46208 | H66: 15 | I66: =IF(OR(G66="",H66=""),"",G66+H66*7) -> 46313 | J66: Not Paid | K66: Completed | L66: =IF(A66="","",IF(OR(G66="",AND(G66>=Dashboard!$C$18,G66<=Dashboard!$C$19)),1,0)) -> 1 | M66: =IF(AND(L66=1,OR(Dashboard!$C$13="All",A66=Dashboard!$C$13),OR(Dashboard!$C$14="All",B66=Dashboard!$C$14),OR(Dashboard!$C$15="All",C66=Dashboard!$C$15),OR(Dashboard!$C$16="All",K66=Dashboard!$C$16),OR(Dashboard!$C$17="All",J66=Dashboard!$C$17)),1,0) -> 1 | N66: =IF(AND(L66=1,OR(Dashboard!$C$13="All",A66=Dashboard!$C$13),OR(Dashboard!$C$14="All",B66=Dashboard!$C$14),OR(Dashboard!$C$16="All",K66=Dashboard!$C$16),OR(Dashboard!$C$17="All",J66=Dashboard!$C$17)),1,0) -> 1 | O66: =IF(AND(L66=1,OR(Dashboard!$C$13="All",A66=Dashboard!$C$13),OR(Dashboard!$C$15="All",C66=Dashboard!$C$15),OR(Dashboard!$C$16="All",K66=Dashboard!$C$16),OR(Dashboard!$C$17="All",J66=Dashboard!$C$17)),1,0) -> 1 | P66: =IF(AND(L66=1,OR(Dashboard!$C$13="All",A66=Dashboard!$C$13),OR(Dashboard!$C$14="All",B66=Dashboard!$C$14),OR(Dashboard!$C$15="All",C66=Dashboard!$C$15),OR(Dashboard!$C$17="All",J66=Dashboard!$C$17)),1,0) -> 1 | Q66: =IF(AND(L66=1,OR(Dashboard!$C$14="All",B66=Dashboard!$C$14),OR(Dashboard!$C$15="All",C66=Dashboard!$C$15),OR(Dashboard!$C$16="All",K66=Dashboard!$C$16),OR(Dashboard!$C$17="All",J66=Dashboard!$C$17)),1,0) -> 1 | R66: =IF(AND(L66=1,OR(Dashboard!$C$13="All",A66=Dashboard!$C$13),OR(Dashboard!$C$14="All",B66=Dashboard!$C$14),OR(Dashboard!$C$15="All",C66=Dashboard!$C$15),OR(Dashboard!$C$16="All",K66=Dashboard!$C$16)),1,0) -> 1 | S66: =IF(M66=1,ROW()-1,"") -> 65 | T66: Reefy | V66: ATID RFID Handheld - AT909
A67: SIDC | C67: HF Cards | D67: 5 | E67: 7 | F67: =IF(E67="","",D67*E67) -> 35 | G67: 46209 | H67: 14 | I67: =IF(OR(G67="",H67=""),"",G67+H67*7) -> 46307 | J67: Not Paid | K67: Delayed | L67: =IF(A67="","",IF(OR(G67="",AND(G67>=Dashboard!$C$18,G67<=Dashboard!$C$19)),1,0)) -> 1 | M67: =IF(AND(L67=1,OR(Dashboard!$C$13="All",A67=Dashboard!$C$13),OR(Dashboard!$C$14="All",B67=Dashboard!$C$14),OR(Dashboard!$C$15="All",C67=Dashboard!$C$15),OR(Dashboard!$C$16="All",K67=Dashboard!$C$16),OR(Dashboard!$C$17="All",J67=Dashboard!$C$17)),1,0) -> 1 | N67: =IF(AND(L67=1,OR(Dashboard!$C$13="All",A67=Dashboard!$C$13),OR(Dashboard!$C$14="All",B67=Dashboard!$C$14),OR(Dashboard!$C$16="All",K67=Dashboard!$C$16),OR(Dashboard!$C$17="All",J67=Dashboard!$C$17)),1,0) -> 1 | O67: =IF(AND(L67=1,OR(Dashboard!$C$13="All",A67=Dashboard!$C$13),OR(Dashboard!$C$15="All",C67=Dashboard!$C$15),OR(Dashboard!$C$16="All",K67=Dashboard!$C$16),OR(Dashboard!$C$17="All",J67=Dashboard!$C$17)),1,0) -> 1 | P67: =IF(AND(L67=1,OR(Dashboard!$C$13="All",A67=Dashboard!$C$13),OR(Dashboard!$C$14="All",B67=Dashboard!$C$14),OR(Dashboard!$C$15="All",C67=Dashboard!$C$15),OR(Dashboard!$C$17="All",J67=Dashboard!$C$17)),1,0) -> 1 | Q67: =IF(AND(L67=1,OR(Dashboard!$C$14="All",B67=Dashboard!$C$14),OR(Dashboard!$C$15="All",C67=Dashboard!$C$15),OR(Dashboard!$C$16="All",K67=Dashboard!$C$16),OR(Dashboard!$C$17="All",J67=Dashboard!$C$17)),1,0) -> 1 | R67: =IF(AND(L67=1,OR(Dashboard!$C$13="All",A67=Dashboard!$C$13),OR(Dashboard!$C$14="All",B67=Dashboard!$C$14),OR(Dashboard!$C$15="All",C67=Dashboard!$C$15),OR(Dashboard!$C$16="All",K67=Dashboard!$C$16)),1,0) -> 1 | S67: =IF(M67=1,ROW()-1,"") -> 66 | T67: Lavista 5,8,Topaz | V67: ATID RFID Handheld AT907
A68: SLR-RFID | B68: FEIG | C68: MAX.U500I | D68: 36 | E68: 8 | F68: =IF(E68="","",D68*E68) -> 288 | G68: 46210 | H68: 15 | I68: =IF(OR(G68="",H68=""),"",G68+H68*7) -> 46315 | J68: Not Paid | K68: Pending | L68: =IF(A68="","",IF(OR(G68="",AND(G68>=Dashboard!$C$18,G68<=Dashboard!$C$19)),1,0)) -> 1 | M68: =IF(AND(L68=1,OR(Dashboard!$C$13="All",A68=Dashboard!$C$13),OR(Dashboard!$C$14="All",B68=Dashboard!$C$14),OR(Dashboard!$C$15="All",C68=Dashboard!$C$15),OR(Dashboard!$C$16="All",K68=Dashboard!$C$16),OR(Dashboard!$C$17="All",J68=Dashboard!$C$17)),1,0) -> 1 | N68: =IF(AND(L68=1,OR(Dashboard!$C$13="All",A68=Dashboard!$C$13),OR(Dashboard!$C$14="All",B68=Dashboard!$C$14),OR(Dashboard!$C$16="All",K68=Dashboard!$C$16),OR(Dashboard!$C$17="All",J68=Dashboard!$C$17)),1,0) -> 1 | O68: =IF(AND(L68=1,OR(Dashboard!$C$13="All",A68=Dashboard!$C$13),OR(Dashboard!$C$15="All",C68=Dashboard!$C$15),OR(Dashboard!$C$16="All",K68=Dashboard!$C$16),OR(Dashboard!$C$17="All",J68=Dashboard!$C$17)),1,0) -> 1 | P68: =IF(AND(L68=1,OR(Dashboard!$C$13="All",A68=Dashboard!$C$13),OR(Dashboard!$C$14="All",B68=Dashboard!$C$14),OR(Dashboard!$C$15="All",C68=Dashboard!$C$15),OR(Dashboard!$C$17="All",J68=Dashboard!$C$17)),1,0) -> 1 | Q68: =IF(AND(L68=1,OR(Dashboard!$C$14="All",B68=Dashboard!$C$14),OR(Dashboard!$C$15="All",C68=Dashboard!$C$15),OR(Dashboard!$C$16="All",K68=Dashboard!$C$16),OR(Dashboard!$C$17="All",J68=Dashboard!$C$17)),1,0) -> 1 | R68: =IF(AND(L68=1,OR(Dashboard!$C$13="All",A68=Dashboard!$C$13),OR(Dashboard!$C$14="All",B68=Dashboard!$C$14),OR(Dashboard!$C$15="All",C68=Dashboard!$C$15),OR(Dashboard!$C$16="All",K68=Dashboard!$C$16)),1,0) -> 1 | S68: =IF(M68=1,ROW()-1,"") -> 67 | T68: Hadayek El-Ferdous | V68: Automatic switch
A69: SLR-RFID | B69: FEIG | C69: ANT.U290/290 | D69: 29 | E69: 2 | F69: =IF(E69="","",D69*E69) -> 58 | G69: 46211 | H69: 14 | I69: =IF(OR(G69="",H69=""),"",G69+H69*7) -> 46309 | J69: Not Paid | K69: Pending | L69: =IF(A69="","",IF(OR(G69="",AND(G69>=Dashboard!$C$18,G69<=Dashboard!$C$19)),1,0)) -> 1 | M69: =IF(AND(L69=1,OR(Dashboard!$C$13="All",A69=Dashboard!$C$13),OR(Dashboard!$C$14="All",B69=Dashboard!$C$14),OR(Dashboard!$C$15="All",C69=Dashboard!$C$15),OR(Dashboard!$C$16="All",K69=Dashboard!$C$16),OR(Dashboard!$C$17="All",J69=Dashboard!$C$17)),1,0) -> 1 | N69: =IF(AND(L69=1,OR(Dashboard!$C$13="All",A69=Dashboard!$C$13),OR(Dashboard!$C$14="All",B69=Dashboard!$C$14),OR(Dashboard!$C$16="All",K69=Dashboard!$C$16),OR(Dashboard!$C$17="All",J69=Dashboard!$C$17)),1,0) -> 1 | O69: =IF(AND(L69=1,OR(Dashboard!$C$13="All",A69=Dashboard!$C$13),OR(Dashboard!$C$15="All",C69=Dashboard!$C$15),OR(Dashboard!$C$16="All",K69=Dashboard!$C$16),OR(Dashboard!$C$17="All",J69=Dashboard!$C$17)),1,0) -> 1 | P69: =IF(AND(L69=1,OR(Dashboard!$C$13="All",A69=Dashboard!$C$13),OR(Dashboard!$C$14="All",B69=Dashboard!$C$14),OR(Dashboard!$C$15="All",C69=Dashboard!$C$15),OR(Dashboard!$C$17="All",J69=Dashboard!$C$17)),1,0) -> 1 | Q69: =IF(AND(L69=1,OR(Dashboard!$C$14="All",B69=Dashboard!$C$14),OR(Dashboard!$C$15="All",C69=Dashboard!$C$15),OR(Dashboard!$C$16="All",K69=Dashboard!$C$16),OR(Dashboard!$C$17="All",J69=Dashboard!$C$17)),1,0) -> 1 | R69: =IF(AND(L69=1,OR(Dashboard!$C$13="All",A69=Dashboard!$C$13),OR(Dashboard!$C$14="All",B69=Dashboard!$C$14),OR(Dashboard!$C$15="All",C69=Dashboard!$C$15),OR(Dashboard!$C$16="All",K69=Dashboard!$C$16)),1,0) -> 1 | S69: =IF(M69=1,ROW()-1,"") -> 68 | T69: Sodic Club | V69: Barcode label (10 * 2 cm) - Blank
A70: Enova | B70: FEIG | C70: RW02.10 | D70: 16 | E70: 15 | F70: =IF(E70="","",D70*E70) -> 240 | G70: 46212 | H70: 12 | I70: =IF(OR(G70="",H70=""),"",G70+H70*7) -> 46296 | J70: Not Paid | K70: Completed | L70: =IF(A70="","",IF(OR(G70="",AND(G70>=Dashboard!$C$18,G70<=Dashboard!$C$19)),1,0)) -> 1 | M70: =IF(AND(L70=1,OR(Dashboard!$C$13="All",A70=Dashboard!$C$13),OR(Dashboard!$C$14="All",B70=Dashboard!$C$14),OR(Dashboard!$C$15="All",C70=Dashboard!$C$15),OR(Dashboard!$C$16="All",K70=Dashboard!$C$16),OR(Dashboard!$C$17="All",J70=Dashboard!$C$17)),1,0) -> 1 | N70: =IF(AND(L70=1,OR(Dashboard!$C$13="All",A70=Dashboard!$C$13),OR(Dashboard!$C$14="All",B70=Dashboard!$C$14),OR(Dashboard!$C$16="All",K70=Dashboard!$C$16),OR(Dashboard!$C$17="All",J70=Dashboard!$C$17)),1,0) -> 1 | O70: =IF(AND(L70=1,OR(Dashboard!$C$13="All",A70=Dashboard!$C$13),OR(Dashboard!$C$15="All",C70=Dashboard!$C$15),OR(Dashboard!$C$16="All",K70=Dashboard!$C$16),OR(Dashboard!$C$17="All",J70=Dashboard!$C$17)),1,0) -> 1 | P70: =IF(AND(L70=1,OR(Dashboard!$C$13="All",A70=Dashboard!$C$13),OR(Dashboard!$C$14="All",B70=Dashboard!$C$14),OR(Dashboard!$C$15="All",C70=Dashboard!$C$15),OR(Dashboard!$C$17="All",J70=Dashboard!$C$17)),1,0) -> 1 | Q70: =IF(AND(L70=1,OR(Dashboard!$C$14="All",B70=Dashboard!$C$14),OR(Dashboard!$C$15="All",C70=Dashboard!$C$15),OR(Dashboard!$C$16="All",K70=Dashboard!$C$16),OR(Dashboard!$C$17="All",J70=Dashboard!$C$17)),1,0) -> 1 | R70: =IF(AND(L70=1,OR(Dashboard!$C$13="All",A70=Dashboard!$C$13),OR(Dashboard!$C$14="All",B70=Dashboard!$C$14),OR(Dashboard!$C$15="All",C70=Dashboard!$C$15),OR(Dashboard!$C$16="All",K70=Dashboard!$C$16)),1,0) -> 1 | S70: =IF(M70=1,ROW()-1,"") -> 69 | T70: Diar | V70: Barcode labels 3500 per roll/ 21000 total
A71: Semiramis | B71: Dipole | C71: UHF Paper tags- Dogbone- Blank | D71: 100000 | E71: 45 | F71: =IF(E71="","",D71*E71) -> 4500000 | G71: 46213 | H71: 14 | I71: =IF(OR(G71="",H71=""),"",G71+H71*7) -> 46311 | J71: Not Paid | K71: Pending | L71: =IF(A71="","",IF(OR(G71="",AND(G71>=Dashboard!$C$18,G71<=Dashboard!$C$19)),1,0)) -> 1 | M71: =IF(AND(L71=1,OR(Dashboard!$C$13="All",A71=Dashboard!$C$13),OR(Dashboard!$C$14="All",B71=Dashboard!$C$14),OR(Dashboard!$C$15="All",C71=Dashboard!$C$15),OR(Dashboard!$C$16="All",K71=Dashboard!$C$16),OR(Dashboard!$C$17="All",J71=Dashboard!$C$17)),1,0) -> 1 | N71: =IF(AND(L71=1,OR(Dashboard!$C$13="All",A71=Dashboard!$C$13),OR(Dashboard!$C$14="All",B71=Dashboard!$C$14),OR(Dashboard!$C$16="All",K71=Dashboard!$C$16),OR(Dashboard!$C$17="All",J71=Dashboard!$C$17)),1,0) -> 1 | O71: =IF(AND(L71=1,OR(Dashboard!$C$13="All",A71=Dashboard!$C$13),OR(Dashboard!$C$15="All",C71=Dashboard!$C$15),OR(Dashboard!$C$16="All",K71=Dashboard!$C$16),OR(Dashboard!$C$17="All",J71=Dashboard!$C$17)),1,0) -> 1 | P71: =IF(AND(L71=1,OR(Dashboard!$C$13="All",A71=Dashboard!$C$13),OR(Dashboard!$C$14="All",B71=Dashboard!$C$14),OR(Dashboard!$C$15="All",C71=Dashboard!$C$15),OR(Dashboard!$C$17="All",J71=Dashboard!$C$17)),1,0) -> 1 | Q71: =IF(AND(L71=1,OR(Dashboard!$C$14="All",B71=Dashboard!$C$14),OR(Dashboard!$C$15="All",C71=Dashboard!$C$15),OR(Dashboard!$C$16="All",K71=Dashboard!$C$16),OR(Dashboard!$C$17="All",J71=Dashboard!$C$17)),1,0) -> 1 | R71: =IF(AND(L71=1,OR(Dashboard!$C$13="All",A71=Dashboard!$C$13),OR(Dashboard!$C$14="All",B71=Dashboard!$C$14),OR(Dashboard!$C$15="All",C71=Dashboard!$C$15),OR(Dashboard!$C$16="All",K71=Dashboard!$C$16)),1,0) -> 1 | S71: =IF(M71=1,ROW()-1,"") -> 70 | T71: Omega | V71: Barcode Printer-(SG112-ex)
A72: Semiramis | B72: RICH RFID | C72: UHF Tags for Metal Assets- RCO7011- Blank | D72: 40000 | E72: 24 | F72: =IF(E72="","",D72*E72) -> 960000 | G72: 46214 | H72: 13 | I72: =IF(OR(G72="",H72=""),"",G72+H72*7) -> 46305 | J72: Not Paid | K72: In Progress | L72: =IF(A72="","",IF(OR(G72="",AND(G72>=Dashboard!$C$18,G72<=Dashboard!$C$19)),1,0)) -> 1 | M72: =IF(AND(L72=1,OR(Dashboard!$C$13="All",A72=Dashboard!$C$13),OR(Dashboard!$C$14="All",B72=Dashboard!$C$14),OR(Dashboard!$C$15="All",C72=Dashboard!$C$15),OR(Dashboard!$C$16="All",K72=Dashboard!$C$16),OR(Dashboard!$C$17="All",J72=Dashboard!$C$17)),1,0) -> 1 | N72: =IF(AND(L72=1,OR(Dashboard!$C$13="All",A72=Dashboard!$C$13),OR(Dashboard!$C$14="All",B72=Dashboard!$C$14),OR(Dashboard!$C$16="All",K72=Dashboard!$C$16),OR(Dashboard!$C$17="All",J72=Dashboard!$C$17)),1,0) -> 1 | O72: =IF(AND(L72=1,OR(Dashboard!$C$13="All",A72=Dashboard!$C$13),OR(Dashboard!$C$15="All",C72=Dashboard!$C$15),OR(Dashboard!$C$16="All",K72=Dashboard!$C$16),OR(Dashboard!$C$17="All",J72=Dashboard!$C$17)),1,0) -> 1 | P72: =IF(AND(L72=1,OR(Dashboard!$C$13="All",A72=Dashboard!$C$13),OR(Dashboard!$C$14="All",B72=Dashboard!$C$14),OR(Dashboard!$C$15="All",C72=Dashboard!$C$15),OR(Dashboard!$C$17="All",J72=Dashboard!$C$17)),1,0) -> 1 | Q72: =IF(AND(L72=1,OR(Dashboard!$C$14="All",B72=Dashboard!$C$14),OR(Dashboard!$C$15="All",C72=Dashboard!$C$15),OR(Dashboard!$C$16="All",K72=Dashboard!$C$16),OR(Dashboard!$C$17="All",J72=Dashboard!$C$17)),1,0) -> 1 | R72: =IF(AND(L72=1,OR(Dashboard!$C$13="All",A72=Dashboard!$C$13),OR(Dashboard!$C$14="All",B72=Dashboard!$C$14),OR(Dashboard!$C$15="All",C72=Dashboard!$C$15),OR(Dashboard!$C$16="All",K72=Dashboard!$C$16)),1,0) -> 1 | S72: =IF(M72=1,ROW()-1,"") -> 71 | T72: SIEMENS | V72: Barcode Silver labels 5X2.5cm
A73: Semiramis | B73: The tag factory | C73: RFID Hard Tag- M-Crown | D73: 2000 | E73: 25 | F73: =IF(E73="","",D73*E73) -> 50000 | G73: 46215 | H73: 19 | I73: =IF(OR(G73="",H73=""),"",G73+H73*7) -> 46348 | J73: Not Paid | K73: Completed | L73: =IF(A73="","",IF(OR(G73="",AND(G73>=Dashboard!$C$18,G73<=Dashboard!$C$19)),1,0)) -> 1 | M73: =IF(AND(L73=1,OR(Dashboard!$C$13="All",A73=Dashboard!$C$13),OR(Dashboard!$C$14="All",B73=Dashboard!$C$14),OR(Dashboard!$C$15="All",C73=Dashboard!$C$15),OR(Dashboard!$C$16="All",K73=Dashboard!$C$16),OR(Dashboard!$C$17="All",J73=Dashboard!$C$17)),1,0) -> 1 | N73: =IF(AND(L73=1,OR(Dashboard!$C$13="All",A73=Dashboard!$C$13),OR(Dashboard!$C$14="All",B73=Dashboard!$C$14),OR(Dashboard!$C$16="All",K73=Dashboard!$C$16),OR(Dashboard!$C$17="All",J73=Dashboard!$C$17)),1,0) -> 1 | O73: =IF(AND(L73=1,OR(Dashboard!$C$13="All",A73=Dashboard!$C$13),OR(Dashboard!$C$15="All",C73=Dashboard!$C$15),OR(Dashboard!$C$16="All",K73=Dashboard!$C$16),OR(Dashboard!$C$17="All",J73=Dashboard!$C$17)),1,0) -> 1 | P73: =IF(AND(L73=1,OR(Dashboard!$C$13="All",A73=Dashboard!$C$13),OR(Dashboard!$C$14="All",B73=Dashboard!$C$14),OR(Dashboard!$C$15="All",C73=Dashboard!$C$15),OR(Dashboard!$C$17="All",J73=Dashboard!$C$17)),1,0) -> 1 | Q73: =IF(AND(L73=1,OR(Dashboard!$C$14="All",B73=Dashboard!$C$14),OR(Dashboard!$C$15="All",C73=Dashboard!$C$15),OR(Dashboard!$C$16="All",K73=Dashboard!$C$16),OR(Dashboard!$C$17="All",J73=Dashboard!$C$17)),1,0) -> 1 | R73: =IF(AND(L73=1,OR(Dashboard!$C$13="All",A73=Dashboard!$C$13),OR(Dashboard!$C$14="All",B73=Dashboard!$C$14),OR(Dashboard!$C$15="All",C73=Dashboard!$C$15),OR(Dashboard!$C$16="All",K73=Dashboard!$C$16)),1,0) -> 1 | S73: =IF(M73=1,ROW()-1,"") -> 72 | T73: AAIB | V73: Barrier Beam Connection Flange Part Number SBH01
A74: Semiramis | B74: SATO | C74: Industrial RFID Printer CL4NX Plus | D74: 1 | E74: 36 | F74: =IF(E74="","",D74*E74) -> 36 | G74: 46216 | H74: 17 | I74: =IF(OR(G74="",H74=""),"",G74+H74*7) -> 46335 | J74: Not Paid | K74: Delayed | L74: =IF(A74="","",IF(OR(G74="",AND(G74>=Dashboard!$C$18,G74<=Dashboard!$C$19)),1,0)) -> 1 | M74: =IF(AND(L74=1,OR(Dashboard!$C$13="All",A74=Dashboard!$C$13),OR(Dashboard!$C$14="All",B74=Dashboard!$C$14),OR(Dashboard!$C$15="All",C74=Dashboard!$C$15),OR(Dashboard!$C$16="All",K74=Dashboard!$C$16),OR(Dashboard!$C$17="All",J74=Dashboard!$C$17)),1,0) -> 1 | N74: =IF(AND(L74=1,OR(Dashboard!$C$13="All",A74=Dashboard!$C$13),OR(Dashboard!$C$14="All",B74=Dashboard!$C$14),OR(Dashboard!$C$16="All",K74=Dashboard!$C$16),OR(Dashboard!$C$17="All",J74=Dashboard!$C$17)),1,0) -> 1 | O74: =IF(AND(L74=1,OR(Dashboard!$C$13="All",A74=Dashboard!$C$13),OR(Dashboard!$C$15="All",C74=Dashboard!$C$15),OR(Dashboard!$C$16="All",K74=Dashboard!$C$16),OR(Dashboard!$C$17="All",J74=Dashboard!$C$17)),1,0) -> 1 | P74: =IF(AND(L74=1,OR(Dashboard!$C$13="All",A74=Dashboard!$C$13),OR(Dashboard!$C$14="All",B74=Dashboard!$C$14),OR(Dashboard!$C$15="All",C74=Dashboard!$C$15),OR(Dashboard!$C$17="All",J74=Dashboard!$C$17)),1,0) -> 1 | Q74: =IF(AND(L74=1,OR(Dashboard!$C$14="All",B74=Dashboard!$C$14),OR(Dashboard!$C$15="All",C74=Dashboard!$C$15),OR(Dashboard!$C$16="All",K74=Dashboard!$C$16),OR(Dashboard!$C$17="All",J74=Dashboard!$C$17)),1,0) -> 1 | R74: =IF(AND(L74=1,OR(Dashboard!$C$13="All",A74=Dashboard!$C$13),OR(Dashboard!$C$14="All",B74=Dashboard!$C$14),OR(Dashboard!$C$15="All",C74=Dashboard!$C$15),OR(Dashboard!$C$16="All",K74=Dashboard!$C$16)),1,0) -> 1 | S74: =IF(M74=1,ROW()-1,"") -> 73 | T74: Orascom | V74: Battary
A75: Semiramis | B75: SATO | C75: Resin ribbon- Y10110600364 | D75: 6 | E75: 95 | F75: =IF(E75="","",D75*E75) -> 570 | G75: 46217 | H75: 19 | I75: =IF(OR(G75="",H75=""),"",G75+H75*7) -> 46350 | J75: Not Paid | K75: Pending | L75: =IF(A75="","",IF(OR(G75="",AND(G75>=Dashboard!$C$18,G75<=Dashboard!$C$19)),1,0)) -> 1 | M75: =IF(AND(L75=1,OR(Dashboard!$C$13="All",A75=Dashboard!$C$13),OR(Dashboard!$C$14="All",B75=Dashboard!$C$14),OR(Dashboard!$C$15="All",C75=Dashboard!$C$15),OR(Dashboard!$C$16="All",K75=Dashboard!$C$16),OR(Dashboard!$C$17="All",J75=Dashboard!$C$17)),1,0) -> 1 | N75: =IF(AND(L75=1,OR(Dashboard!$C$13="All",A75=Dashboard!$C$13),OR(Dashboard!$C$14="All",B75=Dashboard!$C$14),OR(Dashboard!$C$16="All",K75=Dashboard!$C$16),OR(Dashboard!$C$17="All",J75=Dashboard!$C$17)),1,0) -> 1 | O75: =IF(AND(L75=1,OR(Dashboard!$C$13="All",A75=Dashboard!$C$13),OR(Dashboard!$C$15="All",C75=Dashboard!$C$15),OR(Dashboard!$C$16="All",K75=Dashboard!$C$16),OR(Dashboard!$C$17="All",J75=Dashboard!$C$17)),1,0) -> 1 | P75: =IF(AND(L75=1,OR(Dashboard!$C$13="All",A75=Dashboard!$C$13),OR(Dashboard!$C$14="All",B75=Dashboard!$C$14),OR(Dashboard!$C$15="All",C75=Dashboard!$C$15),OR(Dashboard!$C$17="All",J75=Dashboard!$C$17)),1,0) -> 1 | Q75: =IF(AND(L75=1,OR(Dashboard!$C$14="All",B75=Dashboard!$C$14),OR(Dashboard!$C$15="All",C75=Dashboard!$C$15),OR(Dashboard!$C$16="All",K75=Dashboard!$C$16),OR(Dashboard!$C$17="All",J75=Dashboard!$C$17)),1,0) -> 1 | R75: =IF(AND(L75=1,OR(Dashboard!$C$13="All",A75=Dashboard!$C$13),OR(Dashboard!$C$14="All",B75=Dashboard!$C$14),OR(Dashboard!$C$15="All",C75=Dashboard!$C$15),OR(Dashboard!$C$16="All",K75=Dashboard!$C$16)),1,0) -> 1 | S75: =IF(M75=1,ROW()-1,"") -> 74 | T75: Evergreen | V75: Boom 4m - FAAC B615 BPR
A76: Semiramis | B76: ATID | C76: Handheld- AT907 | D76: 2 | E76: 574 | F76: =IF(E76="","",D76*E76) -> 1148 | G76: 46218 | H76: 21 | I76: =IF(OR(G76="",H76=""),"",G76+H76*7) -> 46365 | J76: Not Paid | K76: Pending | L76: =IF(A76="","",IF(OR(G76="",AND(G76>=Dashboard!$C$18,G76<=Dashboard!$C$19)),1,0)) -> 1 | M76: =IF(AND(L76=1,OR(Dashboard!$C$13="All",A76=Dashboard!$C$13),OR(Dashboard!$C$14="All",B76=Dashboard!$C$14),OR(Dashboard!$C$15="All",C76=Dashboard!$C$15),OR(Dashboard!$C$16="All",K76=Dashboard!$C$16),OR(Dashboard!$C$17="All",J76=Dashboard!$C$17)),1,0) -> 1 | N76: =IF(AND(L76=1,OR(Dashboard!$C$13="All",A76=Dashboard!$C$13),OR(Dashboard!$C$14="All",B76=Dashboard!$C$14),OR(Dashboard!$C$16="All",K76=Dashboard!$C$16),OR(Dashboard!$C$17="All",J76=Dashboard!$C$17)),1,0) -> 1 | O76: =IF(AND(L76=1,OR(Dashboard!$C$13="All",A76=Dashboard!$C$13),OR(Dashboard!$C$15="All",C76=Dashboard!$C$15),OR(Dashboard!$C$16="All",K76=Dashboard!$C$16),OR(Dashboard!$C$17="All",J76=Dashboard!$C$17)),1,0) -> 1 | P76: =IF(AND(L76=1,OR(Dashboard!$C$13="All",A76=Dashboard!$C$13),OR(Dashboard!$C$14="All",B76=Dashboard!$C$14),OR(Dashboard!$C$15="All",C76=Dashboard!$C$15),OR(Dashboard!$C$17="All",J76=Dashboard!$C$17)),1,0) -> 1 | Q76: =IF(AND(L76=1,OR(Dashboard!$C$14="All",B76=Dashboard!$C$14),OR(Dashboard!$C$15="All",C76=Dashboard!$C$15),OR(Dashboard!$C$16="All",K76=Dashboard!$C$16),OR(Dashboard!$C$17="All",J76=Dashboard!$C$17)),1,0) -> 1 | R76: =IF(AND(L76=1,OR(Dashboard!$C$13="All",A76=Dashboard!$C$13),OR(Dashboard!$C$14="All",B76=Dashboard!$C$14),OR(Dashboard!$C$15="All",C76=Dashboard!$C$15),OR(Dashboard!$C$16="All",K76=Dashboard!$C$16)),1,0) -> 1 | S76: =IF(M76=1,ROW()-1,"") -> 75 | T76: ANOPC | V76: Boom-5m
A77: AIB | B77: Metalcraft | C77: EU Universal tags- Blank | D77: 1100 out of 5000 | E77: 558 | F77: =IF(E77="","",D77*E77) -> #VALUE! | G77: 46219 | H77: 20 | I77: =IF(OR(G77="",H77=""),"",G77+H77*7) -> 46359 | J77: Not Paid | K77: Pending | L77: =IF(A77="","",IF(OR(G77="",AND(G77>=Dashboard!$C$18,G77<=Dashboard!$C$19)),1,0)) -> 1 | M77: =IF(AND(L77=1,OR(Dashboard!$C$13="All",A77=Dashboard!$C$13),OR(Dashboard!$C$14="All",B77=Dashboard!$C$14),OR(Dashboard!$C$15="All",C77=Dashboard!$C$15),OR(Dashboard!$C$16="All",K77=Dashboard!$C$16),OR(Dashboard!$C$17="All",J77=Dashboard!$C$17)),1,0) -> 1 | N77: =IF(AND(L77=1,OR(Dashboard!$C$13="All",A77=Dashboard!$C$13),OR(Dashboard!$C$14="All",B77=Dashboard!$C$14),OR(Dashboard!$C$16="All",K77=Dashboard!$C$16),OR(Dashboard!$C$17="All",J77=Dashboard!$C$17)),1,0) -> 1 | O77: =IF(AND(L77=1,OR(Dashboard!$C$13="All",A77=Dashboard!$C$13),OR(Dashboard!$C$15="All",C77=Dashboard!$C$15),OR(Dashboard!$C$16="All",K77=Dashboard!$C$16),OR(Dashboard!$C$17="All",J77=Dashboard!$C$17)),1,0) -> 1 | P77: =IF(AND(L77=1,OR(Dashboard!$C$13="All",A77=Dashboard!$C$13),OR(Dashboard!$C$14="All",B77=Dashboard!$C$14),OR(Dashboard!$C$15="All",C77=Dashboard!$C$15),OR(Dashboard!$C$17="All",J77=Dashboard!$C$17)),1,0) -> 1 | Q77: =IF(AND(L77=1,OR(Dashboard!$C$14="All",B77=Dashboard!$C$14),OR(Dashboard!$C$15="All",C77=Dashboard!$C$15),OR(Dashboard!$C$16="All",K77=Dashboard!$C$16),OR(Dashboard!$C$17="All",J77=Dashboard!$C$17)),1,0) -> 1 | R77: =IF(AND(L77=1,OR(Dashboard!$C$13="All",A77=Dashboard!$C$13),OR(Dashboard!$C$14="All",B77=Dashboard!$C$14),OR(Dashboard!$C$15="All",C77=Dashboard!$C$15),OR(Dashboard!$C$16="All",K77=Dashboard!$C$16)),1,0) -> 1 | S77: =IF(M77=1,ROW()-1,"") -> 76 | T77: IDB | V77: CL4NX Plus Barcode Printer
A78: Obour Institute | B78: FEIG | C78: ID CPR30+ USB | D78: 1 out of 3 | E78: 2265 | F78: =IF(E78="","",D78*E78) -> #VALUE! | G78: 46220 | H78: 21 | I78: =IF(OR(G78="",H78=""),"",G78+H78*7) -> 46367 | J78: Not Paid | K78: Pending | L78: =IF(A78="","",IF(OR(G78="",AND(G78>=Dashboard!$C$18,G78<=Dashboard!$C$19)),1,0)) -> 1 | M78: =IF(AND(L78=1,OR(Dashboard!$C$13="All",A78=Dashboard!$C$13),OR(Dashboard!$C$14="All",B78=Dashboard!$C$14),OR(Dashboard!$C$15="All",C78=Dashboard!$C$15),OR(Dashboard!$C$16="All",K78=Dashboard!$C$16),OR(Dashboard!$C$17="All",J78=Dashboard!$C$17)),1,0) -> 1 | N78: =IF(AND(L78=1,OR(Dashboard!$C$13="All",A78=Dashboard!$C$13),OR(Dashboard!$C$14="All",B78=Dashboard!$C$14),OR(Dashboard!$C$16="All",K78=Dashboard!$C$16),OR(Dashboard!$C$17="All",J78=Dashboard!$C$17)),1,0) -> 1 | O78: =IF(AND(L78=1,OR(Dashboard!$C$13="All",A78=Dashboard!$C$13),OR(Dashboard!$C$15="All",C78=Dashboard!$C$15),OR(Dashboard!$C$16="All",K78=Dashboard!$C$16),OR(Dashboard!$C$17="All",J78=Dashboard!$C$17)),1,0) -> 1 | P78: =IF(AND(L78=1,OR(Dashboard!$C$13="All",A78=Dashboard!$C$13),OR(Dashboard!$C$14="All",B78=Dashboard!$C$14),OR(Dashboard!$C$15="All",C78=Dashboard!$C$15),OR(Dashboard!$C$17="All",J78=Dashboard!$C$17)),1,0) -> 1 | Q78: =IF(AND(L78=1,OR(Dashboard!$C$14="All",B78=Dashboard!$C$14),OR(Dashboard!$C$15="All",C78=Dashboard!$C$15),OR(Dashboard!$C$16="All",K78=Dashboard!$C$16),OR(Dashboard!$C$17="All",J78=Dashboard!$C$17)),1,0) -> 1 | R78: =IF(AND(L78=1,OR(Dashboard!$C$13="All",A78=Dashboard!$C$13),OR(Dashboard!$C$14="All",B78=Dashboard!$C$14),OR(Dashboard!$C$15="All",C78=Dashboard!$C$15),OR(Dashboard!$C$16="All",K78=Dashboard!$C$16)),1,0) -> 1 | S78: =IF(M78=1,ROW()-1,"") -> 77 | T78: Hayat Centric | V78: Cleaning Kit- Smart 1
A79: AUBE | B79: Dipole | C79: Dogbone tags- Pre printed in black&encoded | D79: 9405 | E79: 45 | F79: =IF(E79="","",D79*E79) -> 423225 | G79: 46221 | H79: 18 | I79: =IF(OR(G79="",H79=""),"",G79+H79*7) -> 46347 | J79: Not Paid | K79: Pending | L79: =IF(A79="","",IF(OR(G79="",AND(G79>=Dashboard!$C$18,G79<=Dashboard!$C$19)),1,0)) -> 1 | M79: =IF(AND(L79=1,OR(Dashboard!$C$13="All",A79=Dashboard!$C$13),OR(Dashboard!$C$14="All",B79=Dashboard!$C$14),OR(Dashboard!$C$15="All",C79=Dashboard!$C$15),OR(Dashboard!$C$16="All",K79=Dashboard!$C$16),OR(Dashboard!$C$17="All",J79=Dashboard!$C$17)),1,0) -> 1 | N79: =IF(AND(L79=1,OR(Dashboard!$C$13="All",A79=Dashboard!$C$13),OR(Dashboard!$C$14="All",B79=Dashboard!$C$14),OR(Dashboard!$C$16="All",K79=Dashboard!$C$16),OR(Dashboard!$C$17="All",J79=Dashboard!$C$17)),1,0) -> 1 | O79: =IF(AND(L79=1,OR(Dashboard!$C$13="All",A79=Dashboard!$C$13),OR(Dashboard!$C$15="All",C79=Dashboard!$C$15),OR(Dashboard!$C$16="All",K79=Dashboard!$C$16),OR(Dashboard!$C$17="All",J79=Dashboard!$C$17)),1,0) -> 1 | P79: =IF(AND(L79=1,OR(Dashboard!$C$13="All",A79=Dashboard!$C$13),OR(Dashboard!$C$14="All",B79=Dashboard!$C$14),OR(Dashboard!$C$15="All",C79=Dashboard!$C$15),OR(Dashboard!$C$17="All",J79=Dashboard!$C$17)),1,0) -> 1 | Q79: =IF(AND(L79=1,OR(Dashboard!$C$14="All",B79=Dashboard!$C$14),OR(Dashboard!$C$15="All",C79=Dashboard!$C$15),OR(Dashboard!$C$16="All",K79=Dashboard!$C$16),OR(Dashboard!$C$17="All",J79=Dashboard!$C$17)),1,0) -> 1 | R79: =IF(AND(L79=1,OR(Dashboard!$C$13="All",A79=Dashboard!$C$13),OR(Dashboard!$C$14="All",B79=Dashboard!$C$14),OR(Dashboard!$C$15="All",C79=Dashboard!$C$15),OR(Dashboard!$C$16="All",K79=Dashboard!$C$16)),1,0) -> 1 | S79: =IF(M79=1,ROW()-1,"") -> 78 | T79: Roya | V79: Coaxial 10m
A80: AUBE | B80: Metalcraft | C80: EU Universal tags- Printed | D80: 6820 | E80: 5554 | F80: =IF(E80="","",D80*E80) -> 37878280 | G80: 46222 | H80: 17 | I80: =IF(OR(G80="",H80=""),"",G80+H80*7) -> 46341 | J80: Not Paid | K80: Completed | L80: =IF(A80="","",IF(OR(G80="",AND(G80>=Dashboard!$C$18,G80<=Dashboard!$C$19)),1,0)) -> 1 | M80: =IF(AND(L80=1,OR(Dashboard!$C$13="All",A80=Dashboard!$C$13),OR(Dashboard!$C$14="All",B80=Dashboard!$C$14),OR(Dashboard!$C$15="All",C80=Dashboard!$C$15),OR(Dashboard!$C$16="All",K80=Dashboard!$C$16),OR(Dashboard!$C$17="All",J80=Dashboard!$C$17)),1,0) -> 1 | N80: =IF(AND(L80=1,OR(Dashboard!$C$13="All",A80=Dashboard!$C$13),OR(Dashboard!$C$14="All",B80=Dashboard!$C$14),OR(Dashboard!$C$16="All",K80=Dashboard!$C$16),OR(Dashboard!$C$17="All",J80=Dashboard!$C$17)),1,0) -> 1 | O80: =IF(AND(L80=1,OR(Dashboard!$C$13="All",A80=Dashboard!$C$13),OR(Dashboard!$C$15="All",C80=Dashboard!$C$15),OR(Dashboard!$C$16="All",K80=Dashboard!$C$16),OR(Dashboard!$C$17="All",J80=Dashboard!$C$17)),1,0) -> 1 | P80: =IF(AND(L80=1,OR(Dashboard!$C$13="All",A80=Dashboard!$C$13),OR(Dashboard!$C$14="All",B80=Dashboard!$C$14),OR(Dashboard!$C$15="All",C80=Dashboard!$C$15),OR(Dashboard!$C$17="All",J80=Dashboard!$C$17)),1,0) -> 1 | Q80: =IF(AND(L80=1,OR(Dashboard!$C$14="All",B80=Dashboard!$C$14),OR(Dashboard!$C$15="All",C80=Dashboard!$C$15),OR(Dashboard!$C$16="All",K80=Dashboard!$C$16),OR(Dashboard!$C$17="All",J80=Dashboard!$C$17)),1,0) -> 1 | R80: =IF(AND(L80=1,OR(Dashboard!$C$13="All",A80=Dashboard!$C$13),OR(Dashboard!$C$14="All",B80=Dashboard!$C$14),OR(Dashboard!$C$15="All",C80=Dashboard!$C$15),OR(Dashboard!$C$16="All",K80=Dashboard!$C$16)),1,0) -> 1 | S80: =IF(M80=1,ROW()-1,"") -> 79 | T80: HAP | V80: Coaxial 13m
A81: AUBE | B81: Metalcraft | C81: Destructive windshield tags- Printed | D81: 110 | E81: 41 | F81: =IF(E81="","",D81*E81) -> 4510 | G81: 46223 | H81: 20 | I81: =IF(OR(G81="",H81=""),"",G81+H81*7) -> 46363 | J81: Not Paid | K81: Pending | L81: =IF(A81="","",IF(OR(G81="",AND(G81>=Dashboard!$C$18,G81<=Dashboard!$C$19)),1,0)) -> 1 | M81: =IF(AND(L81=1,OR(Dashboard!$C$13="All",A81=Dashboard!$C$13),OR(Dashboard!$C$14="All",B81=Dashboard!$C$14),OR(Dashboard!$C$15="All",C81=Dashboard!$C$15),OR(Dashboard!$C$16="All",K81=Dashboard!$C$16),OR(Dashboard!$C$17="All",J81=Dashboard!$C$17)),1,0) -> 1 | N81: =IF(AND(L81=1,OR(Dashboard!$C$13="All",A81=Dashboard!$C$13),OR(Dashboard!$C$14="All",B81=Dashboard!$C$14),OR(Dashboard!$C$16="All",K81=Dashboard!$C$16),OR(Dashboard!$C$17="All",J81=Dashboard!$C$17)),1,0) -> 1 | O81: =IF(AND(L81=1,OR(Dashboard!$C$13="All",A81=Dashboard!$C$13),OR(Dashboard!$C$15="All",C81=Dashboard!$C$15),OR(Dashboard!$C$16="All",K81=Dashboard!$C$16),OR(Dashboard!$C$17="All",J81=Dashboard!$C$17)),1,0) -> 1 | P81: =IF(AND(L81=1,OR(Dashboard!$C$13="All",A81=Dashboard!$C$13),OR(Dashboard!$C$14="All",B81=Dashboard!$C$14),OR(Dashboard!$C$15="All",C81=Dashboard!$C$15),OR(Dashboard!$C$17="All",J81=Dashboard!$C$17)),1,0) -> 1 | Q81: =IF(AND(L81=1,OR(Dashboard!$C$14="All",B81=Dashboard!$C$14),OR(Dashboard!$C$15="All",C81=Dashboard!$C$15),OR(Dashboard!$C$16="All",K81=Dashboard!$C$16),OR(Dashboard!$C$17="All",J81=Dashboard!$C$17)),1,0) -> 1 | R81: =IF(AND(L81=1,OR(Dashboard!$C$13="All",A81=Dashboard!$C$13),OR(Dashboard!$C$14="All",B81=Dashboard!$C$14),OR(Dashboard!$C$15="All",C81=Dashboard!$C$15),OR(Dashboard!$C$16="All",K81=Dashboard!$C$16)),1,0) -> 1 | S81: =IF(M81=1,ROW()-1,"") -> 80 | T81: La vista | V81: Coaxial 3m
A82: AUBE | B82: ATID | C82: AT907 | D82: 2 | E82: 231 | F82: =IF(E82="","",D82*E82) -> 462 | G82: 46224 | H82: 20 | I82: =IF(OR(G82="",H82=""),"",G82+H82*7) -> 46364 | J82: Not Paid | K82: In Progress | L82: =IF(A82="","",IF(OR(G82="",AND(G82>=Dashboard!$C$18,G82<=Dashboard!$C$19)),1,0)) -> 1 | M82: =IF(AND(L82=1,OR(Dashboard!$C$13="All",A82=Dashboard!$C$13),OR(Dashboard!$C$14="All",B82=Dashboard!$C$14),OR(Dashboard!$C$15="All",C82=Dashboard!$C$15),OR(Dashboard!$C$16="All",K82=Dashboard!$C$16),OR(Dashboard!$C$17="All",J82=Dashboard!$C$17)),1,0) -> 1 | N82: =IF(AND(L82=1,OR(Dashboard!$C$13="All",A82=Dashboard!$C$13),OR(Dashboard!$C$14="All",B82=Dashboard!$C$14),OR(Dashboard!$C$16="All",K82=Dashboard!$C$16),OR(Dashboard!$C$17="All",J82=Dashboard!$C$17)),1,0) -> 1 | O82: =IF(AND(L82=1,OR(Dashboard!$C$13="All",A82=Dashboard!$C$13),OR(Dashboard!$C$15="All",C82=Dashboard!$C$15),OR(Dashboard!$C$16="All",K82=Dashboard!$C$16),OR(Dashboard!$C$17="All",J82=Dashboard!$C$17)),1,0) -> 1 | P82: =IF(AND(L82=1,OR(Dashboard!$C$13="All",A82=Dashboard!$C$13),OR(Dashboard!$C$14="All",B82=Dashboard!$C$14),OR(Dashboard!$C$15="All",C82=Dashboard!$C$15),OR(Dashboard!$C$17="All",J82=Dashboard!$C$17)),1,0) -> 1 | Q82: =IF(AND(L82=1,OR(Dashboard!$C$14="All",B82=Dashboard!$C$14),OR(Dashboard!$C$15="All",C82=Dashboard!$C$15),OR(Dashboard!$C$16="All",K82=Dashboard!$C$16),OR(Dashboard!$C$17="All",J82=Dashboard!$C$17)),1,0) -> 1 | R82: =IF(AND(L82=1,OR(Dashboard!$C$13="All",A82=Dashboard!$C$13),OR(Dashboard!$C$14="All",B82=Dashboard!$C$14),OR(Dashboard!$C$15="All",C82=Dashboard!$C$15),OR(Dashboard!$C$16="All",K82=Dashboard!$C$16)),1,0) -> 1 | S82: =IF(M82=1,ROW()-1,"") -> 81 | T82: EL Sewedy electric | V82: Coaxial 4m
A83: Lavista | B83: Fusion | C83: Palm Vein F-Pro | D83: 2 | E83: 25 | F83: =IF(E83="","",D83*E83) -> 50 | G83: 46225 | H83: 23 | I83: =IF(OR(G83="",H83=""),"",G83+H83*7) -> 46386 | J83: Not Paid | K83: Completed | L83: =IF(A83="","",IF(OR(G83="",AND(G83>=Dashboard!$C$18,G83<=Dashboard!$C$19)),1,0)) -> 1 | M83: =IF(AND(L83=1,OR(Dashboard!$C$13="All",A83=Dashboard!$C$13),OR(Dashboard!$C$14="All",B83=Dashboard!$C$14),OR(Dashboard!$C$15="All",C83=Dashboard!$C$15),OR(Dashboard!$C$16="All",K83=Dashboard!$C$16),OR(Dashboard!$C$17="All",J83=Dashboard!$C$17)),1,0) -> 1 | N83: =IF(AND(L83=1,OR(Dashboard!$C$13="All",A83=Dashboard!$C$13),OR(Dashboard!$C$14="All",B83=Dashboard!$C$14),OR(Dashboard!$C$16="All",K83=Dashboard!$C$16),OR(Dashboard!$C$17="All",J83=Dashboard!$C$17)),1,0) -> 1 | O83: =IF(AND(L83=1,OR(Dashboard!$C$13="All",A83=Dashboard!$C$13),OR(Dashboard!$C$15="All",C83=Dashboard!$C$15),OR(Dashboard!$C$16="All",K83=Dashboard!$C$16),OR(Dashboard!$C$17="All",J83=Dashboard!$C$17)),1,0) -> 1 | P83: =IF(AND(L83=1,OR(Dashboard!$C$13="All",A83=Dashboard!$C$13),OR(Dashboard!$C$14="All",B83=Dashboard!$C$14),OR(Dashboard!$C$15="All",C83=Dashboard!$C$15),OR(Dashboard!$C$17="All",J83=Dashboard!$C$17)),1,0) -> 1 | Q83: =IF(AND(L83=1,OR(Dashboard!$C$14="All",B83=Dashboard!$C$14),OR(Dashboard!$C$15="All",C83=Dashboard!$C$15),OR(Dashboard!$C$16="All",K83=Dashboard!$C$16),OR(Dashboard!$C$17="All",J83=Dashboard!$C$17)),1,0) -> 1 | R83: =IF(AND(L83=1,OR(Dashboard!$C$13="All",A83=Dashboard!$C$13),OR(Dashboard!$C$14="All",B83=Dashboard!$C$14),OR(Dashboard!$C$15="All",C83=Dashboard!$C$15),OR(Dashboard!$C$16="All",K83=Dashboard!$C$16)),1,0) -> 1 | S83: =IF(M83=1,ROW()-1,"") -> 82 | T83: AlBorouj | V83: Coaxial Cable 20m
A84: Lavista | B84: ATC | C84: Tripode Turnstile | D84: 1 | E84: 245 | F84: =IF(E84="","",D84*E84) -> 245 | G84: 46226 | H84: 24 | I84: =IF(OR(G84="",H84=""),"",G84+H84*7) -> 46394 | J84: Not Paid | K84: Delayed | L84: =IF(A84="","",IF(OR(G84="",AND(G84>=Dashboard!$C$18,G84<=Dashboard!$C$19)),1,0)) -> 1 | M84: =IF(AND(L84=1,OR(Dashboard!$C$13="All",A84=Dashboard!$C$13),OR(Dashboard!$C$14="All",B84=Dashboard!$C$14),OR(Dashboard!$C$15="All",C84=Dashboard!$C$15),OR(Dashboard!$C$16="All",K84=Dashboard!$C$16),OR(Dashboard!$C$17="All",J84=Dashboard!$C$17)),1,0) -> 1 | N84: =IF(AND(L84=1,OR(Dashboard!$C$13="All",A84=Dashboard!$C$13),OR(Dashboard!$C$14="All",B84=Dashboard!$C$14),OR(Dashboard!$C$16="All",K84=Dashboard!$C$16),OR(Dashboard!$C$17="All",J84=Dashboard!$C$17)),1,0) -> 1 | O84: =IF(AND(L84=1,OR(Dashboard!$C$13="All",A84=Dashboard!$C$13),OR(Dashboard!$C$15="All",C84=Dashboard!$C$15),OR(Dashboard!$C$16="All",K84=Dashboard!$C$16),OR(Dashboard!$C$17="All",J84=Dashboard!$C$17)),1,0) -> 1 | P84: =IF(AND(L84=1,OR(Dashboard!$C$13="All",A84=Dashboard!$C$13),OR(Dashboard!$C$14="All",B84=Dashboard!$C$14),OR(Dashboard!$C$15="All",C84=Dashboard!$C$15),OR(Dashboard!$C$17="All",J84=Dashboard!$C$17)),1,0) -> 1 | Q84: =IF(AND(L84=1,OR(Dashboard!$C$14="All",B84=Dashboard!$C$14),OR(Dashboard!$C$15="All",C84=Dashboard!$C$15),OR(Dashboard!$C$16="All",K84=Dashboard!$C$16),OR(Dashboard!$C$17="All",J84=Dashboard!$C$17)),1,0) -> 1 | R84: =IF(AND(L84=1,OR(Dashboard!$C$13="All",A84=Dashboard!$C$13),OR(Dashboard!$C$14="All",B84=Dashboard!$C$14),OR(Dashboard!$C$15="All",C84=Dashboard!$C$15),OR(Dashboard!$C$16="All",K84=Dashboard!$C$16)),1,0) -> 1 | S84: =IF(M84=1,ROW()-1,"") -> 83 | T84: SLR/hap-town | V84: Coaxial Cables
A85: Select | B85: RICH RFID | C85: Jewelry tags | D85: 5000 | E85: 2555 | F85: =IF(E85="","",D85*E85) -> 12775000 | G85: 46227 | H85: 23 | I85: =IF(OR(G85="",H85=""),"",G85+H85*7) -> 46388 | J85: Not Paid | K85: Pending | L85: =IF(A85="","",IF(OR(G85="",AND(G85>=Dashboard!$C$18,G85<=Dashboard!$C$19)),1,0)) -> 1 | M85: =IF(AND(L85=1,OR(Dashboard!$C$13="All",A85=Dashboard!$C$13),OR(Dashboard!$C$14="All",B85=Dashboard!$C$14),OR(Dashboard!$C$15="All",C85=Dashboard!$C$15),OR(Dashboard!$C$16="All",K85=Dashboard!$C$16),OR(Dashboard!$C$17="All",J85=Dashboard!$C$17)),1,0) -> 1 | N85: =IF(AND(L85=1,OR(Dashboard!$C$13="All",A85=Dashboard!$C$13),OR(Dashboard!$C$14="All",B85=Dashboard!$C$14),OR(Dashboard!$C$16="All",K85=Dashboard!$C$16),OR(Dashboard!$C$17="All",J85=Dashboard!$C$17)),1,0) -> 1 | O85: =IF(AND(L85=1,OR(Dashboard!$C$13="All",A85=Dashboard!$C$13),OR(Dashboard!$C$15="All",C85=Dashboard!$C$15),OR(Dashboard!$C$16="All",K85=Dashboard!$C$16),OR(Dashboard!$C$17="All",J85=Dashboard!$C$17)),1,0) -> 1 | P85: =IF(AND(L85=1,OR(Dashboard!$C$13="All",A85=Dashboard!$C$13),OR(Dashboard!$C$14="All",B85=Dashboard!$C$14),OR(Dashboard!$C$15="All",C85=Dashboard!$C$15),OR(Dashboard!$C$17="All",J85=Dashboard!$C$17)),1,0) -> 1 | Q85: =IF(AND(L85=1,OR(Dashboard!$C$14="All",B85=Dashboard!$C$14),OR(Dashboard!$C$15="All",C85=Dashboard!$C$15),OR(Dashboard!$C$16="All",K85=Dashboard!$C$16),OR(Dashboard!$C$17="All",J85=Dashboard!$C$17)),1,0) -> 1 | R85: =IF(AND(L85=1,OR(Dashboard!$C$13="All",A85=Dashboard!$C$13),OR(Dashboard!$C$14="All",B85=Dashboard!$C$14),OR(Dashboard!$C$15="All",C85=Dashboard!$C$15),OR(Dashboard!$C$16="All",K85=Dashboard!$C$16)),1,0) -> 1 | S85: =IF(M85=1,ROW()-1,"") -> 84 | T85: SLG | V85: Condenser
A86: Select | B86: SATO | C86: CT4LX Printer with feeder | D86: 1 | E86: 255 | F86: =IF(E86="","",D86*E86) -> 255 | G86: 46228 | H86: 21 | I86: =IF(OR(G86="",H86=""),"",G86+H86*7) -> 46375 | J86: Not Paid | K86: Pending | L86: =IF(A86="","",IF(OR(G86="",AND(G86>=Dashboard!$C$18,G86<=Dashboard!$C$19)),1,0)) -> 1 | M86: =IF(AND(L86=1,OR(Dashboard!$C$13="All",A86=Dashboard!$C$13),OR(Dashboard!$C$14="All",B86=Dashboard!$C$14),OR(Dashboard!$C$15="All",C86=Dashboard!$C$15),OR(Dashboard!$C$16="All",K86=Dashboard!$C$16),OR(Dashboard!$C$17="All",J86=Dashboard!$C$17)),1,0) -> 1 | N86: =IF(AND(L86=1,OR(Dashboard!$C$13="All",A86=Dashboard!$C$13),OR(Dashboard!$C$14="All",B86=Dashboard!$C$14),OR(Dashboard!$C$16="All",K86=Dashboard!$C$16),OR(Dashboard!$C$17="All",J86=Dashboard!$C$17)),1,0) -> 1 | O86: =IF(AND(L86=1,OR(Dashboard!$C$13="All",A86=Dashboard!$C$13),OR(Dashboard!$C$15="All",C86=Dashboard!$C$15),OR(Dashboard!$C$16="All",K86=Dashboard!$C$16),OR(Dashboard!$C$17="All",J86=Dashboard!$C$17)),1,0) -> 1 | P86: =IF(AND(L86=1,OR(Dashboard!$C$13="All",A86=Dashboard!$C$13),OR(Dashboard!$C$14="All",B86=Dashboard!$C$14),OR(Dashboard!$C$15="All",C86=Dashboard!$C$15),OR(Dashboard!$C$17="All",J86=Dashboard!$C$17)),1,0) -> 1 | Q86: =IF(AND(L86=1,OR(Dashboard!$C$14="All",B86=Dashboard!$C$14),OR(Dashboard!$C$15="All",C86=Dashboard!$C$15),OR(Dashboard!$C$16="All",K86=Dashboard!$C$16),OR(Dashboard!$C$17="All",J86=Dashboard!$C$17)),1,0) -> 1 | R86: =IF(AND(L86=1,OR(Dashboard!$C$13="All",A86=Dashboard!$C$13),OR(Dashboard!$C$14="All",B86=Dashboard!$C$14),OR(Dashboard!$C$15="All",C86=Dashboard!$C$15),OR(Dashboard!$C$16="All",K86=Dashboard!$C$16)),1,0) -> 1 | S86: =IF(M86=1,ROW()-1,"") -> 85 | T86: Sia Lagoon | V86: Control Board
A87: Select | B87: SATO | C87: Ribbons | D87: 2 | E87: 45 | F87: =IF(E87="","",D87*E87) -> 90 | G87: 46229 | H87: 24 | I87: =IF(OR(G87="",H87=""),"",G87+H87*7) -> 46397 | J87: Not Paid | K87: Pending | L87: =IF(A87="","",IF(OR(G87="",AND(G87>=Dashboard!$C$18,G87<=Dashboard!$C$19)),1,0)) -> 1 | M87: =IF(AND(L87=1,OR(Dashboard!$C$13="All",A87=Dashboard!$C$13),OR(Dashboard!$C$14="All",B87=Dashboard!$C$14),OR(Dashboard!$C$15="All",C87=Dashboard!$C$15),OR(Dashboard!$C$16="All",K87=Dashboard!$C$16),OR(Dashboard!$C$17="All",J87=Dashboard!$C$17)),1,0) -> 1 | N87: =IF(AND(L87=1,OR(Dashboard!$C$13="All",A87=Dashboard!$C$13),OR(Dashboard!$C$14="All",B87=Dashboard!$C$14),OR(Dashboard!$C$16="All",K87=Dashboard!$C$16),OR(Dashboard!$C$17="All",J87=Dashboard!$C$17)),1,0) -> 1 | O87: =IF(AND(L87=1,OR(Dashboard!$C$13="All",A87=Dashboard!$C$13),OR(Dashboard!$C$15="All",C87=Dashboard!$C$15),OR(Dashboard!$C$16="All",K87=Dashboard!$C$16),OR(Dashboard!$C$17="All",J87=Dashboard!$C$17)),1,0) -> 1 | P87: =IF(AND(L87=1,OR(Dashboard!$C$13="All",A87=Dashboard!$C$13),OR(Dashboard!$C$14="All",B87=Dashboard!$C$14),OR(Dashboard!$C$15="All",C87=Dashboard!$C$15),OR(Dashboard!$C$17="All",J87=Dashboard!$C$17)),1,0) -> 1 | Q87: =IF(AND(L87=1,OR(Dashboard!$C$14="All",B87=Dashboard!$C$14),OR(Dashboard!$C$15="All",C87=Dashboard!$C$15),OR(Dashboard!$C$16="All",K87=Dashboard!$C$16),OR(Dashboard!$C$17="All",J87=Dashboard!$C$17)),1,0) -> 1 | R87: =IF(AND(L87=1,OR(Dashboard!$C$13="All",A87=Dashboard!$C$13),OR(Dashboard!$C$14="All",B87=Dashboard!$C$14),OR(Dashboard!$C$15="All",C87=Dashboard!$C$15),OR(Dashboard!$C$16="All",K87=Dashboard!$C$16)),1,0) -> 1 | S87: =IF(M87=1,ROW()-1,"") -> 86 | T87: Boyot | V87: Control board for Magnetic Toll
A88: Select | B88: ATID | C88: AT907 | D88: 1 | E88: 36 | F88: =IF(E88="","",D88*E88) -> 36 | G88: 46230 | H88: 22 | I88: =IF(OR(G88="",H88=""),"",G88+H88*7) -> 46384 | J88: Not Paid | K88: Pending | L88: =IF(A88="","",IF(OR(G88="",AND(G88>=Dashboard!$C$18,G88<=Dashboard!$C$19)),1,0)) -> 1 | M88: =IF(AND(L88=1,OR(Dashboard!$C$13="All",A88=Dashboard!$C$13),OR(Dashboard!$C$14="All",B88=Dashboard!$C$14),OR(Dashboard!$C$15="All",C88=Dashboard!$C$15),OR(Dashboard!$C$16="All",K88=Dashboard!$C$16),OR(Dashboard!$C$17="All",J88=Dashboard!$C$17)),1,0) -> 1 | N88: =IF(AND(L88=1,OR(Dashboard!$C$13="All",A88=Dashboard!$C$13),OR(Dashboard!$C$14="All",B88=Dashboard!$C$14),OR(Dashboard!$C$16="All",K88=Dashboard!$C$16),OR(Dashboard!$C$17="All",J88=Dashboard!$C$17)),1,0) -> 1 | O88: =IF(AND(L88=1,OR(Dashboard!$C$13="All",A88=Dashboard!$C$13),OR(Dashboard!$C$15="All",C88=Dashboard!$C$15),OR(Dashboard!$C$16="All",K88=Dashboard!$C$16),OR(Dashboard!$C$17="All",J88=Dashboard!$C$17)),1,0) -> 1 | P88: =IF(AND(L88=1,OR(Dashboard!$C$13="All",A88=Dashboard!$C$13),OR(Dashboard!$C$14="All",B88=Dashboard!$C$14),OR(Dashboard!$C$15="All",C88=Dashboard!$C$15),OR(Dashboard!$C$17="All",J88=Dashboard!$C$17)),1,0) -> 1 | Q88: =IF(AND(L88=1,OR(Dashboard!$C$14="All",B88=Dashboard!$C$14),OR(Dashboard!$C$15="All",C88=Dashboard!$C$15),OR(Dashboard!$C$16="All",K88=Dashboard!$C$16),OR(Dashboard!$C$17="All",J88=Dashboard!$C$17)),1,0) -> 1 | R88: =IF(AND(L88=1,OR(Dashboard!$C$13="All",A88=Dashboard!$C$13),OR(Dashboard!$C$14="All",B88=Dashboard!$C$14),OR(Dashboard!$C$15="All",C88=Dashboard!$C$15),OR(Dashboard!$C$16="All",K88=Dashboard!$C$16)),1,0) -> 1 | S88: =IF(M88=1,ROW()-1,"") -> 87 | T88: Doit | V88: Control Board of Barrier FAAC B614
A89: LoutesTex | B89: SATO | C89: Head Sub for Cl4NX Plus | D89: 2 | E89: 96 | F89: =IF(E89="","",D89*E89) -> 192 | G89: 46231 | H89: 23 | I89: =IF(OR(G89="",H89=""),"",G89+H89*7) -> 46392 | J89: Not Paid | K89: Pending | L89: =IF(A89="","",IF(OR(G89="",AND(G89>=Dashboard!$C$18,G89<=Dashboard!$C$19)),1,0)) -> 1 | M89: =IF(AND(L89=1,OR(Dashboard!$C$13="All",A89=Dashboard!$C$13),OR(Dashboard!$C$14="All",B89=Dashboard!$C$14),OR(Dashboard!$C$15="All",C89=Dashboard!$C$15),OR(Dashboard!$C$16="All",K89=Dashboard!$C$16),OR(Dashboard!$C$17="All",J89=Dashboard!$C$17)),1,0) -> 1 | N89: =IF(AND(L89=1,OR(Dashboard!$C$13="All",A89=Dashboard!$C$13),OR(Dashboard!$C$14="All",B89=Dashboard!$C$14),OR(Dashboard!$C$16="All",K89=Dashboard!$C$16),OR(Dashboard!$C$17="All",J89=Dashboard!$C$17)),1,0) -> 1 | O89: =IF(AND(L89=1,OR(Dashboard!$C$13="All",A89=Dashboard!$C$13),OR(Dashboard!$C$15="All",C89=Dashboard!$C$15),OR(Dashboard!$C$16="All",K89=Dashboard!$C$16),OR(Dashboard!$C$17="All",J89=Dashboard!$C$17)),1,0) -> 1 | P89: =IF(AND(L89=1,OR(Dashboard!$C$13="All",A89=Dashboard!$C$13),OR(Dashboard!$C$14="All",B89=Dashboard!$C$14),OR(Dashboard!$C$15="All",C89=Dashboard!$C$15),OR(Dashboard!$C$17="All",J89=Dashboard!$C$17)),1,0) -> 1 | Q89: =IF(AND(L89=1,OR(Dashboard!$C$14="All",B89=Dashboard!$C$14),OR(Dashboard!$C$15="All",C89=Dashboard!$C$15),OR(Dashboard!$C$16="All",K89=Dashboard!$C$16),OR(Dashboard!$C$17="All",J89=Dashboard!$C$17)),1,0) -> 1 | R89: =IF(AND(L89=1,OR(Dashboard!$C$13="All",A89=Dashboard!$C$13),OR(Dashboard!$C$14="All",B89=Dashboard!$C$14),OR(Dashboard!$C$15="All",C89=Dashboard!$C$15),OR(Dashboard!$C$16="All",K89=Dashboard!$C$16)),1,0) -> 1 | S89: =IF(M89=1,ROW()-1,"") -> 88 | T89: Elsewedy | V89: CT4LX Printer with feeder
A90: LoutesTex | B90: SATO | C90: Platen for Cl4NX Plus | D90: 2 | E90: 8 | F90: =IF(E90="","",D90*E90) -> 16 | G90: 46232 | H90: 21 | I90: =IF(OR(G90="",H90=""),"",G90+H90*7) -> 46379 | J90: Not Paid | K90: Completed | L90: =IF(A90="","",IF(OR(G90="",AND(G90>=Dashboard!$C$18,G90<=Dashboard!$C$19)),1,0)) -> 1 | M90: =IF(AND(L90=1,OR(Dashboard!$C$13="All",A90=Dashboard!$C$13),OR(Dashboard!$C$14="All",B90=Dashboard!$C$14),OR(Dashboard!$C$15="All",C90=Dashboard!$C$15),OR(Dashboard!$C$16="All",K90=Dashboard!$C$16),OR(Dashboard!$C$17="All",J90=Dashboard!$C$17)),1,0) -> 1 | N90: =IF(AND(L90=1,OR(Dashboard!$C$13="All",A90=Dashboard!$C$13),OR(Dashboard!$C$14="All",B90=Dashboard!$C$14),OR(Dashboard!$C$16="All",K90=Dashboard!$C$16),OR(Dashboard!$C$17="All",J90=Dashboard!$C$17)),1,0) -> 1 | O90: =IF(AND(L90=1,OR(Dashboard!$C$13="All",A90=Dashboard!$C$13),OR(Dashboard!$C$15="All",C90=Dashboard!$C$15),OR(Dashboard!$C$16="All",K90=Dashboard!$C$16),OR(Dashboard!$C$17="All",J90=Dashboard!$C$17)),1,0) -> 1 | P90: =IF(AND(L90=1,OR(Dashboard!$C$13="All",A90=Dashboard!$C$13),OR(Dashboard!$C$14="All",B90=Dashboard!$C$14),OR(Dashboard!$C$15="All",C90=Dashboard!$C$15),OR(Dashboard!$C$17="All",J90=Dashboard!$C$17)),1,0) -> 1 | Q90: =IF(AND(L90=1,OR(Dashboard!$C$14="All",B90=Dashboard!$C$14),OR(Dashboard!$C$15="All",C90=Dashboard!$C$15),OR(Dashboard!$C$16="All",K90=Dashboard!$C$16),OR(Dashboard!$C$17="All",J90=Dashboard!$C$17)),1,0) -> 1 | R90: =IF(AND(L90=1,OR(Dashboard!$C$13="All",A90=Dashboard!$C$13),OR(Dashboard!$C$14="All",B90=Dashboard!$C$14),OR(Dashboard!$C$15="All",C90=Dashboard!$C$15),OR(Dashboard!$C$16="All",K90=Dashboard!$C$16)),1,0) -> 1 | S90: =IF(M90=1,ROW()-1,"") -> 89 | T90: Egyptian Steel | V90: Cutter Kit for CL4NX Plus Printer
A91: El Nakheel | C91: GDS410 | D91: 2 | E91: 5 | F91: =IF(E91="","",D91*E91) -> 10 | G91: 46233 | H91: 24 | I91: =IF(OR(G91="",H91=""),"",G91+H91*7) -> 46401 | J91: Not Paid | K91: Pending | L91: =IF(A91="","",IF(OR(G91="",AND(G91>=Dashboard!$C$18,G91<=Dashboard!$C$19)),1,0)) -> 1 | M91: =IF(AND(L91=1,OR(Dashboard!$C$13="All",A91=Dashboard!$C$13),OR(Dashboard!$C$14="All",B91=Dashboard!$C$14),OR(Dashboard!$C$15="All",C91=Dashboard!$C$15),OR(Dashboard!$C$16="All",K91=Dashboard!$C$16),OR(Dashboard!$C$17="All",J91=Dashboard!$C$17)),1,0) -> 1 | N91: =IF(AND(L91=1,OR(Dashboard!$C$13="All",A91=Dashboard!$C$13),OR(Dashboard!$C$14="All",B91=Dashboard!$C$14),OR(Dashboard!$C$16="All",K91=Dashboard!$C$16),OR(Dashboard!$C$17="All",J91=Dashboard!$C$17)),1,0) -> 1 | O91: =IF(AND(L91=1,OR(Dashboard!$C$13="All",A91=Dashboard!$C$13),OR(Dashboard!$C$15="All",C91=Dashboard!$C$15),OR(Dashboard!$C$16="All",K91=Dashboard!$C$16),OR(Dashboard!$C$17="All",J91=Dashboard!$C$17)),1,0) -> 1 | P91: =IF(AND(L91=1,OR(Dashboard!$C$13="All",A91=Dashboard!$C$13),OR(Dashboard!$C$14="All",B91=Dashboard!$C$14),OR(Dashboard!$C$15="All",C91=Dashboard!$C$15),OR(Dashboard!$C$17="All",J91=Dashboard!$C$17)),1,0) -> 1 | Q91: =IF(AND(L91=1,OR(Dashboard!$C$14="All",B91=Dashboard!$C$14),OR(Dashboard!$C$15="All",C91=Dashboard!$C$15),OR(Dashboard!$C$16="All",K91=Dashboard!$C$16),OR(Dashboard!$C$17="All",J91=Dashboard!$C$17)),1,0) -> 1 | R91: =IF(AND(L91=1,OR(Dashboard!$C$13="All",A91=Dashboard!$C$13),OR(Dashboard!$C$14="All",B91=Dashboard!$C$14),OR(Dashboard!$C$15="All",C91=Dashboard!$C$15),OR(Dashboard!$C$16="All",K91=Dashboard!$C$16)),1,0) -> 1 | S91: =IF(M91=1,ROW()-1,"") -> 90 | T91: Heliopollis Residence | V91: Dell OptiPlex 7020
A92: El Nakheel | B92: Local | C92: QR Stands | D92: 2 | E92: 4 | F92: =IF(E92="","",D92*E92) -> 8 | G92: 46234 | H92: 20 | I92: =IF(OR(G92="",H92=""),"",G92+H92*7) -> 46374 | J92: Not Paid | K92: In Progress | L92: =IF(A92="","",IF(OR(G92="",AND(G92>=Dashboard!$C$18,G92<=Dashboard!$C$19)),1,0)) -> 1 | M92: =IF(AND(L92=1,OR(Dashboard!$C$13="All",A92=Dashboard!$C$13),OR(Dashboard!$C$14="All",B92=Dashboard!$C$14),OR(Dashboard!$C$15="All",C92=Dashboard!$C$15),OR(Dashboard!$C$16="All",K92=Dashboard!$C$16),OR(Dashboard!$C$17="All",J92=Dashboard!$C$17)),1,0) -> 1 | N92: =IF(AND(L92=1,OR(Dashboard!$C$13="All",A92=Dashboard!$C$13),OR(Dashboard!$C$14="All",B92=Dashboard!$C$14),OR(Dashboard!$C$16="All",K92=Dashboard!$C$16),OR(Dashboard!$C$17="All",J92=Dashboard!$C$17)),1,0) -> 1 | O92: =IF(AND(L92=1,OR(Dashboard!$C$13="All",A92=Dashboard!$C$13),OR(Dashboard!$C$15="All",C92=Dashboard!$C$15),OR(Dashboard!$C$16="All",K92=Dashboard!$C$16),OR(Dashboard!$C$17="All",J92=Dashboard!$C$17)),1,0) -> 1 | P92: =IF(AND(L92=1,OR(Dashboard!$C$13="All",A92=Dashboard!$C$13),OR(Dashboard!$C$14="All",B92=Dashboard!$C$14),OR(Dashboard!$C$15="All",C92=Dashboard!$C$15),OR(Dashboard!$C$17="All",J92=Dashboard!$C$17)),1,0) -> 1 | Q92: =IF(AND(L92=1,OR(Dashboard!$C$14="All",B92=Dashboard!$C$14),OR(Dashboard!$C$15="All",C92=Dashboard!$C$15),OR(Dashboard!$C$16="All",K92=Dashboard!$C$16),OR(Dashboard!$C$17="All",J92=Dashboard!$C$17)),1,0) -> 1 | R92: =IF(AND(L92=1,OR(Dashboard!$C$13="All",A92=Dashboard!$C$13),OR(Dashboard!$C$14="All",B92=Dashboard!$C$14),OR(Dashboard!$C$15="All",C92=Dashboard!$C$15),OR(Dashboard!$C$16="All",K92=Dashboard!$C$16)),1,0) -> 1 | S92: =IF(M92=1,ROW()-1,"") -> 91 | T92: DOIT | V92: Dest windshield tags
A93: Stone Park | B93: Metalcraft | C93: Dest windshield tags | D93: 3000 | E93: 2 | F93: =IF(E93="","",D93*E93) -> 6000 | G93: 46235 | H93: 16 | I93: =IF(OR(G93="",H93=""),"",G93+H93*7) -> 46347 | J93: Not Paid | K93: Completed | L93: =IF(A93="","",IF(OR(G93="",AND(G93>=Dashboard!$C$18,G93<=Dashboard!$C$19)),1,0)) -> 1 | M93: =IF(AND(L93=1,OR(Dashboard!$C$13="All",A93=Dashboard!$C$13),OR(Dashboard!$C$14="All",B93=Dashboard!$C$14),OR(Dashboard!$C$15="All",C93=Dashboard!$C$15),OR(Dashboard!$C$16="All",K93=Dashboard!$C$16),OR(Dashboard!$C$17="All",J93=Dashboard!$C$17)),1,0) -> 1 | N93: =IF(AND(L93=1,OR(Dashboard!$C$13="All",A93=Dashboard!$C$13),OR(Dashboard!$C$14="All",B93=Dashboard!$C$14),OR(Dashboard!$C$16="All",K93=Dashboard!$C$16),OR(Dashboard!$C$17="All",J93=Dashboard!$C$17)),1,0) -> 1 | O93: =IF(AND(L93=1,OR(Dashboard!$C$13="All",A93=Dashboard!$C$13),OR(Dashboard!$C$15="All",C93=Dashboard!$C$15),OR(Dashboard!$C$16="All",K93=Dashboard!$C$16),OR(Dashboard!$C$17="All",J93=Dashboard!$C$17)),1,0) -> 1 | P93: =IF(AND(L93=1,OR(Dashboard!$C$13="All",A93=Dashboard!$C$13),OR(Dashboard!$C$14="All",B93=Dashboard!$C$14),OR(Dashboard!$C$15="All",C93=Dashboard!$C$15),OR(Dashboard!$C$17="All",J93=Dashboard!$C$17)),1,0) -> 1 | Q93: =IF(AND(L93=1,OR(Dashboard!$C$14="All",B93=Dashboard!$C$14),OR(Dashboard!$C$15="All",C93=Dashboard!$C$15),OR(Dashboard!$C$16="All",K93=Dashboard!$C$16),OR(Dashboard!$C$17="All",J93=Dashboard!$C$17)),1,0) -> 1 | R93: =IF(AND(L93=1,OR(Dashboard!$C$13="All",A93=Dashboard!$C$13),OR(Dashboard!$C$14="All",B93=Dashboard!$C$14),OR(Dashboard!$C$15="All",C93=Dashboard!$C$15),OR(Dashboard!$C$16="All",K93=Dashboard!$C$16)),1,0) -> 1 | S93: =IF(M93=1,ROW()-1,"") -> 92 | T93: The Sovereign Fund of Egypt | V93: Dest windshield tags- Blank
A94: TMG | B94: Metalcraft | C94: Dest windshield tags | D94: 25000 | E94: 36 | F94: =IF(E94="","",D94*E94) -> 900000 | G94: 46236 | H94: 16 | I94: =IF(OR(G94="",H94=""),"",G94+H94*7) -> 46348 | J94: Not Paid | K94: Delayed | L94: =IF(A94="","",IF(OR(G94="",AND(G94>=Dashboard!$C$18,G94<=Dashboard!$C$19)),1,0)) -> 1 | M94: =IF(AND(L94=1,OR(Dashboard!$C$13="All",A94=Dashboard!$C$13),OR(Dashboard!$C$14="All",B94=Dashboard!$C$14),OR(Dashboard!$C$15="All",C94=Dashboard!$C$15),OR(Dashboard!$C$16="All",K94=Dashboard!$C$16),OR(Dashboard!$C$17="All",J94=Dashboard!$C$17)),1,0) -> 1 | N94: =IF(AND(L94=1,OR(Dashboard!$C$13="All",A94=Dashboard!$C$13),OR(Dashboard!$C$14="All",B94=Dashboard!$C$14),OR(Dashboard!$C$16="All",K94=Dashboard!$C$16),OR(Dashboard!$C$17="All",J94=Dashboard!$C$17)),1,0) -> 1 | O94: =IF(AND(L94=1,OR(Dashboard!$C$13="All",A94=Dashboard!$C$13),OR(Dashboard!$C$15="All",C94=Dashboard!$C$15),OR(Dashboard!$C$16="All",K94=Dashboard!$C$16),OR(Dashboard!$C$17="All",J94=Dashboard!$C$17)),1,0) -> 1 | P94: =IF(AND(L94=1,OR(Dashboard!$C$13="All",A94=Dashboard!$C$13),OR(Dashboard!$C$14="All",B94=Dashboard!$C$14),OR(Dashboard!$C$15="All",C94=Dashboard!$C$15),OR(Dashboard!$C$17="All",J94=Dashboard!$C$17)),1,0) -> 1 | Q94: =IF(AND(L94=1,OR(Dashboard!$C$14="All",B94=Dashboard!$C$14),OR(Dashboard!$C$15="All",C94=Dashboard!$C$15),OR(Dashboard!$C$16="All",K94=Dashboard!$C$16),OR(Dashboard!$C$17="All",J94=Dashboard!$C$17)),1,0) -> 1 | R94: =IF(AND(L94=1,OR(Dashboard!$C$13="All",A94=Dashboard!$C$13),OR(Dashboard!$C$14="All",B94=Dashboard!$C$14),OR(Dashboard!$C$15="All",C94=Dashboard!$C$15),OR(Dashboard!$C$16="All",K94=Dashboard!$C$16)),1,0) -> 1 | S94: =IF(M94=1,ROW()-1,"") -> 93 | T94: Venus Jewelry | V94: Dest windshield tags- Blank & Encoding
A95: El-Marwa | B95: RIB | C95: Rapid N-5m | D95: 2 | E95: 2 | F95: =IF(E95="","",D95*E95) -> 4 | G95: 46237 | H95: 19 | I95: =IF(OR(G95="",H95=""),"",G95+H95*7) -> 46370 | J95: Not Paid | K95: Pending | L95: =IF(A95="","",IF(OR(G95="",AND(G95>=Dashboard!$C$18,G95<=Dashboard!$C$19)),1,0)) -> 1 | M95: =IF(AND(L95=1,OR(Dashboard!$C$13="All",A95=Dashboard!$C$13),OR(Dashboard!$C$14="All",B95=Dashboard!$C$14),OR(Dashboard!$C$15="All",C95=Dashboard!$C$15),OR(Dashboard!$C$16="All",K95=Dashboard!$C$16),OR(Dashboard!$C$17="All",J95=Dashboard!$C$17)),1,0) -> 1 | N95: =IF(AND(L95=1,OR(Dashboard!$C$13="All",A95=Dashboard!$C$13),OR(Dashboard!$C$14="All",B95=Dashboard!$C$14),OR(Dashboard!$C$16="All",K95=Dashboard!$C$16),OR(Dashboard!$C$17="All",J95=Dashboard!$C$17)),1,0) -> 1 | O95: =IF(AND(L95=1,OR(Dashboard!$C$13="All",A95=Dashboard!$C$13),OR(Dashboard!$C$15="All",C95=Dashboard!$C$15),OR(Dashboard!$C$16="All",K95=Dashboard!$C$16),OR(Dashboard!$C$17="All",J95=Dashboard!$C$17)),1,0) -> 1 | P95: =IF(AND(L95=1,OR(Dashboard!$C$13="All",A95=Dashboard!$C$13),OR(Dashboard!$C$14="All",B95=Dashboard!$C$14),OR(Dashboard!$C$15="All",C95=Dashboard!$C$15),OR(Dashboard!$C$17="All",J95=Dashboard!$C$17)),1,0) -> 1 | Q95: =IF(AND(L95=1,OR(Dashboard!$C$14="All",B95=Dashboard!$C$14),OR(Dashboard!$C$15="All",C95=Dashboard!$C$15),OR(Dashboard!$C$16="All",K95=Dashboard!$C$16),OR(Dashboard!$C$17="All",J95=Dashboard!$C$17)),1,0) -> 1 | R95: =IF(AND(L95=1,OR(Dashboard!$C$13="All",A95=Dashboard!$C$13),OR(Dashboard!$C$14="All",B95=Dashboard!$C$14),OR(Dashboard!$C$15="All",C95=Dashboard!$C$15),OR(Dashboard!$C$16="All",K95=Dashboard!$C$16)),1,0) -> 1 | S95: =IF(M95=1,ROW()-1,"") -> 94 | T95: Pharma Overseas | V95: Dest windshield tags- Blank- Encoded
A96: El-Marwa | B96: Stock | C96: GDS410 | D96: 6 | E96: 5 | F96: =IF(E96="","",D96*E96) -> 30 | G96: 46238 | H96: 20 | I96: =IF(OR(G96="",H96=""),"",G96+H96*7) -> 46378 | J96: Not Paid | K96: Pending | L96: =IF(A96="","",IF(OR(G96="",AND(G96>=Dashboard!$C$18,G96<=Dashboard!$C$19)),1,0)) -> 1 | M96: =IF(AND(L96=1,OR(Dashboard!$C$13="All",A96=Dashboard!$C$13),OR(Dashboard!$C$14="All",B96=Dashboard!$C$14),OR(Dashboard!$C$15="All",C96=Dashboard!$C$15),OR(Dashboard!$C$16="All",K96=Dashboard!$C$16),OR(Dashboard!$C$17="All",J96=Dashboard!$C$17)),1,0) -> 1 | N96: =IF(AND(L96=1,OR(Dashboard!$C$13="All",A96=Dashboard!$C$13),OR(Dashboard!$C$14="All",B96=Dashboard!$C$14),OR(Dashboard!$C$16="All",K96=Dashboard!$C$16),OR(Dashboard!$C$17="All",J96=Dashboard!$C$17)),1,0) -> 1 | O96: =IF(AND(L96=1,OR(Dashboard!$C$13="All",A96=Dashboard!$C$13),OR(Dashboard!$C$15="All",C96=Dashboard!$C$15),OR(Dashboard!$C$16="All",K96=Dashboard!$C$16),OR(Dashboard!$C$17="All",J96=Dashboard!$C$17)),1,0) -> 1 | P96: =IF(AND(L96=1,OR(Dashboard!$C$13="All",A96=Dashboard!$C$13),OR(Dashboard!$C$14="All",B96=Dashboard!$C$14),OR(Dashboard!$C$15="All",C96=Dashboard!$C$15),OR(Dashboard!$C$17="All",J96=Dashboard!$C$17)),1,0) -> 1 | Q96: =IF(AND(L96=1,OR(Dashboard!$C$14="All",B96=Dashboard!$C$14),OR(Dashboard!$C$15="All",C96=Dashboard!$C$15),OR(Dashboard!$C$16="All",K96=Dashboard!$C$16),OR(Dashboard!$C$17="All",J96=Dashboard!$C$17)),1,0) -> 1 | R96: =IF(AND(L96=1,OR(Dashboard!$C$13="All",A96=Dashboard!$C$13),OR(Dashboard!$C$14="All",B96=Dashboard!$C$14),OR(Dashboard!$C$15="All",C96=Dashboard!$C$15),OR(Dashboard!$C$16="All",K96=Dashboard!$C$16)),1,0) -> 1 | S96: =IF(M96=1,ROW()-1,"") -> 95 | T96: El-Sewedy Electric | V96: Dest windshield tags- printed
A97: Nissan | C97: Magnetic Lock | D97: 1 | E97: 6 | F97: =IF(E97="","",D97*E97) -> 6 | G97: 46239 | H97: 17 | I97: =IF(OR(G97="",H97=""),"",G97+H97*7) -> 46358 | J97: Not Paid | K97: Pending | L97: =IF(A97="","",IF(OR(G97="",AND(G97>=Dashboard!$C$18,G97<=Dashboard!$C$19)),1,0)) -> 1 | M97: =IF(AND(L97=1,OR(Dashboard!$C$13="All",A97=Dashboard!$C$13),OR(Dashboard!$C$14="All",B97=Dashboard!$C$14),OR(Dashboard!$C$15="All",C97=Dashboard!$C$15),OR(Dashboard!$C$16="All",K97=Dashboard!$C$16),OR(Dashboard!$C$17="All",J97=Dashboard!$C$17)),1,0) -> 1 | N97: =IF(AND(L97=1,OR(Dashboard!$C$13="All",A97=Dashboard!$C$13),OR(Dashboard!$C$14="All",B97=Dashboard!$C$14),OR(Dashboard!$C$16="All",K97=Dashboard!$C$16),OR(Dashboard!$C$17="All",J97=Dashboard!$C$17)),1,0) -> 1 | O97: =IF(AND(L97=1,OR(Dashboard!$C$13="All",A97=Dashboard!$C$13),OR(Dashboard!$C$15="All",C97=Dashboard!$C$15),OR(Dashboard!$C$16="All",K97=Dashboard!$C$16),OR(Dashboard!$C$17="All",J97=Dashboard!$C$17)),1,0) -> 1 | P97: =IF(AND(L97=1,OR(Dashboard!$C$13="All",A97=Dashboard!$C$13),OR(Dashboard!$C$14="All",B97=Dashboard!$C$14),OR(Dashboard!$C$15="All",C97=Dashboard!$C$15),OR(Dashboard!$C$17="All",J97=Dashboard!$C$17)),1,0) -> 1 | Q97: =IF(AND(L97=1,OR(Dashboard!$C$14="All",B97=Dashboard!$C$14),OR(Dashboard!$C$15="All",C97=Dashboard!$C$15),OR(Dashboard!$C$16="All",K97=Dashboard!$C$16),OR(Dashboard!$C$17="All",J97=Dashboard!$C$17)),1,0) -> 1 | R97: =IF(AND(L97=1,OR(Dashboard!$C$13="All",A97=Dashboard!$C$13),OR(Dashboard!$C$14="All",B97=Dashboard!$C$14),OR(Dashboard!$C$15="All",C97=Dashboard!$C$15),OR(Dashboard!$C$16="All",K97=Dashboard!$C$16)),1,0) -> 1 | S97: =IF(M97=1,ROW()-1,"") -> 96 | T97: Rooya Group | V97: Dest windshield tags-blank & encoded
A98: Nissan | C98: ZL Bracket | D98: 1 | E98: 7 | F98: =IF(E98="","",D98*E98) -> 7 | G98: 46240 | H98: 20 | I98: =IF(OR(G98="",H98=""),"",G98+H98*7) -> 46380 | J98: Not Paid | K98: Pending | L98: =IF(A98="","",IF(OR(G98="",AND(G98>=Dashboard!$C$18,G98<=Dashboard!$C$19)),1,0)) -> 1 | M98: =IF(AND(L98=1,OR(Dashboard!$C$13="All",A98=Dashboard!$C$13),OR(Dashboard!$C$14="All",B98=Dashboard!$C$14),OR(Dashboard!$C$15="All",C98=Dashboard!$C$15),OR(Dashboard!$C$16="All",K98=Dashboard!$C$16),OR(Dashboard!$C$17="All",J98=Dashboard!$C$17)),1,0) -> 1 | N98: =IF(AND(L98=1,OR(Dashboard!$C$13="All",A98=Dashboard!$C$13),OR(Dashboard!$C$14="All",B98=Dashboard!$C$14),OR(Dashboard!$C$16="All",K98=Dashboard!$C$16),OR(Dashboard!$C$17="All",J98=Dashboard!$C$17)),1,0) -> 1 | O98: =IF(AND(L98=1,OR(Dashboard!$C$13="All",A98=Dashboard!$C$13),OR(Dashboard!$C$15="All",C98=Dashboard!$C$15),OR(Dashboard!$C$16="All",K98=Dashboard!$C$16),OR(Dashboard!$C$17="All",J98=Dashboard!$C$17)),1,0) -> 1 | P98: =IF(AND(L98=1,OR(Dashboard!$C$13="All",A98=Dashboard!$C$13),OR(Dashboard!$C$14="All",B98=Dashboard!$C$14),OR(Dashboard!$C$15="All",C98=Dashboard!$C$15),OR(Dashboard!$C$17="All",J98=Dashboard!$C$17)),1,0) -> 1 | Q98: =IF(AND(L98=1,OR(Dashboard!$C$14="All",B98=Dashboard!$C$14),OR(Dashboard!$C$15="All",C98=Dashboard!$C$15),OR(Dashboard!$C$16="All",K98=Dashboard!$C$16),OR(Dashboard!$C$17="All",J98=Dashboard!$C$17)),1,0) -> 1 | R98: =IF(AND(L98=1,OR(Dashboard!$C$13="All",A98=Dashboard!$C$13),OR(Dashboard!$C$14="All",B98=Dashboard!$C$14),OR(Dashboard!$C$15="All",C98=Dashboard!$C$15),OR(Dashboard!$C$16="All",K98=Dashboard!$C$16)),1,0) -> 1 | S98: =IF(M98=1,ROW()-1,"") -> 97 | T98: Ballah Resort | V98: Destructive Windshield pre
A99: SIDC | B99: RIB | C99: Boom-5m | D99: 1 | E99: 8 | F99: =IF(E99="","",D99*E99) -> 8 | G99: 46241 | H99: 18 | I99: =IF(OR(G99="",H99=""),"",G99+H99*7) -> 46367 | J99: Not Paid | K99: Pending | L99: =IF(A99="","",IF(OR(G99="",AND(G99>=Dashboard!$C$18,G99<=Dashboard!$C$19)),1,0)) -> 1 | M99: =IF(AND(L99=1,OR(Dashboard!$C$13="All",A99=Dashboard!$C$13),OR(Dashboard!$C$14="All",B99=Dashboard!$C$14),OR(Dashboard!$C$15="All",C99=Dashboard!$C$15),OR(Dashboard!$C$16="All",K99=Dashboard!$C$16),OR(Dashboard!$C$17="All",J99=Dashboard!$C$17)),1,0) -> 1 | N99: =IF(AND(L99=1,OR(Dashboard!$C$13="All",A99=Dashboard!$C$13),OR(Dashboard!$C$14="All",B99=Dashboard!$C$14),OR(Dashboard!$C$16="All",K99=Dashboard!$C$16),OR(Dashboard!$C$17="All",J99=Dashboard!$C$17)),1,0) -> 1 | O99: =IF(AND(L99=1,OR(Dashboard!$C$13="All",A99=Dashboard!$C$13),OR(Dashboard!$C$15="All",C99=Dashboard!$C$15),OR(Dashboard!$C$16="All",K99=Dashboard!$C$16),OR(Dashboard!$C$17="All",J99=Dashboard!$C$17)),1,0) -> 1 | P99: =IF(AND(L99=1,OR(Dashboard!$C$13="All",A99=Dashboard!$C$13),OR(Dashboard!$C$14="All",B99=Dashboard!$C$14),OR(Dashboard!$C$15="All",C99=Dashboard!$C$15),OR(Dashboard!$C$17="All",J99=Dashboard!$C$17)),1,0) -> 1 | Q99: =IF(AND(L99=1,OR(Dashboard!$C$14="All",B99=Dashboard!$C$14),OR(Dashboard!$C$15="All",C99=Dashboard!$C$15),OR(Dashboard!$C$16="All",K99=Dashboard!$C$16),OR(Dashboard!$C$17="All",J99=Dashboard!$C$17)),1,0) -> 1 | R99: =IF(AND(L99=1,OR(Dashboard!$C$13="All",A99=Dashboard!$C$13),OR(Dashboard!$C$14="All",B99=Dashboard!$C$14),OR(Dashboard!$C$15="All",C99=Dashboard!$C$15),OR(Dashboard!$C$16="All",K99=Dashboard!$C$16)),1,0) -> 1 | S99: =IF(M99=1,ROW()-1,"") -> 98 | T99: Hay Al Worood | V99: Destructive Windshield pre printed & encoded
A100: Hadayek El Ferdous | B100: FEIG | C100: MRU102-POE | D100: 1 | E100: 2 | F100: =IF(E100="","",D100*E100) -> 2 | G100: 46242 | H100: 20 | I100: =IF(OR(G100="",H100=""),"",G100+H100*7) -> 46382 | J100: Not Paid | K100: Completed | L100: =IF(A100="","",IF(OR(G100="",AND(G100>=Dashboard!$C$18,G100<=Dashboard!$C$19)),1,0)) -> 1 | M100: =IF(AND(L100=1,OR(Dashboard!$C$13="All",A100=Dashboard!$C$13),OR(Dashboard!$C$14="All",B100=Dashboard!$C$14),OR(Dashboard!$C$15="All",C100=Dashboard!$C$15),OR(Dashboard!$C$16="All",K100=Dashboard!$C$16),OR(Dashboard!$C$17="All",J100=Dashboard!$C$17)),1,0) -> 1 | N100: =IF(AND(L100=1,OR(Dashboard!$C$13="All",A100=Dashboard!$C$13),OR(Dashboard!$C$14="All",B100=Dashboard!$C$14),OR(Dashboard!$C$16="All",K100=Dashboard!$C$16),OR(Dashboard!$C$17="All",J100=Dashboard!$C$17)),1,0) -> 1 | O100: =IF(AND(L100=1,OR(Dashboard!$C$13="All",A100=Dashboard!$C$13),OR(Dashboard!$C$15="All",C100=Dashboard!$C$15),OR(Dashboard!$C$16="All",K100=Dashboard!$C$16),OR(Dashboard!$C$17="All",J100=Dashboard!$C$17)),1,0) -> 1 | P100: =IF(AND(L100=1,OR(Dashboard!$C$13="All",A100=Dashboard!$C$13),OR(Dashboard!$C$14="All",B100=Dashboard!$C$14),OR(Dashboard!$C$15="All",C100=Dashboard!$C$15),OR(Dashboard!$C$17="All",J100=Dashboard!$C$17)),1,0) -> 1 | Q100: =IF(AND(L100=1,OR(Dashboard!$C$14="All",B100=Dashboard!$C$14),OR(Dashboard!$C$15="All",C100=Dashboard!$C$15),OR(Dashboard!$C$16="All",K100=Dashboard!$C$16),OR(Dashboard!$C$17="All",J100=Dashboard!$C$17)),1,0) -> 1 | R100: =IF(AND(L100=1,OR(Dashboard!$C$13="All",A100=Dashboard!$C$13),OR(Dashboard!$C$14="All",B100=Dashboard!$C$14),OR(Dashboard!$C$15="All",C100=Dashboard!$C$15),OR(Dashboard!$C$16="All",K100=Dashboard!$C$16)),1,0) -> 1 | S100: =IF(M100=1,ROW()-1,"") -> 99 | T100: Rooya group | V100: Destructive Windshield Tag-printed
A101: Obour institute | B101: ATC | C101: Tripod Turnstile SINGLE UNIT (LTT303A) | D101: 1 | E101: 15 | F101: =IF(E101="","",D101*E101) -> 15 | G101: 46243 | H101: 19 | I101: =IF(OR(G101="",H101=""),"",G101+H101*7) -> 46376 | J101: Not Paid | K101: Pending | L101: =IF(A101="","",IF(OR(G101="",AND(G101>=Dashboard!$C$18,G101<=Dashboard!$C$19)),1,0)) -> 1 | M101: =IF(AND(L101=1,OR(Dashboard!$C$13="All",A101=Dashboard!$C$13),OR(Dashboard!$C$14="All",B101=Dashboard!$C$14),OR(Dashboard!$C$15="All",C101=Dashboard!$C$15),OR(Dashboard!$C$16="All",K101=Dashboard!$C$16),OR(Dashboard!$C$17="All",J101=Dashboard!$C$17)),1,0) -> 1 | N101: =IF(AND(L101=1,OR(Dashboard!$C$13="All",A101=Dashboard!$C$13),OR(Dashboard!$C$14="All",B101=Dashboard!$C$14),OR(Dashboard!$C$16="All",K101=Dashboard!$C$16),OR(Dashboard!$C$17="All",J101=Dashboard!$C$17)),1,0) -> 1 | O101: =IF(AND(L101=1,OR(Dashboard!$C$13="All",A101=Dashboard!$C$13),OR(Dashboard!$C$15="All",C101=Dashboard!$C$15),OR(Dashboard!$C$16="All",K101=Dashboard!$C$16),OR(Dashboard!$C$17="All",J101=Dashboard!$C$17)),1,0) -> 1 | P101: =IF(AND(L101=1,OR(Dashboard!$C$13="All",A101=Dashboard!$C$13),OR(Dashboard!$C$14="All",B101=Dashboard!$C$14),OR(Dashboard!$C$15="All",C101=Dashboard!$C$15),OR(Dashboard!$C$17="All",J101=Dashboard!$C$17)),1,0) -> 1 | Q101: =IF(AND(L101=1,OR(Dashboard!$C$14="All",B101=Dashboard!$C$14),OR(Dashboard!$C$15="All",C101=Dashboard!$C$15),OR(Dashboard!$C$16="All",K101=Dashboard!$C$16),OR(Dashboard!$C$17="All",J101=Dashboard!$C$17)),1,0) -> 1 | R101: =IF(AND(L101=1,OR(Dashboard!$C$13="All",A101=Dashboard!$C$13),OR(Dashboard!$C$14="All",B101=Dashboard!$C$14),OR(Dashboard!$C$15="All",C101=Dashboard!$C$15),OR(Dashboard!$C$16="All",K101=Dashboard!$C$16)),1,0) -> 1 | S101: =IF(M101=1,ROW()-1,"") -> 100 | T101: Shefaa Orman Hospital | V101: Destructive Windshield Tags
A102: Obour institute | B102: FEIG | C102: MAX50.10-RE | D102: 2 | E102: 45 | F102: =IF(E102="","",D102*E102) -> 90 | G102: 46244 | H102: 19 | I102: =IF(OR(G102="",H102=""),"",G102+H102*7) -> 46377 | J102: Not Paid | K102: In Progress | L102: =IF(A102="","",IF(OR(G102="",AND(G102>=Dashboard!$C$18,G102<=Dashboard!$C$19)),1,0)) -> 1 | M102: =IF(AND(L102=1,OR(Dashboard!$C$13="All",A102=Dashboard!$C$13),OR(Dashboard!$C$14="All",B102=Dashboard!$C$14),OR(Dashboard!$C$15="All",C102=Dashboard!$C$15),OR(Dashboard!$C$16="All",K102=Dashboard!$C$16),OR(Dashboard!$C$17="All",J102=Dashboard!$C$17)),1,0) -> 1 | N102: =IF(AND(L102=1,OR(Dashboard!$C$13="All",A102=Dashboard!$C$13),OR(Dashboard!$C$14="All",B102=Dashboard!$C$14),OR(Dashboard!$C$16="All",K102=Dashboard!$C$16),OR(Dashboard!$C$17="All",J102=Dashboard!$C$17)),1,0) -> 1 | O102: =IF(AND(L102=1,OR(Dashboard!$C$13="All",A102=Dashboard!$C$13),OR(Dashboard!$C$15="All",C102=Dashboard!$C$15),OR(Dashboard!$C$16="All",K102=Dashboard!$C$16),OR(Dashboard!$C$17="All",J102=Dashboard!$C$17)),1,0) -> 1 | P102: =IF(AND(L102=1,OR(Dashboard!$C$13="All",A102=Dashboard!$C$13),OR(Dashboard!$C$14="All",B102=Dashboard!$C$14),OR(Dashboard!$C$15="All",C102=Dashboard!$C$15),OR(Dashboard!$C$17="All",J102=Dashboard!$C$17)),1,0) -> 1 | Q102: =IF(AND(L102=1,OR(Dashboard!$C$14="All",B102=Dashboard!$C$14),OR(Dashboard!$C$15="All",C102=Dashboard!$C$15),OR(Dashboard!$C$16="All",K102=Dashboard!$C$16),OR(Dashboard!$C$17="All",J102=Dashboard!$C$17)),1,0) -> 1 | R102: =IF(AND(L102=1,OR(Dashboard!$C$13="All",A102=Dashboard!$C$13),OR(Dashboard!$C$14="All",B102=Dashboard!$C$14),OR(Dashboard!$C$15="All",C102=Dashboard!$C$15),OR(Dashboard!$C$16="All",K102=Dashboard!$C$16)),1,0) -> 1 | S102: =IF(M102=1,ROW()-1,"") -> 101 | T102: Hassan Allam Properties (HQ) | V102: Destructive WINDSHIELD Tags- (New Logo)
A103: Obour university | B103: ATC | C103: Swing Gate (SG 212) | D103: 2 | E103: 24 | F103: =IF(E103="","",D103*E103) -> 48 | G103: 46245 | H103: 20 | I103: =IF(OR(G103="",H103=""),"",G103+H103*7) -> 46385 | J103: Not Paid | K103: Completed | L103: =IF(A103="","",IF(OR(G103="",AND(G103>=Dashboard!$C$18,G103<=Dashboard!$C$19)),1,0)) -> 1 | M103: =IF(AND(L103=1,OR(Dashboard!$C$13="All",A103=Dashboard!$C$13),OR(Dashboard!$C$14="All",B103=Dashboard!$C$14),OR(Dashboard!$C$15="All",C103=Dashboard!$C$15),OR(Dashboard!$C$16="All",K103=Dashboard!$C$16),OR(Dashboard!$C$17="All",J103=Dashboard!$C$17)),1,0) -> 1 | N103: =IF(AND(L103=1,OR(Dashboard!$C$13="All",A103=Dashboard!$C$13),OR(Dashboard!$C$14="All",B103=Dashboard!$C$14),OR(Dashboard!$C$16="All",K103=Dashboard!$C$16),OR(Dashboard!$C$17="All",J103=Dashboard!$C$17)),1,0) -> 1 | O103: =IF(AND(L103=1,OR(Dashboard!$C$13="All",A103=Dashboard!$C$13),OR(Dashboard!$C$15="All",C103=Dashboard!$C$15),OR(Dashboard!$C$16="All",K103=Dashboard!$C$16),OR(Dashboard!$C$17="All",J103=Dashboard!$C$17)),1,0) -> 1 | P103: =IF(AND(L103=1,OR(Dashboard!$C$13="All",A103=Dashboard!$C$13),OR(Dashboard!$C$14="All",B103=Dashboard!$C$14),OR(Dashboard!$C$15="All",C103=Dashboard!$C$15),OR(Dashboard!$C$17="All",J103=Dashboard!$C$17)),1,0) -> 1 | Q103: =IF(AND(L103=1,OR(Dashboard!$C$14="All",B103=Dashboard!$C$14),OR(Dashboard!$C$15="All",C103=Dashboard!$C$15),OR(Dashboard!$C$16="All",K103=Dashboard!$C$16),OR(Dashboard!$C$17="All",J103=Dashboard!$C$17)),1,0) -> 1 | R103: =IF(AND(L103=1,OR(Dashboard!$C$13="All",A103=Dashboard!$C$13),OR(Dashboard!$C$14="All",B103=Dashboard!$C$14),OR(Dashboard!$C$15="All",C103=Dashboard!$C$15),OR(Dashboard!$C$16="All",K103=Dashboard!$C$16)),1,0) -> 1 | S103: =IF(M103=1,ROW()-1,"") -> 102 | T103: Al Baraka Bank | V103: Destructive WINDSHIELD Tags- (Old Logo)
A104: Obour university | B104: FEIG | C104: MAX50.10-RE | D104: 4 | E104: 25 | F104: =IF(E104="","",D104*E104) -> 100 | G104: 46246 | H104: 21 | I104: =IF(OR(G104="",H104=""),"",G104+H104*7) -> 46393 | J104: Not Paid | K104: Delayed | L104: =IF(A104="","",IF(OR(G104="",AND(G104>=Dashboard!$C$18,G104<=Dashboard!$C$19)),1,0)) -> 1 | M104: =IF(AND(L104=1,OR(Dashboard!$C$13="All",A104=Dashboard!$C$13),OR(Dashboard!$C$14="All",B104=Dashboard!$C$14),OR(Dashboard!$C$15="All",C104=Dashboard!$C$15),OR(Dashboard!$C$16="All",K104=Dashboard!$C$16),OR(Dashboard!$C$17="All",J104=Dashboard!$C$17)),1,0) -> 1 | N104: =IF(AND(L104=1,OR(Dashboard!$C$13="All",A104=Dashboard!$C$13),OR(Dashboard!$C$14="All",B104=Dashboard!$C$14),OR(Dashboard!$C$16="All",K104=Dashboard!$C$16),OR(Dashboard!$C$17="All",J104=Dashboard!$C$17)),1,0) -> 1 | O104: =IF(AND(L104=1,OR(Dashboard!$C$13="All",A104=Dashboard!$C$13),OR(Dashboard!$C$15="All",C104=Dashboard!$C$15),OR(Dashboard!$C$16="All",K104=Dashboard!$C$16),OR(Dashboard!$C$17="All",J104=Dashboard!$C$17)),1,0) -> 1 | P104: =IF(AND(L104=1,OR(Dashboard!$C$13="All",A104=Dashboard!$C$13),OR(Dashboard!$C$14="All",B104=Dashboard!$C$14),OR(Dashboard!$C$15="All",C104=Dashboard!$C$15),OR(Dashboard!$C$17="All",J104=Dashboard!$C$17)),1,0) -> 1 | Q104: =IF(AND(L104=1,OR(Dashboard!$C$14="All",B104=Dashboard!$C$14),OR(Dashboard!$C$15="All",C104=Dashboard!$C$15),OR(Dashboard!$C$16="All",K104=Dashboard!$C$16),OR(Dashboard!$C$17="All",J104=Dashboard!$C$17)),1,0) -> 1 | R104: =IF(AND(L104=1,OR(Dashboard!$C$13="All",A104=Dashboard!$C$13),OR(Dashboard!$C$14="All",B104=Dashboard!$C$14),OR(Dashboard!$C$15="All",C104=Dashboard!$C$15),OR(Dashboard!$C$16="All",K104=Dashboard!$C$16)),1,0) -> 1 | S104: =IF(M104=1,ROW()-1,"") -> 103 | T104: EIM Group | V104: Destructive windshield tags- Printed
A105: Tanmyah | C105: Dogbone- printed&encoded | D105: 3000 | E105: 36 | F105: =IF(E105="","",D105*E105) -> 108000 | G105: 46247 | H105: 24 | I105: =IF(OR(G105="",H105=""),"",G105+H105*7) -> 46415 | J105: Not Paid | K105: Pending | L105: =IF(A105="","",IF(OR(G105="",AND(G105>=Dashboard!$C$18,G105<=Dashboard!$C$19)),1,0)) -> 1 | M105: =IF(AND(L105=1,OR(Dashboard!$C$13="All",A105=Dashboard!$C$13),OR(Dashboard!$C$14="All",B105=Dashboard!$C$14),OR(Dashboard!$C$15="All",C105=Dashboard!$C$15),OR(Dashboard!$C$16="All",K105=Dashboard!$C$16),OR(Dashboard!$C$17="All",J105=Dashboard!$C$17)),1,0) -> 1 | N105: =IF(AND(L105=1,OR(Dashboard!$C$13="All",A105=Dashboard!$C$13),OR(Dashboard!$C$14="All",B105=Dashboard!$C$14),OR(Dashboard!$C$16="All",K105=Dashboard!$C$16),OR(Dashboard!$C$17="All",J105=Dashboard!$C$17)),1,0) -> 1 | O105: =IF(AND(L105=1,OR(Dashboard!$C$13="All",A105=Dashboard!$C$13),OR(Dashboard!$C$15="All",C105=Dashboard!$C$15),OR(Dashboard!$C$16="All",K105=Dashboard!$C$16),OR(Dashboard!$C$17="All",J105=Dashboard!$C$17)),1,0) -> 1 | P105: =IF(AND(L105=1,OR(Dashboard!$C$13="All",A105=Dashboard!$C$13),OR(Dashboard!$C$14="All",B105=Dashboard!$C$14),OR(Dashboard!$C$15="All",C105=Dashboard!$C$15),OR(Dashboard!$C$17="All",J105=Dashboard!$C$17)),1,0) -> 1 | Q105: =IF(AND(L105=1,OR(Dashboard!$C$14="All",B105=Dashboard!$C$14),OR(Dashboard!$C$15="All",C105=Dashboard!$C$15),OR(Dashboard!$C$16="All",K105=Dashboard!$C$16),OR(Dashboard!$C$17="All",J105=Dashboard!$C$17)),1,0) -> 1 | R105: =IF(AND(L105=1,OR(Dashboard!$C$13="All",A105=Dashboard!$C$13),OR(Dashboard!$C$14="All",B105=Dashboard!$C$14),OR(Dashboard!$C$15="All",C105=Dashboard!$C$15),OR(Dashboard!$C$16="All",K105=Dashboard!$C$16)),1,0) -> 1 | S105: =IF(M105=1,ROW()-1,"") -> 104 | T105: Mirage City | V105: Destructive Windshield Tags-printed give him 30 tags blank
A106: Tanmyah | B106: RICH RFID | C106: On metal tags- (RCO7012)- printed&encoded | D106: 1500 | E106: 95 | F106: =IF(E106="","",D106*E106) -> 142500 | G106: 46248 | H106: 24 | I106: =IF(OR(G106="",H106=""),"",G106+H106*7) -> 46416 | J106: Not Paid | K106: Completed | L106: =IF(A106="","",IF(OR(G106="",AND(G106>=Dashboard!$C$18,G106<=Dashboard!$C$19)),1,0)) -> 1 | M106: =IF(AND(L106=1,OR(Dashboard!$C$13="All",A106=Dashboard!$C$13),OR(Dashboard!$C$14="All",B106=Dashboard!$C$14),OR(Dashboard!$C$15="All",C106=Dashboard!$C$15),OR(Dashboard!$C$16="All",K106=Dashboard!$C$16),OR(Dashboard!$C$17="All",J106=Dashboard!$C$17)),1,0) -> 1 | N106: =IF(AND(L106=1,OR(Dashboard!$C$13="All",A106=Dashboard!$C$13),OR(Dashboard!$C$14="All",B106=Dashboard!$C$14),OR(Dashboard!$C$16="All",K106=Dashboard!$C$16),OR(Dashboard!$C$17="All",J106=Dashboard!$C$17)),1,0) -> 1 | O106: =IF(AND(L106=1,OR(Dashboard!$C$13="All",A106=Dashboard!$C$13),OR(Dashboard!$C$15="All",C106=Dashboard!$C$15),OR(Dashboard!$C$16="All",K106=Dashboard!$C$16),OR(Dashboard!$C$17="All",J106=Dashboard!$C$17)),1,0) -> 1 | P106: =IF(AND(L106=1,OR(Dashboard!$C$13="All",A106=Dashboard!$C$13),OR(Dashboard!$C$14="All",B106=Dashboard!$C$14),OR(Dashboard!$C$15="All",C106=Dashboard!$C$15),OR(Dashboard!$C$17="All",J106=Dashboard!$C$17)),1,0) -> 1 | Q106: =IF(AND(L106=1,OR(Dashboard!$C$14="All",B106=Dashboard!$C$14),OR(Dashboard!$C$15="All",C106=Dashboard!$C$15),OR(Dashboard!$C$16="All",K106=Dashboard!$C$16),OR(Dashboard!$C$17="All",J106=Dashboard!$C$17)),1,0) -> 1 | R106: =IF(AND(L106=1,OR(Dashboard!$C$13="All",A106=Dashboard!$C$13),OR(Dashboard!$C$14="All",B106=Dashboard!$C$14),OR(Dashboard!$C$15="All",C106=Dashboard!$C$15),OR(Dashboard!$C$16="All",K106=Dashboard!$C$16)),1,0) -> 1 | S106: =IF(M106=1,ROW()-1,"") -> 105 | T106: Hassan Allam Properties (SLG) | V106: Devil 4015 UHF Hard Tag
A107: La Hacienda | B107: Minamark | C107: HF Cards | D107: 500 | E107: 574 | F107: =IF(E107="","",D107*E107) -> 287000 | G107: 46249 | H107: 24 | I107: =IF(OR(G107="",H107=""),"",G107+H107*7) -> 46417 | J107: Not Paid | K107: Pending | L107: =IF(A107="","",IF(OR(G107="",AND(G107>=Dashboard!$C$18,G107<=Dashboard!$C$19)),1,0)) -> 1 | M107: =IF(AND(L107=1,OR(Dashboard!$C$13="All",A107=Dashboard!$C$13),OR(Dashboard!$C$14="All",B107=Dashboard!$C$14),OR(Dashboard!$C$15="All",C107=Dashboard!$C$15),OR(Dashboard!$C$16="All",K107=Dashboard!$C$16),OR(Dashboard!$C$17="All",J107=Dashboard!$C$17)),1,0) -> 1 | N107: =IF(AND(L107=1,OR(Dashboard!$C$13="All",A107=Dashboard!$C$13),OR(Dashboard!$C$14="All",B107=Dashboard!$C$14),OR(Dashboard!$C$16="All",K107=Dashboard!$C$16),OR(Dashboard!$C$17="All",J107=Dashboard!$C$17)),1,0) -> 1 | O107: =IF(AND(L107=1,OR(Dashboard!$C$13="All",A107=Dashboard!$C$13),OR(Dashboard!$C$15="All",C107=Dashboard!$C$15),OR(Dashboard!$C$16="All",K107=Dashboard!$C$16),OR(Dashboard!$C$17="All",J107=Dashboard!$C$17)),1,0) -> 1 | P107: =IF(AND(L107=1,OR(Dashboard!$C$13="All",A107=Dashboard!$C$13),OR(Dashboard!$C$14="All",B107=Dashboard!$C$14),OR(Dashboard!$C$15="All",C107=Dashboard!$C$15),OR(Dashboard!$C$17="All",J107=Dashboard!$C$17)),1,0) -> 1 | Q107: =IF(AND(L107=1,OR(Dashboard!$C$14="All",B107=Dashboard!$C$14),OR(Dashboard!$C$15="All",C107=Dashboard!$C$15),OR(Dashboard!$C$16="All",K107=Dashboard!$C$16),OR(Dashboard!$C$17="All",J107=Dashboard!$C$17)),1,0) -> 1 | R107: =IF(AND(L107=1,OR(Dashboard!$C$13="All",A107=Dashboard!$C$13),OR(Dashboard!$C$14="All",B107=Dashboard!$C$14),OR(Dashboard!$C$15="All",C107=Dashboard!$C$15),OR(Dashboard!$C$16="All",K107=Dashboard!$C$16)),1,0) -> 1 | S107: =IF(M107=1,ROW()-1,"") -> 106 | T107: Hassan allam | V107: Dogbone
A108: Marina | C108: UHF Cards- one side printed | D108: 1000 | E108: 558 | F108: =IF(E108="","",D108*E108) -> 558000 | G108: 46250 | H108: 21 | I108: =IF(OR(G108="",H108=""),"",G108+H108*7) -> 46397 | J108: Not Paid | K108: In Progress | L108: =IF(A108="","",IF(OR(G108="",AND(G108>=Dashboard!$C$18,G108<=Dashboard!$C$19)),1,0)) -> 1 | M108: =IF(AND(L108=1,OR(Dashboard!$C$13="All",A108=Dashboard!$C$13),OR(Dashboard!$C$14="All",B108=Dashboard!$C$14),OR(Dashboard!$C$15="All",C108=Dashboard!$C$15),OR(Dashboard!$C$16="All",K108=Dashboard!$C$16),OR(Dashboard!$C$17="All",J108=Dashboard!$C$17)),1,0) -> 1 | N108: =IF(AND(L108=1,OR(Dashboard!$C$13="All",A108=Dashboard!$C$13),OR(Dashboard!$C$14="All",B108=Dashboard!$C$14),OR(Dashboard!$C$16="All",K108=Dashboard!$C$16),OR(Dashboard!$C$17="All",J108=Dashboard!$C$17)),1,0) -> 1 | O108: =IF(AND(L108=1,OR(Dashboard!$C$13="All",A108=Dashboard!$C$13),OR(Dashboard!$C$15="All",C108=Dashboard!$C$15),OR(Dashboard!$C$16="All",K108=Dashboard!$C$16),OR(Dashboard!$C$17="All",J108=Dashboard!$C$17)),1,0) -> 1 | P108: =IF(AND(L108=1,OR(Dashboard!$C$13="All",A108=Dashboard!$C$13),OR(Dashboard!$C$14="All",B108=Dashboard!$C$14),OR(Dashboard!$C$15="All",C108=Dashboard!$C$15),OR(Dashboard!$C$17="All",J108=Dashboard!$C$17)),1,0) -> 1 | Q108: =IF(AND(L108=1,OR(Dashboard!$C$14="All",B108=Dashboard!$C$14),OR(Dashboard!$C$15="All",C108=Dashboard!$C$15),OR(Dashboard!$C$16="All",K108=Dashboard!$C$16),OR(Dashboard!$C$17="All",J108=Dashboard!$C$17)),1,0) -> 1 | R108: =IF(AND(L108=1,OR(Dashboard!$C$13="All",A108=Dashboard!$C$13),OR(Dashboard!$C$14="All",B108=Dashboard!$C$14),OR(Dashboard!$C$15="All",C108=Dashboard!$C$15),OR(Dashboard!$C$16="All",K108=Dashboard!$C$16)),1,0) -> 1 | S108: =IF(M108=1,ROW()-1,"") -> 107 | T108: 90 AVENUE | V108: dogbone
A109: Marbella | C109: Rapid S- 3m | D109: 2 | E109: 2265 | F109: =IF(E109="","",D109*E109) -> 4530 | G109: 46251 | H109: 20 | I109: =IF(OR(G109="",H109=""),"",G109+H109*7) -> 46391 | J109: Not Paid | K109: Completed | L109: =IF(A109="","",IF(OR(G109="",AND(G109>=Dashboard!$C$18,G109<=Dashboard!$C$19)),1,0)) -> 1 | M109: =IF(AND(L109=1,OR(Dashboard!$C$13="All",A109=Dashboard!$C$13),OR(Dashboard!$C$14="All",B109=Dashboard!$C$14),OR(Dashboard!$C$15="All",C109=Dashboard!$C$15),OR(Dashboard!$C$16="All",K109=Dashboard!$C$16),OR(Dashboard!$C$17="All",J109=Dashboard!$C$17)),1,0) -> 1 | N109: =IF(AND(L109=1,OR(Dashboard!$C$13="All",A109=Dashboard!$C$13),OR(Dashboard!$C$14="All",B109=Dashboard!$C$14),OR(Dashboard!$C$16="All",K109=Dashboard!$C$16),OR(Dashboard!$C$17="All",J109=Dashboard!$C$17)),1,0) -> 1 | O109: =IF(AND(L109=1,OR(Dashboard!$C$13="All",A109=Dashboard!$C$13),OR(Dashboard!$C$15="All",C109=Dashboard!$C$15),OR(Dashboard!$C$16="All",K109=Dashboard!$C$16),OR(Dashboard!$C$17="All",J109=Dashboard!$C$17)),1,0) -> 1 | P109: =IF(AND(L109=1,OR(Dashboard!$C$13="All",A109=Dashboard!$C$13),OR(Dashboard!$C$14="All",B109=Dashboard!$C$14),OR(Dashboard!$C$15="All",C109=Dashboard!$C$15),OR(Dashboard!$C$17="All",J109=Dashboard!$C$17)),1,0) -> 1 | Q109: =IF(AND(L109=1,OR(Dashboard!$C$14="All",B109=Dashboard!$C$14),OR(Dashboard!$C$15="All",C109=Dashboard!$C$15),OR(Dashboard!$C$16="All",K109=Dashboard!$C$16),OR(Dashboard!$C$17="All",J109=Dashboard!$C$17)),1,0) -> 1 | R109: =IF(AND(L109=1,OR(Dashboard!$C$13="All",A109=Dashboard!$C$13),OR(Dashboard!$C$14="All",B109=Dashboard!$C$14),OR(Dashboard!$C$15="All",C109=Dashboard!$C$15),OR(Dashboard!$C$16="All",K109=Dashboard!$C$16)),1,0) -> 1 | S109: =IF(M109=1,ROW()-1,"") -> 108 | T109: SpringNova | V109: Dogbone - blank
A110: Marbella | C110: GDS410 | D110: 2 | E110: 45 | F110: =IF(E110="","",D110*E110) -> 90 | G110: 46252 | H110: 20 | I110: =IF(OR(G110="",H110=""),"",G110+H110*7) -> 46392 | J110: Not Paid | K110: Delayed | L110: =IF(A110="","",IF(OR(G110="",AND(G110>=Dashboard!$C$18,G110<=Dashboard!$C$19)),1,0)) -> 1 | M110: =IF(AND(L110=1,OR(Dashboard!$C$13="All",A110=Dashboard!$C$13),OR(Dashboard!$C$14="All",B110=Dashboard!$C$14),OR(Dashboard!$C$15="All",C110=Dashboard!$C$15),OR(Dashboard!$C$16="All",K110=Dashboard!$C$16),OR(Dashboard!$C$17="All",J110=Dashboard!$C$17)),1,0) -> 1 | N110: =IF(AND(L110=1,OR(Dashboard!$C$13="All",A110=Dashboard!$C$13),OR(Dashboard!$C$14="All",B110=Dashboard!$C$14),OR(Dashboard!$C$16="All",K110=Dashboard!$C$16),OR(Dashboard!$C$17="All",J110=Dashboard!$C$17)),1,0) -> 1 | O110: =IF(AND(L110=1,OR(Dashboard!$C$13="All",A110=Dashboard!$C$13),OR(Dashboard!$C$15="All",C110=Dashboard!$C$15),OR(Dashboard!$C$16="All",K110=Dashboard!$C$16),OR(Dashboard!$C$17="All",J110=Dashboard!$C$17)),1,0) -> 1 | P110: =IF(AND(L110=1,OR(Dashboard!$C$13="All",A110=Dashboard!$C$13),OR(Dashboard!$C$14="All",B110=Dashboard!$C$14),OR(Dashboard!$C$15="All",C110=Dashboard!$C$15),OR(Dashboard!$C$17="All",J110=Dashboard!$C$17)),1,0) -> 1 | Q110: =IF(AND(L110=1,OR(Dashboard!$C$14="All",B110=Dashboard!$C$14),OR(Dashboard!$C$15="All",C110=Dashboard!$C$15),OR(Dashboard!$C$16="All",K110=Dashboard!$C$16),OR(Dashboard!$C$17="All",J110=Dashboard!$C$17)),1,0) -> 1 | R110: =IF(AND(L110=1,OR(Dashboard!$C$13="All",A110=Dashboard!$C$13),OR(Dashboard!$C$14="All",B110=Dashboard!$C$14),OR(Dashboard!$C$15="All",C110=Dashboard!$C$15),OR(Dashboard!$C$16="All",K110=Dashboard!$C$16)),1,0) -> 1 | S110: =IF(M110=1,ROW()-1,"") -> 109 | T110: Sidc | V110: Dogbone blank
A111: Marbella | C111: MRU102-POE | D111: 1 | E111: 5554 | F111: =IF(E111="","",D111*E111) -> 5554 | G111: 46253 | H111: 21 | I111: =IF(OR(G111="",H111=""),"",G111+H111*7) -> 46400 | J111: Not Paid | K111: Pending | L111: =IF(A111="","",IF(OR(G111="",AND(G111>=Dashboard!$C$18,G111<=Dashboard!$C$19)),1,0)) -> 1 | M111: =IF(AND(L111=1,OR(Dashboard!$C$13="All",A111=Dashboard!$C$13),OR(Dashboard!$C$14="All",B111=Dashboard!$C$14),OR(Dashboard!$C$15="All",C111=Dashboard!$C$15),OR(Dashboard!$C$16="All",K111=Dashboard!$C$16),OR(Dashboard!$C$17="All",J111=Dashboard!$C$17)),1,0) -> 1 | N111: =IF(AND(L111=1,OR(Dashboard!$C$13="All",A111=Dashboard!$C$13),OR(Dashboard!$C$14="All",B111=Dashboard!$C$14),OR(Dashboard!$C$16="All",K111=Dashboard!$C$16),OR(Dashboard!$C$17="All",J111=Dashboard!$C$17)),1,0) -> 1 | O111: =IF(AND(L111=1,OR(Dashboard!$C$13="All",A111=Dashboard!$C$13),OR(Dashboard!$C$15="All",C111=Dashboard!$C$15),OR(Dashboard!$C$16="All",K111=Dashboard!$C$16),OR(Dashboard!$C$17="All",J111=Dashboard!$C$17)),1,0) -> 1 | P111: =IF(AND(L111=1,OR(Dashboard!$C$13="All",A111=Dashboard!$C$13),OR(Dashboard!$C$14="All",B111=Dashboard!$C$14),OR(Dashboard!$C$15="All",C111=Dashboard!$C$15),OR(Dashboard!$C$17="All",J111=Dashboard!$C$17)),1,0) -> 1 | Q111: =IF(AND(L111=1,OR(Dashboard!$C$14="All",B111=Dashboard!$C$14),OR(Dashboard!$C$15="All",C111=Dashboard!$C$15),OR(Dashboard!$C$16="All",K111=Dashboard!$C$16),OR(Dashboard!$C$17="All",J111=Dashboard!$C$17)),1,0) -> 1 | R111: =IF(AND(L111=1,OR(Dashboard!$C$13="All",A111=Dashboard!$C$13),OR(Dashboard!$C$14="All",B111=Dashboard!$C$14),OR(Dashboard!$C$15="All",C111=Dashboard!$C$15),OR(Dashboard!$C$16="All",K111=Dashboard!$C$16)),1,0) -> 1 | S111: =IF(M111=1,ROW()-1,"") -> 110 | T111: Hassan Allam (SLR) | V111: dogbone printed
...

Sheet Dashboard
B1: 📊 Project Procurement Tracker Dashboard
B2: Supply Chain Planning & Procurement Insights
B4: 📦 TOTAL QUANTITY | D4: 📄 TOTAL ORDERS | F4: 🏢 SELECTED SUPPLIER | H4: 📁 SELECTED PROJECT | J4: 📅 SELECTED START DATE RANGE
B5: =SUMIFS(Data!D2:D750,Data!M2:M750,1) -> 1299300 | D5: =COUNTIFS(Data!M2:M750,1) -> 566 | F5: =$C$14 -> All | H5: =$C$13 -> All | J5: =TEXT($C$18,"mmm dd")&" - "&TEXT($C$19,"mmm dd, yyyy") -> يناير 01 - ديسمبر 31, 2030
B8: 🔍 Filters
B13: Project Name | C13: All | M13: Quantity by Product
B14: Supplier | C14: All | M14: Category | N14: Quantity
B15: Product | C15: All | M15: TC 56 handheld | N15: =SUMIFS(Data!D2:D750,Data!C2:C750,M15,Data!N2:N750,1) -> 2
B16: Project Status | C16: All | M16: RFD8500 SLED | N16: =SUMIFS(Data!D2:D750,Data!C2:C750,M16,Data!N2:N750,1) -> 0
B17: Payment Status | C17: All | M17: EU Universal tags | N17: =SUMIFS(Data!D2:D750,Data!C2:C750,M17,Data!N2:N750,1) -> 1000
B18: Start Date From | C18: 43831 | M18: Dogbone | N18: =SUMIFS(Data!D2:D750,Data!C2:C750,M18,Data!N2:N750,1) -> 93500
B19: Start Date To | C19: 47848 | M19: FX9600 Reader | N19: =SUMIFS(Data!D2:D750,Data!C2:C750,M19,Data!N2:N750,1) -> 18
M20: AN480 Antenna | N20: =SUMIFS(Data!D2:D750,Data!C2:C750,M20,Data!N2:N750,1) -> 37
M21: Protection cap | N21: =SUMIFS(Data!D2:D750,Data!C2:C750,M21,Data!N2:N750,1) -> 30
B22: 📊 Quantity by Product | F22: 📊 Quantity by Supplier | M22: Antenna Stand | N22: =SUMIFS(Data!D2:D750,Data!C2:C750,M22,Data!N2:N750,1) -> 39
M23: Jewelry tags | N23: =SUMIFS(Data!D2:D750,Data!C2:C750,M23,Data!N2:N750,1) -> 52500
M24: Printer CT4LX | N24: =SUMIFS(Data!D2:D750,Data!C2:C750,M24,Data!N2:N750,1) -> 5
M25: Ribbons | N25: =SUMIFS(Data!D2:D750,Data!C2:C750,M25,Data!N2:N750,1) -> 40
M26: LRU1002 | N26: =SUMIFS(Data!D2:D750,Data!C2:C750,M26,Data!N2:N750,1) -> 39
M27: Antenna | N27: =SUMIFS(Data!D2:D750,Data!C2:C750,M27,Data!N2:N750,1) -> 166
M28: AT907 | N28: =SUMIFS(Data!D2:D750,Data!C2:C750,M28,Data!N2:N750,1) -> 17
M29: RFID Desktop Printer with Feeder- (CT4LX) | N29: =SUMIFS(Data!D2:D750,Data!C2:C750,M29,Data!N2:N750,1) -> 2
M30: Ribbons for the printer | N30: =SUMIFS(Data!D2:D750,Data!C2:C750,M30,Data!N2:N750,1) -> 9
M31: Dogbone tags | N31: =SUMIFS(Data!D2:D750,Data!C2:C750,M31,Data!N2:N750,1) -> 45698
M32: EU Universal tags- Blank | N32: =SUMIFS(Data!D2:D750,Data!C2:C750,M32,Data!N2:N750,1) -> 1069
M33: Hang tags | N33: =SUMIFS(Data!D2:D750,Data!C2:C750,M33,Data!N2:N750,1) -> 447
M34: Dest windshield tags | N34: =SUMIFS(Data!D2:D750,Data!C2:C750,M34,Data!N2:N750,1) -> 37282
M35: MaxU1002 | N35: =SUMIFS(Data!D2:D750,Data!C2:C750,M35,Data!N2:N750,1) -> 1
M36: Antenna 270/270 U | N36: =SUMIFS(Data!D2:D750,Data!C2:C750,M36,Data!N2:N750,1) -> 2
M37: RFID Destructive WINDSHIELD Tags Printed | N37: =SUMIFS(Data!D2:D750,Data!C2:C750,M37,Data!N2:N750,1) -> 50
M38: Sato Printer | N38: =SUMIFS(Data!D2:D750,Data!C2:C750,M38,Data!N2:N750,1) -> 2
M39: Destructive WINDSHIELD Tags- (New Logo) | N39: =SUMIFS(Data!D2:D750,Data!C2:C750,M39,Data!N2:N750,1) -> 2500
M40: Destructive WINDSHIELD Tags- (Old Logo) | N40: =SUMIFS(Data!D2:D750,Data!C2:C750,M40,Data!N2:N750,1) -> 186
M41: Coaxial 4m | N41: =SUMIFS(Data!D2:D750,Data!C2:C750,M41,Data!N2:N750,1) -> 2
M42: Coaxial 3m | N42: =SUMIFS(Data!D2:D750,Data!C2:C750,M42,Data!N2:N750,1) -> 2
M43: Coaxial 10m | N43: =SUMIFS(Data!D2:D750,Data!C2:C750,M43,Data!N2:N750,1) -> 4
M44: Coaxial 13m | N44: =SUMIFS(Data!D2:D750,Data!C2:C750,M44,Data!N2:N750,1) -> 2
M45: FAAC Gate B614- 4m | N45: =SUMIFS(Data!D2:D750,Data!C2:C750,M45,Data!N2:N750,1) -> 2
M46: Control Board of Barrier FAAC B614 | N46: =SUMIFS(Data!D2:D750,Data!C2:C750,M46,Data!N2:N750,1) -> 1
M47: FAAC Boom- 3m | N47: =SUMIFS(Data!D2:D750,Data!C2:C750,M47,Data!N2:N750,1) -> 1
M48: Automatic switch | N48: =SUMIFS(Data!D2:D750,Data!C2:C750,M48,Data!N2:N750,1) -> 1
M49: UHF On metal tags | N49: =SUMIFS(Data!D2:D750,Data!C2:C750,M49,Data!N2:N750,1) -> 3000
M50: Max50.10 | N50: =SUMIFS(Data!D2:D750,Data!C2:C750,M50,Data!N2:N750,1) -> 1
M51: Power reader 24V | N51: =SUMIFS(Data!D2:D750,Data!C2:C750,M51,Data!N2:N750,1) -> 1
M52: Electric lock | N52: =SUMIFS(Data!D2:D750,Data!C2:C750,M52,Data!N2:N750,1) -> 1
M53: Push button | N53: =SUMIFS(Data!D2:D750,Data!C2:C750,M53,Data!N2:N750,1) -> 32
M54: HF Cards | N54: =SUMIFS(Data!D2:D750,Data!C2:C750,M54,Data!N2:N750,1) -> 555
M55: MRU102-POE | N55: =SUMIFS(Data!D2:D750,Data!C2:C750,M55,Data!N2:N750,1) -> 4
M56: spring rubber | N56: =SUMIFS(Data!D2:D750,Data!C2:C750,M56,Data!N2:N750,1) -> 2
M57: Spring blue | N57: =SUMIFS(Data!D2:D750,Data!C2:C750,M57,Data!N2:N750,1) -> 2
M58: Motor body | N58: =SUMIFS(Data!D2:D750,Data!C2:C750,M58,Data!N2:N750,1) -> 1
M59: Limit Switch | N59: =SUMIFS(Data!D2:D750,Data!C2:C750,M59,Data!N2:N750,1) -> 2
M60: HUB | N60: =SUMIFS(Data!D2:D750,Data!C2:C750,M60,Data!N2:N750,1) -> 1
C61: 📊 Quantity by Project Status | H61: 📊 Quantity by Payment Status | M61: Spring Green | N61: =SUMIFS(Data!D2:D750,Data!C2:C750,M61,Data!N2:N750,1) -> 2
M62: Spring Blue | N62: =SUMIFS(Data!D2:D750,Data!C2:C750,M62,Data!N2:N750,1) -> 2
M63: Battary | N63: =SUMIFS(Data!D2:D750,Data!C2:C750,M63,Data!N2:N750,1) -> 1
M64: Adapter and charging cable | N64: =SUMIFS(Data!D2:D750,Data!C2:C750,M64,Data!N2:N750,1) -> 2
M65: Silver Barcode Labels 50mm*25mm Blank 1 Roll includes 1800 labels | N65: =SUMIFS(Data!D2:D750,Data!C2:C750,M65,Data!N2:N750,1) -> 14
M66: Industrial Barcode printer (CL4NX) | N66: =SUMIFS(Data!D2:D750,Data!C2:C750,M66,Data!N2:N750,1) -> 18
M67: MAX.U500I | N67: =SUMIFS(Data!D2:D750,Data!C2:C750,M67,Data!N2:N750,1) -> 36
M68: ANT.U290/290 | N68: =SUMIFS(Data!D2:D750,Data!C2:C750,M68,Data!N2:N750,1) -> 29
M69: RW02.10 | N69: =SUMIFS(Data!D2:D750,Data!C2:C750,M69,Data!N2:N750,1) -> 16
M70: UHF Paper tags- Dogbone- Blank | N70: =SUMIFS(Data!D2:D750,Data!C2:C750,M70,Data!N2:N750,1) -> 100000
M71: UHF Tags for Metal Assets- RCO7011- Blank | N71: =SUMIFS(Data!D2:D750,Data!C2:C750,M71,Data!N2:N750,1) -> 40000
M72: RFID Hard Tag- M-Crown | N72: =SUMIFS(Data!D2:D750,Data!C2:C750,M72,Data!N2:N750,1) -> 2000
M73: Industrial RFID Printer CL4NX Plus | N73: =SUMIFS(Data!D2:D750,Data!C2:C750,M73,Data!N2:N750,1) -> 1
M74: Resin ribbon- Y10110600364 | N74: =SUMIFS(Data!D2:D750,Data!C2:C750,M74,Data!N2:N750,1) -> 6
M75: Handheld- AT907 | N75: =SUMIFS(Data!D2:D750,Data!C2:C750,M75,Data!N2:N750,1) -> 2
M76: ID CPR30+ USB | N76: =SUMIFS(Data!D2:D750,Data!C2:C750,M76,Data!N2:N750,1) -> 0
M77: Dogbone tags- Pre printed in black&encoded | N77: =SUMIFS(Data!D2:D750,Data!C2:C750,M77,Data!N2:N750,1) -> 9405
M78: EU Universal tags- Printed | N78: =SUMIFS(Data!D2:D750,Data!C2:C750,M78,Data!N2:N750,1) -> 24820
M79: Destructive windshield tags- Printed | N79: =SUMIFS(Data!D2:D750,Data!C2:C750,M79,Data!N2:N750,1) -> 110
M80: Palm Vein F-Pro | N80: =SUMIFS(Data!D2:D750,Data!C2:C750,M80,Data!N2:N750,1) -> 2
M81: Tripode Turnstile | N81: =SUMIFS(Data!D2:D750,Data!C2:C750,M81,Data!N2:N750,1) -> 1
M82: CT4LX Printer with feeder | N82: =SUMIFS(Data!D2:D750,Data!C2:C750,M82,Data!N2:N750,1) -> 1
M83: Head Sub for Cl4NX Plus | N83: =SUMIFS(Data!D2:D750,Data!C2:C750,M83,Data!N2:N750,1) -> 2
B84: 📈 Top 10 Projects by Quantity | M84: Platen for Cl4NX Plus | N84: =SUMIFS(Data!D2:D750,Data!C2:C750,M84,Data!N2:N750,1) -> 2
M85: GDS410 | N85: =SUMIFS(Data!D2:D750,Data!C2:C750,M85,Data!N2:N750,1) -> 10
M86: QR Stands | N86: =SUMIFS(Data!D2:D750,Data!C2:C750,M86,Data!N2:N750,1) -> 29
M87: Rapid N-5m | N87: =SUMIFS(Data!D2:D750,Data!C2:C750,M87,Data!N2:N750,1) -> 2
M88: Magnetic Lock | N88: =SUMIFS(Data!D2:D750,Data!C2:C750,M88,Data!N2:N750,1) -> 1
M89: ZL Bracket | N89: =SUMIFS(Data!D2:D750,Data!C2:C750,M89,Data!N2:N750,1) -> 1
M90: Boom-5m | N90: =SUMIFS(Data!D2:D750,Data!C2:C750,M90,Data!N2:N750,1) -> 1
M91: Tripod Turnstile SINGLE UNIT (LTT303A) | N91: =SUMIFS(Data!D2:D750,Data!C2:C750,M91,Data!N2:N750,1) -> 1
M92: MAX50.10-RE | N92: =SUMIFS(Data!D2:D750,Data!C2:C750,M92,Data!N2:N750,1) -> 7
M93: Swing Gate (SG 212) | N93: =SUMIFS(Data!D2:D750,Data!C2:C750,M93,Data!N2:N750,1) -> 2
M94: Dogbone- printed&encoded | N94: =SUMIFS(Data!D2:D750,Data!C2:C750,M94,Data!N2:N750,1) -> 13000
M95: On metal tags- (RCO7012)- printed&encoded | N95: =SUMIFS(Data!D2:D750,Data!C2:C750,M95,Data!N2:N750,1) -> 1500
M96: UHF Cards- one side printed | N96: =SUMIFS(Data!D2:D750,Data!C2:C750,M96,Data!N2:N750,1) -> 1300
M97: Rapid S- 3m | N97: =SUMIFS(Data!D2:D750,Data!C2:C750,M97,Data!N2:N750,1) -> 2
M98: Dest windshield tags- Blank | N98: =SUMIFS(Data!D2:D750,Data!C2:C750,M98,Data!N2:N750,1) -> 1100
M99: Cleaning Kit- Smart 1 | N99: =SUMIFS(Data!D2:D750,Data!C2:C750,M99,Data!N2:N750,1) -> 1
M100: Mini web tags | N100: =SUMIFS(Data!D2:D750,Data!C2:C750,M100,Data!N2:N750,1) -> 2000
M101: LF Cards blank- serial | N101: =SUMIFS(Data!D2:D750,Data!C2:C750,M101,Data!N2:N750,1) -> 300
M102: GDS410 with stand | N102: =SUMIFS(Data!D2:D750,Data!C2:C750,M102,Data!N2:N750,1) -> 2
M103: EU Universal tags- printed | N103: =SUMIFS(Data!D2:D750,Data!C2:C750,M103,Data!N2:N750,1) -> 24820
M104: Rapid S 3m | N104: =SUMIFS(Data!D2:D750,Data!C2:C750,M104,Data!N2:N750,1) -> 1
B105: 📋 Filtered Order Detail | M105: HF Cards- double side printed | N105: =SUMIFS(Data!D2:D750,Data!C2:C750,M105,Data!N2:N750,1) -> 700
B106: Project Name | C106: Supplier | D106: Product | E106: Quantity | F106: Unit Price | G106: Total | H106: Start Date | I106: Project Duration (Weeks) | J106: Deadline | K106: Payment Status | L106: Status | M106: Toshiba B-SX8T Spare Printhead | N106: =SUMIFS(Data!D2:D750,Data!C2:C750,M106,Data!N2:N750,1) -> 1
B107: {=IFERROR(INDEX(Data!$A$2:$A$750,SMALL(Data!$S$2:$S$750,1)),"")} -> FRA | C107: {=IFERROR(IF(INDEX(Data!$B$2:$B$750,SMALL(Data!$S$2:$S$750,1))=0,"",INDEX(Data!$B$2:$B$750,SMALL(Data!$S$2:$S$750,1))),"")} -> Wireless dynamics | D107: {=IFERROR(INDEX(Data!$C$2:$C$750,SMALL(Data!$S$2:$S$750,1)),"")} -> TC 56 handheld | E107: {=IFERROR(IF(INDEX(Data!$D$2:$D$750,SMALL(Data!$S$2:$S$750,1))=0,"",INDEX(Data!$D$2:$D$750,SMALL(Data!$S$2:$S$750,1))),"")} -> 2 | F107: {=IFERROR(IF(INDEX(Data!$E$2:$E$750,SMALL(Data!$S$2:$S$750,1))=0,"",INDEX(Data!$E$2:$E$750,SMALL(Data!$S$2:$S$750,1))),"")} -> 2 | G107: {=IFERROR(INDEX(Data!$F$2:$F$750,SMALL(Data!$S$2:$S$750,1)),"")} -> 4 | H107: {=IFERROR(IF(INDEX(Data!$G$2:$G$750,SMALL(Data!$S$2:$S$750,1))=0,"",INDEX(Data!$G$2:$G$750,SMALL(Data!$S$2:$S$750,1))),"")} -> 46144 | I107: {=IFERROR(IF(INDEX(Data!$H$2:$H$750,SMALL(Data!$S$2:$S$750,1))=0,"",INDEX(Data!$H$2:$H$750,SMALL(Data!$S$2:$S$750,1))),"")} -> 1 | J107: {=IFERROR(INDEX(Data!$I$2:$I$750,SMALL(Data!$S$2:$S$750,1)),"")} -> 46151 | K107: {=IFERROR(INDEX(Data!$J$2:$J$750,SMALL(Data!$S$2:$S$750,1)),"")} -> Not Paid | L107: {=IFERROR(INDEX(Data!$K$2:$K$750,SMALL(Data!$S$2:$S$750,1)),"")} -> Completed | M107: RC2005 Tags | N107: =SUMIFS(Data!D2:D750,Data!C2:C750,M107,Data!N2:N750,1) -> 50000
...
